Workbook

Sheet Theatre
N1: VENUE TOTAL | Q1: PARTNER SPLIT
B2: ***MAJESTIC THEATRE RESULTS*** | N2: MAJESTIC THEATRE | Q2: MTC, Inc. | T2: AEG
B3: Name | C3: Date | D3: Day of the week | E3: Tickets Sold | F3: Venue Capacity | G3: Capacity Rate | H3: Gross Ticket Revenue | I3: Avg. Ticket Price (including TW rebate) | J3: Bar Revenue | K3: Avg sale of alcohol per guest | L3: Band(s) guarantee | M3: % of Gross Ticket Revenue | N3: Gate Settlement Gain/(Loss) | O3: Bar Sales - 100% | P3: Show Gross Proceeds (before COGS, Labor, & Facility Costs) | Q3: Gate Settlement Gain/(Loss) | R3: Bar Sales - 70% | S3: Show Gross Proceeds (before COGS, Labor, & Facility Costs) | T3: Gate Settlement Gain/(Loss) | U3: Bar Sales - 30% | V3: Show Gross Proceeds | W3: INPUT - Total Gate Settlement
B4: TOTALS | E4: =SUM(E7:E108) -> 48058 | F4: =SUM(F7:F108) -> 79903 | H4: =SUM(H7:H108) -> 1567678.5 | J4: =SUM(J7:J108) -> 469010.18 | L4: =SUM(L7:L108) -> 916655.94 | M4: =SUM(M7:M108) -> 53.699747 | N4: =SUM(N7:N108) -> 89341.569 | O4: =SUM(O7:O108) -> 469010.18 | P4: =SUM(P7:P108) -> 558351.75 | Q4: =SUM(Q7:Q108) -> 44670.785 | R4: =SUM(R7:R108) -> 328307.13 | S4: =SUM(S7:S108) -> 372977.91 | ... V4: =SUM(V7:V108) -> 185373.84
B5: AVERAGES | E5: =E4/COUNTA(E7:E108) -> 608.32911 | F5: =F4/COUNTA(F7:F108) -> 1011.4304 | G5: =E4/F4 -> 0.60145426 | H5: =H4/COUNTA(H7:H108) -> 19844.031 | I5: =H4/E4 -> 32.620551 | J5: =J4/COUNTA(J7:J108) -> 5650.7251 | K5: =J4/E4 -> 9.759253 | L5: =L4/COUNTA(L7:L108) -> 11603.24 | M5: =L4/H4 -> 0.58472191 | N5: =N4/COUNTA(N7:N108) -> 1076.4044 | O5: =O4/COUNTA(O7:O108) -> 5650.7251 | P5: =P4/COUNTA(P7:P108) -> 6727.1295 | Q5: =Q4/COUNTA(Q7:Q108) -> 551.49117 | R5: =R4/COUNTA(R7:R108) -> 3955.5075 | S5: =S4/COUNTA(S7:S108) -> 4493.7098 | T5: =T4/COUNTA(T7:T108) -> 551.49117 | U5: =U4/COUNTA(U7:U108) -> 1695.2175 | V5: =V4/COUNTA(V7:V108) -> 2233.4197
A7: 1 | B7: Noname | C7: 43467 | D7: =C7 -> 43467 | E7: 1092 | F7: 1100 | G7: =IFERROR(E7/F7,"") -> 0.99272727 | H7: 34484 | I7: =IFERROR(H7/E7,"") -> 31.578755 | J7: 4600.91 | K7: =IFERROR(J7/E7,"") -> 4.2132875 | L7: 16500 | M7: =L7/H7 -> 0.47848277 | N7: =Q7+T7 -> 11365.64 | O7: =R7+U7 -> 4600.91 | P7: =N7+O7 -> 15966.55 | Q7: =W7*50% -> 5682.82 | R7: =J7*70% -> 3220.637 | S7: =Q7+R7 -> 8903.457 | T7: =Q7 -> 5682.82 | U7: =J7*30% -> 1380.273 | V7: =T7+U7 -> 7063.093 | W7: 11365.64
A8: 2 | B8: Ookay (1) | C8: 43470 | D8: =C8 -> 43470 | E8: 658 | F8: 1100 | G8: =IFERROR(E8/F8,"") -> 0.59818182 | H8: 15822.5 | I8: =IFERROR(H8/E8,"") -> 24.046353 | J8: 9016.06 | K8: =IFERROR(J8/E8,"") -> 13.702219 | L8: 7500 | M8: =L8/H8 -> 0.47400853 | N8: =Q8+T8 -> 1217.2121 | O8: =R8+U8 -> 9016.06 | P8: =N8+O8 -> 10233.272 | Q8: =W8*33.3333% -> 608.60606 | R8: =J8*70% -> 6311.242 | S8: =Q8+R8 -> 6919.8481 | T8: =Q8 -> 608.60606 | U8: =J8*30% -> 2704.818 | V8: =T8+U8 -> 3313.4241 | W8: 1825.82
A9: 3 | B9: Piff the Magic Dragon | C9: 43489 | D9: =C9 -> 43489 | E9: 325 | F9: 400 | G9: =IFERROR(E9/F9,"") -> 0.8125 | H9: 16471 | I9: =IFERROR(H9/E9,"") -> 50.68 | J9: 1563.51 | K9: =IFERROR(J9/E9,"") -> 4.8108 | L9: 6000 | M9: =L9/H9 -> 0.36427661 | N9: =Q9+T9 -> 2128.28 | O9: =R9+U9 -> 1563.51 | P9: =N9+O9 -> 3691.79 | Q9: =W9*50% -> 1064.14 | R9: =J9*70% -> 1094.457 | S9: =Q9+R9 -> 2158.597 | T9: =Q9 -> 1064.14 | U9: =J9*30% -> 469.053 | V9: =T9+U9 -> 1533.193 | W9: 2128.28
A10: 4 | B10: The Amity Affliction | C10: 43491 | D10: =C10 -> 43491 | E10: 1100 | F10: 1100 | G10: =IFERROR(E10/F10,"") -> 1 | H10: 37758 | I10: =IFERROR(H10/E10,"") -> 34.325455 | J10: 12222.24 | K10: =IFERROR(J10/E10,"") -> 11.111127 | L10: 15516.32 | M10: =L10/H10 -> 0.41094126 | N10: =Q10+T10 -> 11019.12 | O10: =R10+U10 -> 12222.24 | P10: =N10+O10 -> 23241.36 | Q10: =W10*50% -> 5509.56 | R10: =J10*70% -> 8555.568 | S10: =Q10+R10 -> 14065.128 | T10: =Q10 -> 5509.56 | U10: =J10*30% -> 3666.672 | V10: =T10+U10 -> 9176.232 | W10: 11019.12
A11: 5 | B11: Nao | C11: 43492 | D11: =C11 -> 43492 | E11: 961 | F11: 1000 | G11: =IFERROR(E11/F11,"") -> 0.961 | H11: 30066.5 | I11: =IFERROR(H11/E11,"") -> 31.286681 | J11: 6018.26 | K11: =IFERROR(J11/E11,"") -> 6.2624974 | L11: 15763.8 | M11: =L11/H11 -> 0.52429781 | N11: =Q11+T11 -> 7719.22 | O11: =R11+U11 -> 6018.26 | P11: =N11+O11 -> 13737.48 | Q11: =W11*50% -> 3859.61 | R11: =J11*70% -> 4212.782 | S11: =Q11+R11 -> 8072.392 | T11: =Q11 -> 3859.61 | U11: =J11*30% -> 1805.478 | V11: =T11+U11 -> 5665.088 | W11: 7719.22
A12: 6 | B12: Spafford | C12: 43498 | D12: =C12 -> 43498 | E12: 499 | F12: 1100 | G12: =IFERROR(E12/F12,"") -> 0.45363636 | H12: 12212.5 | I12: =IFERROR(H12/E12,"") -> 24.473948 | J12: 9715.38 | K12: =IFERROR(J12/E12,"") -> 19.469699 | L12: 5119 | M12: =L12/H12 -> 0.4191607 | N12: =Q12+T12 -> 738.14 | O12: =R12+U12 -> 9715.38 | P12: =N12+O12 -> 10453.52 | Q12: =W12*50% -> 369.07 | R12: =J12*70% -> 6800.766 | S12: =Q12+R12 -> 7169.836 | T12: =Q12 -> 369.07 | U12: =J12*30% -> 2914.614 | V12: =T12+U12 -> 3283.684 | W12: 738.14
A13: 7 | B13: Sharon Van Etten | C13: 43509 | D13: =C13 -> 43509 | E13: 417 | F13: 1000 | G13: =IFERROR(E13/F13,"") -> 0.417 | H13: 12917.5 | I13: =IFERROR(H13/E13,"") -> 30.977218 | J13: 3653.31 | K13: =IFERROR(J13/E13,"") -> 8.7609353 | L13: 8000 | M13: =L13/H13 -> 0.61931488 | N13: =Q13+T13 -> -449.14 | O13: =R13+U13 -> 3653.31 | P13: =N13+O13 -> 3204.17 | Q13: =W13*50% -> -224.57 | R13: =J13*70% -> 2557.317 | S13: =Q13+R13 -> 2332.747 | T13: =Q13 -> -224.57 | U13: =J13*30% -> 1095.993 | V13: =T13+U13 -> 871.423 | W13: -449.14
A14: 8 | B14: Space Jesus (1) | C14: 43511 | D14: =C14 -> 43511 | E14: 1100 | F14: 1100 | G14: =IFERROR(E14/F14,"") -> 1 | H14: 34369 | I14: =IFERROR(H14/E14,"") -> 31.244545 | J14: 11658.7 | K14: =IFERROR(J14/E14,"") -> 10.598818 | L14: 15500 | M14: =L14/H14 -> 0.45098781 | N14: =Q14+T14 -> 7689.7523 | O14: =R14+U14 -> 11658.7 | P14: =N14+O14 -> 19348.452 | Q14: =W14*33.3333% -> 3844.8762 | R14: =J14*70% -> 8161.09 | S14: =Q14+R14 -> 12005.966 | T14: =Q14 -> 3844.8762 | U14: =J14*30% -> 3497.61 | V14: =T14+U14 -> 7342.4862 | W14: 11534.64
A15: 9 | B15: Kurt Vile | C15: 43515 | D15: =C15 -> 43515 | E15: 814 | F15: 1100 | G15: =IFERROR(E15/F15,"") -> 0.74 | H15: 26731 | I15: =IFERROR(H15/E15,"") -> 32.839066 | J15: 10123.62 | K15: =IFERROR(J15/E15,"") -> 12.43688 | L15: 20750 | M15: =L15/H15 -> 0.77625229 | N15: =Q15+T15 -> -380.12 | O15: =R15+U15 -> 10123.62 | P15: =N15+O15 -> 9743.5 | Q15: =W15*50% -> -190.06 | R15: =J15*70% -> 7086.534 | S15: =Q15+R15 -> 6896.474 | T15: =Q15 -> -190.06 | U15: =J15*30% -> 3037.086 | V15: =T15+U15 -> 2847.026 | W15: -380.12
A16: 10 | B16: Yung Gravy | C16: 43519 | D16: =C16 -> 43519 | E16: 1100 | F16: 1100 | G16: =IFERROR(E16/F16,"") -> 1 | H16: 37283 | I16: =IFERROR(H16/E16,"") -> 33.893636 | J16: 3341.27 | K16: =IFERROR(J16/E16,"") -> 3.0375182 | L16: 13556.69 | M16: =L16/H16 -> 0.36361586 | N16: =Q16+T16 -> 13305.32 | O16: =R16+U16 -> 3341.27 | P16: =N16+O16 -> 16646.59 | Q16: =W16*50% -> 6652.66 | R16: =J16*70% -> 2338.889 | S16: =Q16+R16 -> 8991.549 | T16: =Q16 -> 6652.66 | U16: =J16*30% -> 1002.381 | V16: =T16+U16 -> 7655.041 | W16: 13305.32
A17: 11 | B17: Cold Cave | C17: 43524 | D17: =C17 -> 43524 | E17: 224 | F17: 1000 | G17: =IFERROR(E17/F17,"") -> 0.224 | H17: 5844 | I17: =IFERROR(H17/E17,"") -> 26.089286 | J17: 4204.03 | K17: =IFERROR(J17/E17,"") -> 18.767991 | L17: 4350 | M17: =L17/H17 -> 0.74435318 | N17: =Q17+T17 -> -3860.62 | O17: =R17+U17 -> 4204.03 | P17: =N17+O17 -> 343.41 | Q17: =W17*50% -> -1930.31 | R17: =J17*70% -> 2942.821 | S17: =Q17+R17 -> 1012.511 | T17: =Q17 -> -1930.31 | U17: =J17*30% -> 1261.209 | V17: =T17+U17 -> -669.101 | W17: -3860.62
A18: 12 | B18: Jacob Banks | C18: 43525 | D18: =C18 -> 43525 | E18: 397 | F18: 1000 | G18: =IFERROR(E18/F18,"") -> 0.397 | H18: 12868 | I18: =IFERROR(H18/E18,"") -> 32.413098 | J18: 4903.83 | K18: =IFERROR(J18/E18,"") -> 12.352217 | L18: 7500 | M18: =L18/H18 -> 0.58284116 | N18: =Q18+T18 -> -994.08 | O18: =R18+U18 -> 4903.83 | P18: =N18+O18 -> 3909.75 | Q18: =W18*50% -> -497.04 | R18: =J18*70% -> 3432.681 | S18: =Q18+R18 -> 2935.641 | T18: =Q18 -> -497.04 | U18: =J18*30% -> 1471.149 | V18: =T18+U18 -> 974.109 | W18: -994.08
A19: 13 | B19: Wet | C19: 43532 | D19: =C19 -> 43532 | E19: 177 | F19: 1000 | G19: =IFERROR(E19/F19,"") -> 0.177 | H19: 6505.5 | I19: =IFERROR(H19/E19,"") -> 36.754237 | J19: 1960.3 | K19: =IFERROR(J19/E19,"") -> 11.075141 | L19: 12750 | M19: =L19/H19 -> 1.9598801 | N19: =Q19+T19 -> -10669.96 | O19: =R19+U19 -> 1960.3 | P19: =N19+O19 -> -8709.66 | Q19: =W19*50% -> -5334.98 | R19: =J19*70% -> 1372.21 | S19: =Q19+R19 -> -3962.77 | T19: =Q19 -> -5334.98 | U19: =J19*30% -> 588.09 | V19: =T19+U19 -> -4746.89 | W19: -10669.96
A20: 14 | B20: Jonathan McReynolds | C20: 43537 | D20: =C20 -> 43537 | E20: 447 | F20: 1000 | G20: =IFERROR(E20/F20,"") -> 0.447 | H20: 18410 | I20: =IFERROR(H20/E20,"") -> 41.185682 | J20: 223 | K20: =IFERROR(J20/E20,"") -> 0.49888143 | L20: 8000 | M20: =L20/H20 -> 0.43454644 | N20: =Q20+T20 -> -821.52 | O20: =R20+U20 -> 223 | P20: =N20+O20 -> -598.52 | Q20: =W20*50% -> -410.76 | R20: =J20*70% -> 156.1 | S20: =Q20+R20 -> -254.66 | T20: =Q20 -> -410.76 | U20: =J20*30% -> 66.9 | V20: =T20+U20 -> -343.86 | W20: -821.52
A21: 15 | B21: Arkells | C21: 43539 | D21: =C21 -> 43539 | E21: 1100 | F21: 1100 | G21: =IFERROR(E21/F21,"") -> 1 | H21: 27622 | I21: =IFERROR(H21/E21,"") -> 25.110909 | J21: 12845.26 | K21: =IFERROR(J21/E21,"") -> 11.677509 | L21: 9434.76 | M21: =L21/H21 -> 0.34156687 | N21: =Q21+T21 -> 10248.1 | O21: =R21+U21 -> 12845.26 | P21: =N21+O21 -> 23093.36 | Q21: =W21*50% -> 5124.05 | R21: =J21*70% -> 8991.682 | S21: =Q21+R21 -> 14115.732 | T21: =Q21 -> 5124.05 | U21: =J21*30% -> 3853.578 | V21: =T21+U21 -> 8977.628 | W21: 10248.1
A22: 16 | B22: Big Wild (1) | C22: 43547 | D22: =C22 -> 43547 | E22: 1100 | F22: 1100 | G22: =IFERROR(E22/F22,"") -> 1 | H22: 28174 | I22: =IFERROR(H22/E22,"") -> 25.612727 | J22: 13163.96 | K22: =IFERROR(J22/E22,"") -> 11.967236 | L22: 11980.74 | M22: =IFERROR(L22/H22,"") -> 0.425241 | N22: =Q22+T22 -> 6343.1203 | O22: =R22+U22 -> 13163.96 | P22: =N22+O22 -> 19507.08 | Q22: =W22*33.3333% -> 3171.5602 | R22: =J22*70% -> 9214.772 | S22: =Q22+R22 -> 12386.332 | T22: =Q22 -> 3171.5602 | U22: =J22*30% -> 3949.188 | V22: =T22+U22 -> 7120.7482 | W22: 9514.69
A23: 17 | B23: Sunsquabi (1) | C23: 43553 | D23: =C23 -> 43553 | E23: 484 | F23: 1000 | G23: =IFERROR(E23/F23,"") -> 0.484 | H23: 11243.5 | I23: =IFERROR(H23/E23,"") -> 23.230372 | J23: 7293.28 | K23: =IFERROR(J23/E23,"") -> 15.06876 | L23: 6400 | M23: =IFERROR(L23/H23,"") -> 0.56921777 | N23: =Q23+T23 -> -814.06585 | O23: =R23+U23 -> 7293.28 | P23: =N23+O23 -> 6479.2141 | Q23: =W23*33.3333% -> -407.03293 | R23: =J23*70% -> 5105.296 | S23: =Q23+R23 -> 4698.2631 | T23: =Q23 -> -407.03293 | U23: =J23*30% -> 2187.984 | V23: =T23+U23 -> 1780.9511 | W23: -1221.1
A24: 18 | B24: Failure | C24: 43558 | D24: =C24 -> 43558 | E24: 303 | F24: 1100 | G24: =IFERROR(E24/F24,"") -> 0.27545455 | H24: 11740 | I24: =IFERROR(H24/E24,"") -> 38.745875 | J24: 4399.89 | K24: =IFERROR(J24/E24,"") -> 14.521089 | L24: 15000 | M24: =IFERROR(L24/H24,"") -> 1.2776831 | N24: =Q24+T24 -> -9327.55 | O24: =R24+U24 -> 4399.89 | P24: =N24+O24 -> -4927.66 | Q24: =W24*50% -> -4663.775 | R24: =J24*70% -> 3079.923 | S24: =Q24+R24 -> -1583.852 | T24: =Q24 -> -4663.775 | U24: =J24*30% -> 1319.967 | V24: =T24+U24 -> -3343.808 | W24: -9327.55
A25: 19 | B25: Nils Frahm | C25: 43559 | D25: =C25 -> 43559 | E25: 272 | F25: 1100 | G25: =IFERROR(E25/F25,"") -> 0.24727273 | H25: 9684 | I25: =IFERROR(H25/E25,"") -> 35.602941 | J25: 2241.55 | K25: =IFERROR(J25/E25,"") -> 8.2409926 | L25: 16000 | M25: =IFERROR(L25/H25,"") -> 1.6522098 | N25: =Q25+T25 -> -12042.67 | O25: =R25+U25 -> 2241.55 | P25: =N25+O25 -> -9801.12 | Q25: =W25*50% -> -6021.335 | R25: =J25*70% -> 1569.085 | S25: =Q25+R25 -> -4452.25 | T25: =Q25 -> -6021.335 | U25: =J25*30% -> 672.465 | V25: =T25+U25 -> -5348.87 | W25: -12042.67
A26: 20 | B26: Manic Focus (1) | C26: 43561 | D26: =C26 -> 43561 | E26: 402 | F26: 1100 | G26: =IFERROR(E26/F26,"") -> 0.36545455 | H26: 9729.5 | I26: =IFERROR(H26/E26,"") -> 24.202736 | J26: 7276.94 | K26: =IFERROR(J26/E26,"") -> 18.101841 | L26: 7000 | M26: =IFERROR(L26/H26,"") -> 0.71946143 | N26: =Q26+T26 -> -2002.7113 | O26: =R26+U26 -> 7276.94 | P26: =N26+O26 -> 5274.2287 | Q26: =W26*33.3333% -> -1001.3557 | R26: =J26*70% -> 5093.858 | S26: =Q26+R26 -> 4092.5023 | T26: =Q26 -> -1001.3557 | U26: =J26*30% -> 2183.082 | V26: =T26+U26 -> 1181.7263 | W26: -3004.07
A27: 21 | B27: The Driver Era | C27: 43568 | D27: =C27 -> 43568 | E27: 598 | F27: 1100 | G27: =IFERROR(E27/F27,"") -> 0.54363636 | H27: 25609.5 | I27: =IFERROR(H27/E27,"") -> 42.825251 | J27: 2327.56 | K27: =IFERROR(J27/E27,"") -> 3.8922408 | L27: 12750 | M27: =IFERROR(L27/H27,"") -> 0.49786212 | N27: =Q27+T27 -> -349.51 | O27: =R27+U27 -> 2327.56 | P27: =N27+O27 -> 1978.05 | Q27: =W27*50% -> -174.755 | R27: =J27*70% -> 1629.292 | S27: =Q27+R27 -> 1454.537 | T27: =Q27 -> -174.755 | U27: =J27*30% -> 698.268 | V27: =T27+U27 -> 523.513 | W27: -349.51
A28: 22 | B28: Adam Conover [GUARANTEED] | C28: 43569 | D28: =C28 -> 43569 | G28: =IFERROR(E28/F28,"") | J28: 1430.64 | N28: =Q28+T28 -> 0 | O28: =R28+U28 -> 1430.64 | P28: =N28+O28 -> 1430.64 | R28: =J28*70% -> 1001.448 | S28: =Q28+R28 -> 1001.448 | U28: =J28*30% -> 429.192 | V28: =T28+U28 -> 429.192 | W28: 0
A29: 23 | B29: Swmrs | C29: 43571 | D29: =C29 -> 43571 | E29: 367 | F29: 1000 | G29: =IFERROR(E29/F29,"") -> 0.367 | H29: 9083 | I29: =IFERROR(H29/E29,"") -> 24.749319 | J29: 1685.73 | K29: =IFERROR(J29/E29,"") -> 4.5932698 | L29: 7500 | M29: =IFERROR(L29/H29,"") -> 0.82571837 | N29: =Q29+T29 -> -3464.68 | O29: =R29+U29 -> 1685.73 | P29: =N29+O29 -> -1778.95 | Q29: =W29*50% -> -1732.34 | R29: =J29*70% -> 1180.011 | S29: =Q29+R29 -> -552.329 | T29: =Q29 -> -1732.34 | U29: =J29*30% -> 505.719 | V29: =T29+U29 -> -1226.621 | W29: -3464.68
A30: 24 | B30: Sunn O))) [GUARANTEED] | C30: 43573 | D30: =C30 -> 43573 | G30: =IFERROR(E30/F30,"") | J30: 3274.82 | N30: =Q30+T30 -> 0 | O30: =R30+U30 -> 3274.82 | P30: =N30+O30 -> 3274.82 | R30: =J30*70% -> 2292.374 | S30: =Q30+R30 -> 2292.374 | U30: =J30*30% -> 982.446 | V30: =T30+U30 -> 982.446
A31: 25 | B31: Jai Wolf (1) | C31: 43575 | D31: =C31 -> 43575 | E31: 1100 | F31: 1100 | G31: =IFERROR(E31/F31,"") -> 1 | H31: 27840 | I31: =IFERROR(H31/E31,"") -> 25.309091 | J31: 13062.2 | K31: =IFERROR(J31/E31,"") -> 11.874727 | L31: 12318.93 | M31: =IFERROR(L31/H31,"") -> 0.4424903 | N31: =Q31+T31 -> 5084.6216 | O31: =R31+U31 -> 13062.2 | P31: =N31+O31 -> 18146.822 | Q31: =W31*33.3333% -> 2542.3108 | R31: =J31*70% -> 9143.54 | S31: =Q31+R31 -> 11685.851 | T31: =Q31 -> 2542.3108 | U31: =J31*30% -> 3918.66 | V31: =T31+U31 -> 6460.9708 | W31: 7626.94
A32: 26 | B32: Neko Case | C32: 43577 | D32: =C32 -> 43577 | E32: 674 | F32: 1100 | G32: =IFERROR(E32/F32,"") -> 0.61272727 | H32: 24059.5 | I32: =IFERROR(H32/E32,"") -> 35.696588 | J32: 6679.44 | K32: =IFERROR(J32/E32,"") -> 9.9101484 | L32: 19000 | M32: =IFERROR(L32/H32,"") -> 0.78970885 | N32: =Q32+T32 -> -1867.24 | O32: =R32+U32 -> 6679.44 | P32: =N32+O32 -> 4812.2 | Q32: =W32*50% -> -933.62 | R32: =J32*70% -> 4675.608 | S32: =Q32+R32 -> 3741.988 | T32: =Q32 -> -933.62 | U32: =J32*30% -> 2003.832 | V32: =T32+U32 -> 1070.212 | W32: -1867.24
A33: 27 | B33: Bad Suns | C33: 43580 | D33: =C33 -> 43580 | E33: 689 | F33: 1100 | G33: =IFERROR(E33/F33,"") -> 0.62636364 | H33: 19549.5 | I33: =IFERROR(H33/E33,"") -> 28.37373 | J33: 3714.44 | K33: =IFERROR(J33/E33,"") -> 5.3910595 | L33: 15400 | M33: =IFERROR(L33/H33,"") -> 0.78774393 | N33: =Q33+T33 -> -2116.45 | O33: =R33+U33 -> 3714.44 | P33: =N33+O33 -> 1597.99 | Q33: =W33*50% -> -1058.225 | R33: =J33*70% -> 2600.108 | S33: =Q33+R33 -> 1541.883 | T33: =Q33 -> -1058.225 | U33: =J33*30% -> 1114.332 | V33: =T33+U33 -> 56.107 | W33: -2116.45
A34: 28 | B34: Claypool Lennon Delerium | C34: 43582 | D34: =C34 -> 43582 | E34: 1100 | F34: 1100 | G34: =IFERROR(E34/F34,"") -> 1 | H34: 50826 | I34: =IFERROR(H34/E34,"") -> 46.205455 | J34: 14217.94 | K34: =IFERROR(J34/E34,"") -> 12.9254 | L34: 15500 | M34: =IFERROR(L34/H34,"") -> 0.30496203 | N34: =Q34+T34 -> 13945.74 | O34: =R34+U34 -> 14217.94 | P34: =N34+O34 -> 28163.68 | Q34: =W34*50% -> 6972.87 | R34: =J34*70% -> 9952.558 | S34: =Q34+R34 -> 16925.428 | T34: =Q34 -> 6972.87 | U34: =J34*30% -> 4265.382 | V34: =T34+U34 -> 11238.252 | W34: 13945.74
A35: 29 | B35: Ann Marie | C35: 43583 | D35: =C35 -> 43583 | E35: 257 | F35: 1000 | G35: =IFERROR(E35/F35,"") -> 0.257 | H35: 9478 | I35: =IFERROR(H35/E35,"") -> 36.879377 | J35: 1363.61 | K35: =IFERROR(J35/E35,"") -> 5.3058755 | L35: 3900 | M35: =IFERROR(L35/H35,"") -> 0.41147922 | N35: =Q35+T35 -> -2032.41 | O35: =R35+U35 -> 1363.61 | P35: =N35+O35 -> -668.8 | Q35: =W35*50% -> -1016.205 | R35: =J35*70% -> 954.527 | S35: =Q35+R35 -> -61.678 | T35: =Q35 -> -1016.205 | U35: =J35*30% -> 409.083 | V35: =T35+U35 -> -607.122 | W35: -2032.41
A36: 30 | B36: Turnover | C36: 43588 | D36: =C36 -> 43588 | E36: 914 | F36: 1100 | G36: =IFERROR(E36/F36,"") -> 0.83090909 | H36: 28549.5 | I36: =IFERROR(H36/E36,"") -> 31.235777 | J36: 9555.76 | K36: =IFERROR(J36/E36,"") -> 10.45488 | L36: 17500 | M36: =IFERROR(L36/H36,"") -> 0.61297045 | N36: =Q36+T36 -> 3622.75 | O36: =R36+U36 -> 9555.76 | P36: =N36+O36 -> 13178.51 | Q36: =W36*50% -> 1811.375 | R36: =J36*70% -> 6689.032 | S36: =Q36+R36 -> 8500.407 | T36: =Q36 -> 1811.375 | U36: =J36*30% -> 2866.728 | V36: =T36+U36 -> 4678.103 | W36: 3622.75
A37: 31 | B37: Higher Brothers | C37: 43594 | D37: =C37 -> 43594 | E37: 194 | F37: 1000 | G37: =IFERROR(E37/F37,"") -> 0.194 | H37: 8312.5 | I37: =IFERROR(H37/E37,"") -> 42.847938 | J37: 1412.04 | K37: =IFERROR(J37/E37,"") -> 7.2785567 | L37: 10500 | M37: =IFERROR(L37/H37,"") -> 1.2631579 | N37: =Q37+T37 -> -10415.5 | O37: =R37+U37 -> 1412.04 | P37: =N37+O37 -> -9003.46 | Q37: =W37*50% -> -5207.75 | R37: =J37*70% -> 988.428 | S37: =Q37+R37 -> -4219.322 | T37: =Q37 -> -5207.75 | U37: =J37*30% -> 423.612 | V37: =T37+U37 -> -4784.138 | W37: -10415.5
A38: 32 | B38: Andy Black | C38: 43596 | D38: =C38 -> 43596 | E38: 358 | F38: 1100 | G38: =IFERROR(E38/F38,"") -> 0.32545455 | H38: 11466.5 | I38: =IFERROR(H38/E38,"") -> 32.02933 | J38: 1403.19 | K38: =IFERROR(J38/E38,"") -> 3.9195251 | L38: 12150 | M38: =IFERROR(L38/H38,"") -> 1.0596084 | N38: =Q38+T38 -> -8341.48 | O38: =R38+U38 -> 1403.19 | P38: =N38+O38 -> -6938.29 | Q38: =W38*50% -> -4170.74 | R38: =J38*70% -> 982.233 | S38: =Q38+R38 -> -3188.507 | T38: =Q38 -> -4170.74 | U38: =J38*30% -> 420.957 | V38: =T38+U38 -> -3749.783 | W38: -8341.48
A39: 33 | B39: Gretchen Rubin | C39: 43600 | D39: =C39 -> 43600 | E39: 337 | F39: 400 | G39: =IFERROR(E39/F39,"") -> 0.8425 | H39: 16489 | I39: =IFERROR(H39/E39,"") -> 48.928783 | J39: 1249.94 | K39: =IFERROR(J39/E39,"") -> 3.7090208 | L39: 4419.37 | M39: =IFERROR(L39/H39,"") -> 0.26801929 | N39: =Q39+T39 -> 5448.47 | O39: =R39+U39 -> 1249.94 | P39: =N39+O39 -> 6698.41 | Q39: =W39*50% -> 2724.235 | R39: =J39*70% -> 874.958 | S39: =Q39+R39 -> 3599.193 | T39: =Q39 -> 2724.235 | U39: =J39*30% -> 374.982 | V39: =T39+U39 -> 3099.217 | W39: 5448.47
A40: 34 | B40: FKJ (1) | C40: 43601 | D40: =C40 -> 43601 | E40: 1100 | F40: 1100 | G40: =IFERROR(E40/F40,"") -> 1 | H40: 30495 | I40: =IFERROR(H40/E40,"") -> 27.722727 | J40: 13512.85 | K40: =IFERROR(J40/E40,"") -> 12.284409 | L40: 13506.58 | M40: =IFERROR(L40/H40,"") -> 0.4429113 | N40: =Q40+T40 -> 6448.9269 | O40: =R40+U40 -> 13512.85 | P40: =N40+O40 -> 19961.777 | Q40: =W40*33.3333% -> 3224.4634 | R40: =J40*70% -> 9458.995 | S40: =Q40+R40 -> 12683.458 | T40: =Q40 -> 3224.4634 | U40: =J40*30% -> 4053.855 | V40: =T40+U40 -> 7278.3184 | W40: 9673.4 | X40: 9673.4 | Y40: -3224.47
A41: 35 | B41: Movements | C41: 43602 | D41: =C41 -> 43602 | E41: 654 | F41: 1100 | G41: =IFERROR(E41/F41,"") -> 0.59454545 | H41: 17853.5 | I41: =IFERROR(H41/E41,"") -> 27.29893 | J41: 6010.96 | K41: =IFERROR(J41/E41,"") -> 9.1910703 | L41: 12000 | M41: =IFERROR(L41/H41,"") -> 0.67213712 | N41: =Q41+T41 -> 928.94 | O41: =R41+U41 -> 6010.96 | P41: =N41+O41 -> 6939.9 | Q41: =W41*50% -> 464.47 | R41: =J41*70% -> 4207.672 | S41: =Q41+R41 -> 4672.142 | T41: =Q41 -> 464.47 | U41: =J41*30% -> 1803.288 | V41: =T41+U41 -> 2267.758 | W41: 928.94
A42: 36 | B42: Josh Ritter | C42: 43608 | D42: =C42 -> 43608 | E42: 376 | F42: 700 | G42: =IFERROR(E42/F42,"") -> 0.53714286 | H42: 20529 | I42: =IFERROR(H42/E42,"") -> 54.598404 | J42: 3595.4 | K42: =IFERROR(J42/E42,"") -> 9.562234 | L42: 10700 | M42: =IFERROR(L42/H42,"") -> 0.52121389 | N42: =Q42+T42 -> -306.56 | O42: =R42+U42 -> 3595.4 | P42: =N42+O42 -> 3288.84 | Q42: =W42*50% -> -153.28 | R42: =J42*70% -> 2516.78 | S42: =Q42+R42 -> 2363.5 | T42: =Q42 -> -153.28 | U42: =J42*30% -> 1078.62 | V42: =T42+U42 -> 925.34 | W42: -306.56
A43: 37 | B43: Architects | C43: 43609 | D43: =C43 -> 43609 | E43: 1062 | F43: 1100 | G43: =IFERROR(E43/F43,"") -> 0.96545455 | H43: 37289 | I43: =IFERROR(H43/E43,"") -> 35.112053 | J43: 11878.48 | K43: =IFERROR(J43/E43,"") -> 11.185009 | L43: 20000 | M43: =IFERROR(L43/H43,"") -> 0.5363512 | N43: =Q43+T43 -> 8534.98 | O43: =R43+U43 -> 11878.48 | P43: =N43+O43 -> 20413.46 | Q43: =W43*50% -> 4267.49 | R43: =J43*70% -> 8314.936 | S43: =Q43+R43 -> 12582.426 | T43: =Q43 -> 4267.49 | U43: =J43*30% -> 3563.544 | V43: =T43+U43 -> 7831.034 | W43: 8534.98
A44: 38 | B44: Local Natives | C44: 43610 | D44: =C44 -> 43610 | E44: 975 | F44: 1100 | G44: =IFERROR(E44/F44,"") -> 0.88636364 | H44: 34714.5 | I44: =IFERROR(H44/E44,"") -> 35.604615 | J44: 11836.7 | K44: =IFERROR(J44/E44,"") -> 12.140205 | L44: 23000 | M44: =IFERROR(L44/H44,"") -> 0.66254735 | N44: =Q44+T44 -> 4144.53 | O44: =R44+U44 -> 11836.7 | P44: =N44+O44 -> 15981.23 | Q44: =W44*50% -> 2072.265 | R44: =J44*70% -> 8285.69 | S44: =Q44+R44 -> 10357.955 | T44: =Q44 -> 2072.265 | U44: =J44*30% -> 3551.01 | V44: =T44+U44 -> 5623.275 | W44: 4144.53
A45: 39 | B45: Basement | C45: 43611 | D45: =C45 -> 43611 | E45: 224 | F45: 1000 | G45: =IFERROR(E45/F45,"") -> 0.224 | H45: 5351 | I45: =IFERROR(H45/E45,"") -> 23.888393 | J45: 1954.47 | K45: =IFERROR(J45/E45,"") -> 8.7253125 | L45: 8000 | M45: =IFERROR(L45/H45,"") -> 1.4950477 | N45: =Q45+T45 -> -7771.41 | O45: =R45+U45 -> 1954.47 | P45: =N45+O45 -> -5816.94 | Q45: =W45*50% -> -3885.705 | R45: =J45*70% -> 1368.129 | S45: =Q45+R45 -> -2517.576 | T45: =Q45 -> -3885.705 | U45: =J45*30% -> 586.341 | V45: =T45+U45 -> -3299.364 | W45: -7771.41
A46: 40 | B46: Chromatics | C46: 43612 | D46: =C46 -> 43612 | E46: 407 | F46: 1000 | G46: =IFERROR(E46/F46,"") -> 0.407 | H46: 12665.5 | I46: =IFERROR(H46/E46,"") -> 31.119165 | J46: 3846.65 | K46: =IFERROR(J46/E46,"") -> 9.4512285 | L46: 9450 | M46: =IFERROR(L46/H46,"") -> 0.74612135 | N46: =Q46+T46 -> -2512.56 | O46: =R46+U46 -> 3846.65 | P46: =N46+O46 -> 1334.09 | Q46: =W46*50% -> -1256.28 | R46: =J46*70% -> 2692.655 | S46: =Q46+R46 -> 1436.375 | T46: =Q46 -> -1256.28 | U46: =J46*30% -> 1153.995 | V46: =T46+U46 -> -102.285 | W46: -2512.56
A47: 41 | B47: Aly & AJ | C47: 43614 | D47: =C47 -> 43614 | E47: 610 | F47: 1000 | G47: =IFERROR(E47/F47,"") -> 0.61 | H47: 23024.5 | I47: =IFERROR(H47/E47,"") -> 37.745082 | J47: 3634.1 | K47: =IFERROR(J47/E47,"") -> 5.957541 | L47: 12400 | M47: =IFERROR(L47/H47,"") -> 0.53855675 | N47: =Q47+T47 -> 616.57 | O47: =R47+U47 -> 3634.1 | P47: =N47+O47 -> 4250.67 | Q47: =W47*50% -> 308.285 | R47: =J47*70% -> 2543.87 | S47: =Q47+R47 -> 2852.155 | T47: =Q47 -> 308.285 | U47: =J47*30% -> 1090.23 | V47: =T47+U47 -> 1398.515 | W47: 616.57
A48: 42 | B48: The Strumbellas | C48: 43620 | D48: =C48 -> 43620 | E48: 646 | F48: 1100 | G48: =IFERROR(E48/F48,"") -> 0.58727273 | H48: 20182 | I48: =IFERROR(H48/E48,"") -> 31.241486 | J48: 7715.76 | K48: =IFERROR(J48/E48,"") -> 11.943901 | L48: 15500 | M48: =IFERROR(L48/H48,"") -> 0.7680111 | N48: =Q48+T48 -> -1060.74 | O48: =R48+U48 -> 7715.76 | P48: =N48+O48 -> 6655.02 | Q48: =W48*50% -> -530.37 | R48: =J48*70% -> 5401.032 | S48: =Q48+R48 -> 4870.662 | T48: =Q48 -> -530.37 | U48: =J48*30% -> 2314.728 | V48: =T48+U48 -> 1784.358 | W48: -1060.74
A49: 43 | B49: Josh Garrels | C49: 43625 | D49: =C49 -> 43625 | E49: 506 | F49: 1100 | G49: =IFERROR(E49/F49,"") -> 0.46 | H49: 16336.5 | I49: =IFERROR(H49/E49,"") -> 32.285573 | J49: 1801.56 | K49: =IFERROR(J49/E49,"") -> 3.5603953 | L49: 6697.9 | M49: =IFERROR(L49/H49,"") -> 0.40999602 | N49: =Q49+T49 -> 4354.21 | O49: =R49+U49 -> 1801.56 | P49: =N49+O49 -> 6155.77 | Q49: =W49*50% -> 2177.105 | R49: =J49*70% -> 1261.092 | S49: =Q49+R49 -> 3438.197 | T49: =Q49 -> 2177.105 | U49: =J49*30% -> 540.468 | V49: =T49+U49 -> 2717.573 | W49: 4354.21
A50: 44 | B50: Tank and the Bangas | C50: 43629 | D50: =C50 -> 43629 | E50: 636 | F50: 1100 | G50: =IFERROR(E50/F50,"") -> 0.57818182 | H50: 16363 | I50: =IFERROR(H50/E50,"") -> 25.727987 | J50: 5675.97 | K50: =IFERROR(J50/E50,"") -> 8.9244811 | L50: 15000 | M50: =IFERROR(L50/H50,"") -> 0.91670232 | N50: =Q50+T50 -> -4177.18 | O50: =R50+U50 -> 5675.97 | P50: =N50+O50 -> 1498.79 | Q50: =W50*50% -> -2088.59 | R50: =J50*70% -> 3973.179 | S50: =Q50+R50 -> 1884.589 | T50: =Q50 -> -2088.59 | U50: =J50*30% -> 1702.791 | V50: =T50+U50 -> -385.799 | W50: -4177.18
A51: 45 | B51: Citizen | C51: 43631 | D51: =C51 -> 43631 | E51: 594 | F51: 1100 | G51: =IFERROR(E51/F51,"") -> 0.54 | H51: 17509.5 | I51: =IFERROR(H51/E51,"") -> 29.477273 | J51: 5160.11 | K51: =IFERROR(J51/E51,"") -> 8.6870539 | L51: 12000 | M51: =IFERROR(L51/H51,"") -> 0.68534224 | N51: =Q51+T51 -> -551.97 | O51: =R51+U51 -> 5160.11 | P51: =N51+O51 -> 4608.14 | Q51: =W51*50% -> -275.985 | R51: =J51*70% -> 3612.077 | S51: =Q51+R51 -> 3336.092 | T51: =Q51 -> -275.985 | U51: =J51*30% -> 1548.033 | V51: =T51+U51 -> 1272.048 | W51: -551.97
A52: 46 | B52: lovelytheband | C52: 43637 | D52: =C52 -> 43637 | E52: 589 | F52: 1100 | G52: =IFERROR(E52/F52,"") -> 0.53545455 | H52: 18608.5 | I52: =IFERROR(H52/E52,"") -> 31.593379 | J52: 4829.49 | K52: =IFERROR(J52/E52,"") -> 8.1994737 | L52: 9350 | M52: =IFERROR(L52/H52,"") -> 0.50245855 | N52: =Q52+T52 -> 686.48 | O52: =R52+U52 -> 4829.49 | P52: =N52+O52 -> 5515.97 | Q52: =W52*50% -> 343.24 | R52: =J52*70% -> 3380.643 | S52: =Q52+R52 -> 3723.883 | T52: =Q52 -> 343.24 | U52: =J52*30% -> 1448.847 | V52: =T52+U52 -> 1792.087 | W52: 686.48
A53: 47 | B53: Feed Me (1) | C53: 43638 | D53: =C53 -> 43638 | E53: 474 | F53: 1100 | G53: =IFERROR(E53/F53,"") -> 0.43090909 | H53: 13860.5 | I53: =IFERROR(H53/E53,"") -> 29.241561 | J53: 5530.14 | K53: =IFERROR(J53/E53,"") -> 11.666962 | L53: 14000 | M53: =IFERROR(L53/H53,"") -> 1.0100646 | N53: =Q53+T53 -> -4231.9062 | O53: =R53+U53 -> 5530.14 | P53: =N53+O53 -> 1298.2338 | Q53: =W53*33.33333% -> -2115.9531 | R53: =J53*70% -> 3871.098 | S53: =Q53+R53 -> 1755.1449 | T53: =Q53 -> -2115.9531 | U53: =J53*30% -> 1659.042 | V53: =T53+U53 -> -456.91112 | W53: -6347.86
A54: 48 | B54: Wine and Crime (podcast) | C54: 43639 | D54: =C54 -> 43639 | E54: 196 | F54: 400 | G54: =IFERROR(E54/F54,"") -> 0.49 | H54: 7478.5 | I54: =IFERROR(H54/E54,"") -> 38.155612 | J54: 2329.4 | K54: =IFERROR(J54/E54,"") -> 11.884694 | L54: 2000 | M54: =IFERROR(L54/H54,"") -> 0.26743331 | N54: =Q54+T54 -> 573.34 | O54: =R54+U54 -> 2329.4 | P54: =N54+O54 -> 2902.74 | Q54: =W54*50% -> 286.67 | R54: =J54*70% -> 1630.58 | S54: =Q54+R54 -> 1917.25 | T54: =Q54 -> 286.67 | U54: =J54*30% -> 698.82 | V54: =T54+U54 -> 985.49 | W54: 573.34
A55: 49 | B55: Chon | C55: 43643 | D55: =C55 -> 43643 | E55: 357 | F55: 1100 | G55: =IFERROR(E55/F55,"") -> 0.32454545 | H55: 9332 | I55: =IFERROR(H55/E55,"") -> 26.140056 | J55: 3005.81 | K55: =IFERROR(J55/E55,"") -> 8.4196359 | L55: 15000 | M55: =IFERROR(L55/H55,"") -> 1.6073725 | N55: =Q55+T55 -> -10721.1 | O55: =R55+U55 -> 3005.81 | P55: =N55+O55 -> -7715.29 | Q55: =W55*50% -> -5360.55 | R55: =J55*70% -> 2104.067 | S55: =Q55+R55 -> -3256.483 | T55: =Q55 -> -5360.55 | U55: =J55*30% -> 901.743 | V55: =T55+U55 -> -4458.807 | W55: -10721.1
A56: 50 | B56: Dussepalooza | C56: 43665 | D56: =C56 -> 43665 | E56: 682 | F56: 1100 | G56: =IFERROR(E56/F56,"") -> 0.62 | H56: 33137 | I56: =IFERROR(H56/E56,"") -> 48.587977 | J56: 6094.73 | K56: =IFERROR(J56/E56,"") -> 8.9365543 | L56: 12260.6 | M56: =IFERROR(L56/H56,"") -> 0.36999728 | N56: =Q56+T56 -> 9761.53 | O56: =R56+U56 -> 6094.73 | P56: =N56+O56 -> 15856.26 | Q56: =W56*50% -> 4880.765 | R56: =J56*70% -> 4266.311 | S56: =Q56+R56 -> 9147.076 | T56: =Q56 -> 4880.765 | U56: =J56*30% -> 1828.419 | V56: =T56+U56 -> 6709.184 | W56: 9761.53
A57: 51 | B57: Baroness | C57: 43666 | D57: =C57 -> 43666 | E57: 547 | F57: 1100 | G57: =IFERROR(E57/F57,"") -> 0.49727273 | H57: 17827.5 | I57: =IFERROR(H57/E57,"") -> 32.591408 | J57: 7129.38 | K57: =IFERROR(J57/E57,"") -> 13.033601 | L57: 8000 | M57: =IFERROR(L57/H57,"") -> 0.44874492 | N57: =Q57+T57 -> 2867.77 | O57: =R57+U57 -> 7129.38 | P57: =N57+O57 -> 9997.15 | Q57: =W57*50% -> 1433.885 | R57: =J57*70% -> 4990.566 | S57: =Q57+R57 -> 6424.451 | T57: =Q57 -> 1433.885 | U57: =J57*30% -> 2138.814 | V57: =T57+U57 -> 3572.699 | W57: 2867.77
A58: 52 | B58: This Might Get Weird (podcast) | C58: 43700 | D58: =C58 -> 43700 | E58: 404 | F58: 418 | G58: =IFERROR(E58/F58,"") -> 0.96650718 | H58: 19707.86 | I58: =IFERROR(H58/E58,"") -> 48.781832 | J58: 2991.41 | K58: =IFERROR(J58/E58,"") -> 7.4044802 | L58: 5631.22 | M58: =IFERROR(L58/H58,"") -> 0.28573473 | N58: =Q58+T58 -> 8467.51 | O58: =R58+U58 -> 2991.41 | P58: =N58+O58 -> 11458.92 | Q58: =W58*50% -> 4233.755 | R58: =J58*70% -> 2093.987 | S58: =Q58+R58 -> 6327.742 | T58: =Q58 -> 4233.755 | U58: =J58*30% -> 897.423 | V58: =T58+U58 -> 5131.178 | W58: 8467.51
A59: 53 | B59: The Growlers | C59: 43716 | D59: =C59 -> 43716 | E59: 560 | F59: 1118 | G59: =IFERROR(E59/F59,"") -> 0.50089445 | H59: 19533.5 | I59: =IFERROR(H59/E59,"") -> 34.88125 | J59: 5174.86 | K59: =IFERROR(J59/E59,"") -> 9.2408214 | L59: 20000 | M59: =IFERROR(L59/H59,"") -> 1.023882 | N59: =Q59+T59 -> -6279.42 | O59: =R59+U59 -> 5174.86 | P59: =N59+O59 -> -1104.56 | Q59: =W59*50% -> -3139.71 | R59: =J59*70% -> 3622.402 | S59: =Q59+R59 -> 482.692 | T59: =Q59 -> -3139.71 | U59: =J59*30% -> 1552.458 | V59: =T59+U59 -> -1587.252 | W59: -6279.42
A60: 54 | B60: Pinegrove | C60: 43717 | D60: =C60 -> 43717 | E60: 706 | F60: 1118 | G60: =IFERROR(E60/F60,"") -> 0.63148479 | H60: 17500 | I60: =IFERROR(H60/E60,"") -> 24.787535 | J60: 7353.89 | K60: =IFERROR(J60/E60,"") -> 10.416275 | L60: 12500 | M60: =IFERROR(L60/H60,"") -> 0.71428571 | N60: =Q60+T60 -> -935.42 | O60: =R60+U60 -> 7353.89 | P60: =N60+O60 -> 6418.47 | Q60: =W60*50% -> -467.71 | R60: =J60*70% -> 5147.723 | S60: =Q60+R60 -> 4680.013 | T60: =Q60 -> -467.71 | U60: =J60*30% -> 2206.167 | V60: =T60+U60 -> 1738.457 | W60: -935.42
A61: =A60+1 -> 55 | B61: Twin Peaks | C61: 43720 | D61: =C61 -> 43720 | E61: 267 | F61: 1100 | G61: =IFERROR(E61/F61,"") -> 0.24272727 | H61: 7262 | I61: =IFERROR(H61/E61,"") -> 27.198502 | J61: 2497.76 | K61: =IFERROR(J61/E61,"") -> 9.3549064 | L61: 3110.92 | M61: =IFERROR(L61/H61,"") -> 0.42838337 | N61: =Q61+T61 -> -1006.96 | O61: =R61+U61 -> 2497.76 | P61: =N61+O61 -> 1490.8 | Q61: =W61*50% -> -503.48 | R61: =J61*70% -> 1748.432 | S61: =Q61+R61 -> 1244.952 | T61: =Q61 -> -503.48 | U61: =J61*30% -> 749.328 | V61: =T61+U61 -> 245.848 | W61: -1006.96
A62: =A61+1 -> 56 | B62: The Aquabats | C62: 43721 | D62: =C62 -> 43721 | E62: 566 | F62: 1118 | G62: =IFERROR(E62/F62,"") -> 0.50626118 | H62: 19993.27 | I62: =IFERROR(H62/E62,"") -> 35.323799 | J62: 3839.76 | K62: =IFERROR(J62/E62,"") -> 6.7840283 | L62: 10000 | M62: =IFERROR(L62/H62,"") -> 0.50016831 | N62: =Q62+T62 -> 2527.68 | O62: =R62+U62 -> 3839.76 | P62: =N62+O62 -> 6367.44 | Q62: =W62*50% -> 1263.84 | R62: =J62*70% -> 2687.832 | S62: =Q62+R62 -> 3951.672 | T62: =Q62 -> 1263.84 | U62: =J62*30% -> 1151.928 | V62: =T62+U62 -> 2415.768 | W62: 2527.68
A63: =A62+1 -> 57 | B63: Dodie | C63: 43722 | D63: =C63 -> 43722 | E63: 1118 | F63: 1118 | G63: =IFERROR(E63/F63,"") -> 1 | H63: 34682.39 | I63: =IFERROR(H63/E63,"") -> 31.021816 | J63: 2319.24 | K63: =IFERROR(J63/E63,"") -> 2.0744544 | L63: 15500 | M63: =IFERROR(L63/H63,"") -> 0.44691268 | N63: =Q63+T63 -> 13189.14 | O63: =R63+U63 -> 2319.24 | P63: =N63+O63 -> 15508.38 | Q63: =W63*50% -> 6594.57 | R63: =J63*70% -> 1623.468 | S63: =Q63+R63 -> 8218.038 | T63: =Q63 -> 6594.57 | U63: =J63*30% -> 695.772 | V63: =T63+U63 -> 7290.342 | W63: 13189.14
A64: =A63+1 -> 58 | B64: grandson | C64: 43723 | D64: =C64 -> 43723 | E64: 514 | F64: 1118 | G64: =IFERROR(E64/F64,"") -> 0.45974955 | H64: 15894 | I64: =IFERROR(H64/E64,"") -> 30.922179 | J64: 3817.37 | K64: =IFERROR(J64/E64,"") -> 7.4267899 | L64: 16500 | M64: =IFERROR(L64/H64,"") -> 1.0381276 | N64: =Q64+T64 -> -6786.33 | O64: =R64+U64 -> 3817.37 | P64: =N64+O64 -> -2968.96 | Q64: =W64*50% -> -3393.165 | R64: =J64*70% -> 2672.159 | S64: =Q64+R64 -> -721.006 | T64: =Q64 -> -3393.165 | U64: =J64*30% -> 1145.211 | V64: =T64+U64 -> -2247.954 | W64: -6786.33
A65: =A64+1 -> 59 | B65: Gwar | C65: 43726 | D65: =C65 -> 43726 | E65: 482 | F65: 1000 | G65: =IFERROR(E65/F65,"") -> 0.482 | H65: 12788 | I65: =IFERROR(H65/E65,"") -> 26.53112 | J65: 6895.84 | K65: =IFERROR(J65/E65,"") -> 14.306722 | L65: 7750 | M65: =IFERROR(L65/H65,"") -> 0.60603691 | N65: =Q65+T65 -> -2657.04 | O65: =R65+U65 -> 6895.84 | P65: =N65+O65 -> 4238.8 | Q65: =W65*50% -> -1328.52 | R65: =J65*70% -> 4827.088 | S65: =Q65+R65 -> 3498.568 | T65: =Q65 -> -1328.52 | U65: =J65*30% -> 2068.752 | V65: =T65+U65 -> 740.232 | W65: -2657.04
A66: =A65+1 -> 60 | B66: Two Door Cinema Club [GUARANTEED] | C66: 43727 | D66: =C66 -> 43727 | G66: =IFERROR(E66/F66,"") | I66: =IFERROR(H66/E66,"") | J66: 8183.9 | K66: =IFERROR(J66/E66,"") | M66: =IFERROR(L66/H66,"") | N66: =Q66+T66 -> 0 | O66: =R66+U66 -> 8183.9 | P66: =N66+O66 -> 8183.9 | Q66: =W66*50% -> 0 | R66: =J66*70% -> 5728.73 | S66: =Q66+R66 -> 5728.73 | T66: =Q66 -> 0 | U66: =J66*30% -> 2455.17 | V66: =T66+U66 -> 2455.17 | W66: 0
A67: =A66+1 -> 61 | B67: Girls Gotta Eat (podcast) | C67: 43729 | D67: =C67 -> 43729 | E67: 412 | F67: 418 | G67: =IFERROR(E67/F67,"") -> 0.98564593 | H67: 17315.2 | I67: =IFERROR(H67/E67,"") -> 42.027184 | J67: 6969.88 | K67: =IFERROR(J67/E67,"") -> 16.917184 | L67: 7247.63 | M67: =IFERROR(L67/H67,"") -> 0.41857039 | N67: =Q67+T67 -> 4828.7 | O67: =R67+U67 -> 6969.88 | P67: =N67+O67 -> 11798.58 | Q67: =W67*50% -> 2414.35 | R67: =J67*70% -> 4878.916 | S67: =Q67+R67 -> 7293.266 | T67: =Q67 -> 2414.35 | U67: =J67*30% -> 2090.964 | V67: =T67+U67 -> 4505.314 | W67: 4828.7
A68: =A67+1 -> 62 | B68: Joseph | C68: 43730 | D68: =C68 -> 43730 | E68: 221 | F68: 1000 | G68: =IFERROR(E68/F68,"") -> 0.221 | H68: 9262 | I68: =IFERROR(H68/E68,"") -> 41.909502 | J68: 2369.97 | K68: =IFERROR(J68/E68,"") -> 10.723846 | L68: 10500 | M68: =IFERROR(L68/H68,"") -> 1.1336644 | N68: =Q68+T68 -> -8468.37 | O68: =R68+U68 -> 2369.97 | P68: =N68+O68 -> -6098.4 | Q68: =W68*50% -> -4234.185 | R68: =J68*70% -> 1658.979 | S68: =Q68+R68 -> -2575.206 | T68: =Q68 -> -4234.185 | U68: =J68*30% -> 710.991 | V68: =T68+U68 -> -3523.194 | W68: -8468.37
A69: =A68+1 -> 63 | B69: Cuco | C69: 43732 | D69: =C69 -> 43732 | E69: 655 | F69: 1100 | G69: =IFERROR(E69/F69,"") -> 0.59545455 | H69: 18350 | I69: =IFERROR(H69/E69,"") -> 28.015267 | J69: 2683.62 | K69: =IFERROR(J69/E69,"") -> 4.0971298 | L69: 17250 | M69: =IFERROR(L69/H69,"") -> 0.9400545 | N69: =Q69+T69 -> -5541.15 | O69: =R69+U69 -> 2683.62 | P69: =N69+O69 -> -2857.53 | Q69: =W69*50% -> -2770.575 | R69: =J69*70% -> 1878.534 | S69: =Q69+R69 -> -892.041 | T69: =Q69 -> -2770.575 | U69: =J69*30% -> 805.086 | V69: =T69+U69 -> -1965.489 | W69: -5541.15
A70: =A69+1 -> 64 | B70: The Waterboys | C70: 43734 | D70: =C70 -> 43734 | E70: 415 | F70: 1000 | G70: =IFERROR(E70/F70,"") -> 0.415 | H70: 16807 | I70: =IFERROR(H70/E70,"") -> 40.498795 | J70: 5130.81 | K70: =IFERROR(J70/E70,"") -> 12.363398 | L70: 10000 | M70: =IFERROR(L70/H70,"") -> 0.59499018 | N70: =Q70+T70 -> 2792.5 | O70: =R70+U70 -> 5130.81 | P70: =N70+O70 -> 7923.31 | Q70: =W70*50% -> 1396.25 | R70: =J70*70% -> 3591.567 | S70: =Q70+R70 -> 4987.817 | T70: =Q70 -> 1396.25 | U70: =J70*30% -> 1539.243 | V70: =T70+U70 -> 2935.493 | W70: 2792.5
A71: =A70+1 -> 65 | B71: Jason Nash | C71: 43735 | D71: =C71 -> 43735 | E71: 400 | F71: 400 | G71: =IFERROR(E71/F71,"") -> 1 | H71: 28171 | I71: =IFERROR(H71/E71,"") -> 70.4275 | J71: 2018.82 | K71: =IFERROR(J71/E71,"") -> 5.04705 | L71: 5000 | M71: =IFERROR(L71/H71,"") -> 0.17748749 | N71: =Q71+T71 -> 19437.45 | O71: =R71+U71 -> 2018.82 | P71: =N71+O71 -> 21456.27 | Q71: =W71*50% -> 9718.725 | R71: =J71*70% -> 1413.174 | S71: =Q71+R71 -> 11131.899 | T71: =Q71 -> 9718.725 | U71: =J71*30% -> 605.646 | V71: =T71+U71 -> 10324.371 | W71: 19437.45
A72: =A71+1 -> 66 | B72: Steve Lacy | C72: 43736 | D72: =C72 -> 43736 | E72: 518 | F72: 1118 | G72: =IFERROR(E72/F72,"") -> 0.46332737 | H72: 18930 | I72: =IFERROR(H72/E72,"") -> 36.544402 | J72: 3515.78 | K72: =IFERROR(J72/E72,"") -> 6.7872201 | L72: 15500 | M72: =IFERROR(L72/H72,"") -> 0.81880613 | N72: =Q72+T72 -> -648.39 | O72: =R72+U72 -> 3515.78 | P72: =N72+O72 -> 2867.39 | Q72: =W72*50% -> -324.195 | R72: =J72*70% -> 2461.046 | S72: =Q72+R72 -> 2136.851 | T72: =Q72 -> -324.195 | U72: =J72*30% -> 1054.734 | V72: =T72+U72 -> 730.539 | W72: -648.39
A73: =A72+1 -> 67 | B73: Gus Dapperton | C73: 43739 | D73: =C73 -> 43739 | E73: 247 | F73: 1000 | G73: =IFERROR(E73/F73,"") -> 0.247 | H73: 6968 | I73: =IFERROR(H73/E73,"") -> 28.210526 | J73: 1687.1 | K73: =IFERROR(J73/E73,"") -> 6.8303644 | L73: 8000 | M73: =IFERROR(L73/H73,"") -> 1.1481056 | N73: =Q73+T73 -> -6502.38 | O73: =R73+U73 -> 1687.1 | P73: =N73+O73 -> -4815.28 | Q73: =W73*50% -> -3251.19 | R73: =J73*70% -> 1180.97 | S73: =Q73+R73 -> -2070.22 | T73: =Q73 -> -3251.19 | U73: =J73*30% -> 506.13 | V73: =T73+U73 -> -2745.06 | W73: -6502.38
A74: =A73+1 -> 68 | B74: The New Pornographers | C74: 43741 | D74: =C74 -> 43741 | E74: 413 | F74: 1000 | G74: =IFERROR(E74/F74,"") -> 0.413 | H74: 14856 | I74: =IFERROR(H74/E74,"") -> 35.970944 | J74: 4607.99 | K74: =IFERROR(J74/E74,"") -> 11.157361 | L74: 15500 | M74: =IFERROR(L74/H74,"") -> 1.0433495 | N74: =Q74+T74 -> -4428.44 | O74: =R74+U74 -> 4607.99 | P74: =N74+O74 -> 179.55 | Q74: =W74*50% -> -2214.22 | R74: =J74*70% -> 3225.593 | S74: =Q74+R74 -> 1011.373 | T74: =Q74 -> -2214.22 | U74: =J74*30% -> 1382.397 | V74: =T74+U74 -> -831.823 | W74: -4428.44
A75: =A74+1 -> 69 | B75: Dark Star Orchestra | C75: 43743 | D75: =C75 -> 43743 | E75: 748 | F75: 1100 | G75: =IFERROR(E75/F75,"") -> 0.68 | H75: 25330 | I75: =IFERROR(H75/E75,"") -> 33.863636 | J75: 13395.89 | K75: =IFERROR(J75/E75,"") -> 17.908944 | L75: 15164 | M75: =IFERROR(L75/H75,"") -> 0.59865772 | N75: =Q75+T75 -> 2924.34 | O75: =R75+U75 -> 13395.89 | P75: =N75+O75 -> 16320.23 | Q75: =W75*50% -> 1462.17 | R75: =J75*70% -> 9377.123 | S75: =Q75+R75 -> 10839.293 | T75: =Q75 -> 1462.17 | U75: =J75*30% -> 4018.767 | V75: =T75+U75 -> 5480.937 | W75: 2924.34
A76: =A75+1 -> 70 | B76: Noah Kahan | C76: 43753 | D76: =C76 -> 43753 | E76: 497 | F76: 1100 | G76: =IFERROR(E76/F76,"") -> 0.45181818 | H76: 16512 | I76: =IFERROR(H76/E76,"") -> 33.22334 | J76: 2800.6 | K76: =IFERROR(J76/E76,"") -> 5.6350101 | L76: 4500 | M76: =IFERROR(L76/H76,"") -> 0.27252907 | N76: =Q76+T76 -> 4011.37 | O76: =R76+U76 -> 2800.6 | P76: =N76+O76 -> 6811.97 | Q76: =W76*50% -> 2005.685 | R76: =J76*70% -> 1960.42 | S76: =Q76+R76 -> 3966.105 | T76: =Q76 -> 2005.685 | U76: =J76*30% -> 840.18 | V76: =T76+U76 -> 2845.865 | W76: 4011.37
A77: =A76+1 -> 71 | B77: Municipal Waste | C77: 43754 | D77: =C77 -> 43754 | E77: 359 | F77: 1000 | G77: =IFERROR(E77/F77,"") -> 0.359 | H77: 10889.5 | I77: =IFERROR(H77/E77,"") -> 30.332869 | J77: 4638.54 | K77: =IFERROR(J77/E77,"") -> 12.920724 | L77: 10500 | M77: =IFERROR(L77/H77,"") -> 0.9642316 | N77: =Q77+T77 -> -5594.44 | O77: =R77+U77 -> 4638.54 | P77: =N77+O77 -> -955.9 | Q77: =W77*50% -> -2797.22 | R77: =J77*70% -> 3246.978 | S77: =Q77+R77 -> 449.758 | T77: =Q77 -> -2797.22 | U77: =J77*30% -> 1391.562 | V77: =T77+U77 -> -1405.658 | W77: -5594.44
A78: =A77+1 -> 72 | B78: Big Thief | C78: 43755 | D78: =C78 -> 43755 | E78: 966 | F78: 1100 | G78: =IFERROR(E78/F78,"") -> 0.87818182 | H78: 25700.5 | I78: =IFERROR(H78/E78,"") -> 26.605072 | J78: 7572.93 | K78: =IFERROR(J78/E78,"") -> 7.839472 | L78: 9517.841 | M78: =IFERROR(L78/H78,"") -> 0.3703368 | N78: =Q78+T78 -> 8786.53 | O78: =R78+U78 -> 7572.93 | P78: =N78+O78 -> 16359.46 | Q78: =W78*50% -> 4393.265 | R78: =J78*70% -> 5301.051 | S78: =Q78+R78 -> 9694.316 | T78: =Q78 -> 4393.265 | U78: =J78*30% -> 2271.879 | V78: =T78+U78 -> 6665.144 | W78: 8786.53
... A80: =A79+1 -> 74 | B80: Alejandro Aranda | C80: 43763 | D80: =C80 -> 43763 | E80: 1109 | F80: 1218 | G80: =IFERROR(E80/F80,"") -> 0.91050903 | H80: 29835.74 | I80: =IFERROR(H80/E80,"") -> 26.903282 | J80: 5509.31 | K80: =IFERROR(J80/E80,"") -> 4.9678179 | L80: 11963.55 | M80: =IFERROR(L80/H80,"") -> 0.4009805 | N80: =Q80+T80 -> 11897.46 | O80: =R80+U80 -> 5509.31 | P80: =N80+O80 -> 17406.77 | Q80: =W80*50% -> 5948.73 | R80: =J80*70% -> 3856.517 | S80: =Q80+R80 -> 9805.247 | T80: =Q80 -> 5948.73 | U80: =J80*30% -> 1652.793 | V80: =T80+U80 -> 7601.523 | W80: 11897.46
A81: =A80+1 -> 75 | B81: Loud Luxury (1) | C81: 43764 | D81: =C81 -> 43764 | E81: 943 | F81: 1100 | G81: =IFERROR(E81/F81,"") -> 0.85727273 | H81: 23724.5 | I81: =IFERROR(H81/E81,"") -> 25.158537 | J81: 14127.21 | K81: =IFERROR(J81/E81,"") -> 14.981135 | L81: 7540.63 | M81: =IFERROR(L81/H81,"") -> 0.31784147 | N81: =Q81+T81 -> 5778.3394 | O81: =R81+U81 -> 14127.21 | P81: =N81+O81 -> 19905.549 | Q81: =W81*33.33333% -> 2889.1697 | R81: =J81*70% -> 9889.047 | S81: =Q81+R81 -> 12778.217 | T81: =Q81 -> 2889.1697 | U81: =J81*30% -> 4238.163 | V81: =T81+U81 -> 7127.3327 | W81: 8667.51
A82: =A81+1 -> 76 | B82: Starset | C82: 43768 | D82: =C82 -> 43768 | E82: 722 | F82: 1000 | G82: =IFERROR(E82/F82,"") -> 0.722 | H82: 23692 | I82: =IFERROR(H82/E82,"") -> 32.814404 | J82: 5241.12 | K82: =IFERROR(J82/E82,"") -> 7.259169 | L82: 10000 | M82: =IFERROR(L82/H82,"") -> 0.4220834 | N82: =Q82+T82 -> 5819.55 | O82: =R82+U82 -> 5241.12 | P82: =N82+O82 -> 11060.67 | Q82: =W82*50% -> 2909.775 | R82: =J82*70% -> 3668.784 | S82: =Q82+R82 -> 6578.559 | T82: =Q82 -> 2909.775 | U82: =J82*30% -> 1572.336 | V82: =T82+U82 -> 4482.111 | W82: 5819.55
A83: =A82+1 -> 77 | B83: Tom Papa | C83: 43770 | D83: =C83 -> 43770 | E83: 245 | F83: 275 | G83: =IFERROR(E83/F83,"") -> 0.89090909 | H83: 9692 | I83: =IFERROR(H83/E83,"") -> 39.559184 | J83: 0 | K83: =IFERROR(J83/E83,"") -> 0 | L83: 4750 | M83: =IFERROR(L83/H83,"") -> 0.49009492 | N83: =Q83+T83 -> 158.85 | O83: =R83+U83 -> 0 | P83: =N83+O83 -> 158.85 | Q83: =W83*50% -> 79.425 | R83: =J83*70% -> 0 | S83: =Q83+R83 -> 79.425 | T83: =Q83 -> 79.425 | U83: =J83*30% -> 0 | V83: =T83+U83 -> 79.425 | W83: 158.85
A84: =A83+1 -> 78 | B84: Oliver Tree | C84: 43770 | D84: =C84 -> 43770 | E84: 1220 | F84: 1218 | G84: =IFERROR(E84/F84,"") -> 1.001642 | H84: 35521 | I84: =IFERROR(H84/E84,"") -> 29.115574 | J84: 8583.02 | K84: =IFERROR(J84/E84,"") -> 7.0352623 | L84: 13975.46 | M84: =IFERROR(L84/H84,"") -> 0.39344219 | N84: =Q84+T84 -> 15157.18 | O84: =R84+U84 -> 8583.02 | P84: =N84+O84 -> 23740.2 | Q84: =W84*50% -> 7578.59 | R84: =J84*70% -> 6008.114 | S84: =Q84+R84 -> 13586.704 | T84: =Q84 -> 7578.59 | U84: =J84*30% -> 2574.906 | V84: =T84+U84 -> 10153.496 | W84: 15157.18
A85: =A84+1 -> 79 | B85: Toro y Moi | C85: 43771 | D85: =C85 -> 43771 | E85: 1100 | F85: 1108 | G85: =IFERROR(E85/F85,"") -> 0.99277978 | H85: 30422 | I85: =IFERROR(H85/E85,"") -> 27.656364 | J85: 11590.33 | K85: =IFERROR(J85/E85,"") -> 10.536664 | L85: 15000 | M85: =IFERROR(L85/H85,"") -> 0.49306423 | N85: =Q85+T85 -> 9369.38 | O85: =R85+U85 -> 11590.33 | P85: =N85+O85 -> 20959.71 | Q85: =W85*50% -> 4684.69 | R85: =J85*70% -> 8113.231 | S85: =Q85+R85 -> 12797.921 | T85: =Q85 -> 4684.69 | U85: =J85*30% -> 3477.099 | V85: =T85+U85 -> 8161.789 | W85: 9369.38
A86: =A85+1 -> 80 | B86: Sleater Kinney | C86: 43773 | D86: =C86 -> 43773 | E86: 730 | F86: 1140 | G86: =IFERROR(E86/F86,"") -> 0.64035088 | H86: 33191 | I86: =IFERROR(H86/E86,"") -> 45.467123 | J86: 5269.25 | K86: =IFERROR(J86/E86,"") -> 7.2181507 | L86: 30500 | M86: =IFERROR(L86/H86,"") -> 0.9189238 | N86: =Q86+T86 -> -6030.22 | O86: =R86+U86 -> 5269.25 | P86: =N86+O86 -> -760.97 | Q86: =W86*50% -> -3015.11 | R86: =J86*70% -> 3688.475 | S86: =Q86+R86 -> 673.365 | T86: =Q86 -> -3015.11 | U86: =J86*30% -> 1580.775 | V86: =T86+U86 -> -1434.335 | W86: -6030.22
A87: =A86+1 -> 81 | B87: Crumb | C87: 43774 | D87: =C87 -> 43774 | E87: 386 | F87: 1100 | G87: =IFERROR(E87/F87,"") -> 0.35090909 | H87: 10035 | I87: =IFERROR(H87/E87,"") -> 25.997409 | J87: 3545.49 | K87: =IFERROR(J87/E87,"") -> 9.1852073 | L87: 8000 | M87: =IFERROR(L87/H87,"") -> 0.79720977 | N87: =Q87+T87 -> -3505.44 | O87: =R87+U87 -> 3545.49 | P87: =N87+O87 -> 40.05 | Q87: =W87*50% -> -1752.72 | R87: =J87*70% -> 2481.843 | S87: =Q87+R87 -> 729.123 | T87: =Q87 -> -1752.72 | U87: =J87*30% -> 1063.647 | V87: =T87+U87 -> -689.073 | W87: -3505.44
A88: =A87+1 -> 82 | B88: A$ap Ferg [GUARANTEED] | C88: 43777 | D88: =C88 -> 43777 | G88: =IFERROR(E88/F88,"") | J88: 4760.99 | M88: =IFERROR(L88/H88,"") | N88: =Q88+T88 -> 0 | O88: =R88+U88 -> 4760.99 | P88: =N88+O88 -> 4760.99 | Q88: =W88*50% -> 0 | R88: =J88*70% -> 3332.693 | S88: =Q88+R88 -> 3332.693 | T88: =Q88 -> 0 | U88: =J88*30% -> 1428.297 | V88: =T88+U88 -> 1428.297
A89: =A88+1 -> 83 | B89: The Interrupters | C89: 43778 | D89: =C89 -> 43778 | E89: 845 | F89: 1100 | G89: =IFERROR(E89/F89,"") -> 0.76818182 | H89: 26905.5 | I89: =IFERROR(H89/E89,"") -> 31.840828 | J89: 11143.64 | K89: =IFERROR(J89/E89,"") -> 13.18774 | L89: 14080 | M89: =IFERROR(L89/H89,"") -> 0.52331308 | N89: =Q89+T89 -> 4858.76 | O89: =R89+U89 -> 11143.64 | P89: =N89+O89 -> 16002.4 | Q89: =W89*50% -> 2429.38 | R89: =J89*70% -> 7800.548 | S89: =Q89+R89 -> 10229.928 | T89: =Q89 -> 2429.38 | U89: =J89*30% -> 3343.092 | V89: =T89+U89 -> 5772.472 | W89: 4858.76
A90: =A89+1 -> 84
A91: =A90+1 -> 85
A92: =A91+1 -> 86
A93: =A92+1 -> 87
A94: =A93+1 -> 88
A95: =A94+1 -> 89
A96: =A95+1 -> 90
A97: =A96+1 -> 91
A98: =A97+1 -> 92
A99: =A98+1 -> 93
A100: =A99+1 -> 94
A101: =A100+1 -> 95
... A108: =A107+1 -> 102

Sheet Magic Stick
O1: VENUE TOTAL | R1: PARTNER SPLIT
B2: ***MAGIC STICK RESULTS*** | O2: MAGIC STICK | R2: MTC, Inc. | U2: J&A
B3: Name | C3: Promoter Code | D3: Date | E3: Day of the week | F3: Tickets Sold | G3: Venue Capacity | H3: Capacity Rate | I3: Gross Ticket Revenue | J3: Avg. Ticket Price (including TW rebate) | K3: Bar Revenue | L3: Avg sale of alcohol per guest | M3: Band(s) guarantee | N3: % of Gross Ticket Revenue | O3: Gate Settlement Gain/(Loss) | P3: Bar Sales - 100% | Q3: Show Gross Proceeds (before COGS, Labor, & Facility Costs) | R3: Gate Settlement Gain/(Loss) | S3: Bar Sales - 50% | T3: Show Gross Proceeds (before COGS, Labor, & Facility Costs) | U3: Gate Settlement Gain/(Loss) | V3: Bar Sales - 50% | W3: Show Gross Proceeds (before COGS, Labor, & Facility Costs) | X3: INPUT - Total Gate Settlement | AA3: Facility Fee & Rebate | AB3: React per person promoter fees
B4: TOTALS | F4: =SUM(F7:F82) -> 28952 | G4: =SUM(G7:G82) -> 43700 | I4: =SUM(I7:I82) -> 754923 | K4: =SUM(K7:K82) -> 523492.54 | M4: =SUM(M7:M82) -> 456312.56 | N4: =SUM(N7:N82) -> 43.154911 | O4: =SUM(O7:O82) -> 31502.43 | P4: =SUM(P7:P82) -> 523492.54 | Q4: =SUM(Q7:Q82) -> 554994.97 | R4: =SUM(R7:R82) -> 15751.215 | S4: =SUM(S7:S82) -> 261746.27 | T4: =SUM(T7:T82) -> 277497.49 | ... W4: =SUM(W7:W82) -> 277497.49
B5: AVERAGES | F5: =F4/COUNTA(F7:F82) -> 482.53333 | G5: =G4/COUNTA(G7:G82) -> 728.33333 | H5: =F4/G4 -> 0.66251716 | I5: =I4/COUNTA(I7:I82) -> 12582.05 | J5: =I4/F4 -> 26.074986 | K5: =K4/COUNTA(K7:K82) -> 8581.8449 | L5: =K4/F4 -> 18.081395 | M5: =M4/COUNTA(M7:M82) -> 7605.2093 | N5: =M4/I4 -> 0.60444914 | O5: =O4/COUNTA(O7:O82) -> 516.43328 | P5: =P4/COUNTA(P7:P82) -> 8581.8449 | Q5: =Q4/COUNTA(Q7:Q82) -> 9098.2782 | R5: =R4/COUNTA(R7:R82) -> 258.21664 | S5: =S4/COUNTA(S7:S82) -> 4290.9225 | T5: =T4/COUNTA(T7:T82) -> 4549.1391 | U5: =U4/COUNTA(U7:U82) -> 258.21664 | V5: =V4/COUNTA(V7:V82) -> 4290.9225 | W5: =W4/COUNTA(W7:W82) -> 4549.1391
A7: 1 | B7: Will Sessions | C7: 1 | D7: 43491 | E7: =D7 -> 43491 | F7: 270 | G7: 700 | H7: =IFERROR(F7/G7,"") -> 0.38571429 | I7: 4193 | J7: =IFERROR(I7/F7,"") -> 15.52963 | K7: 5772 | L7: =IFERROR(K7/F7,"") -> 21.377778 | M7: 3300 | N7: =IFERROR(M7/I7,"") -> 0.787026 | O7: =R7+U7 -> -278 | P7: =S7+V7 -> 5772 | Q7: =O7+P7 -> 5494 | R7: =X7*50% -> -139 | S7: =K7*50% -> 2886 | T7: =R7+S7 -> 2747 | U7: =R7 -> -139 | V7: =K7*50% -> 2886 | W7: =U7+V7 -> 2747 | X7: -278 | Y7: =T7+W7 -> 5494
A8: 2 | B8: Claude VonStroke - Night 1 | C8: 5 | D8: 43504 | E8: =D8 -> 43504 | F8: 800 | G8: 800 | H8: =IFERROR(F8/G8,"") -> 1 | I8: 27370.5 | J8: =IFERROR(I8/F8,"") -> 34.213125 | K8: 18143 | L8: =IFERROR(K8/F8,"") -> 22.67875 | M8: 15400 | N8: =IFERROR(M8/I8,"") -> 0.56264957 | O8: =R8+U8 -> 5503.13 | P8: =S8+V8 -> 18143 | Q8: =O8+P8 -> 23646.13 | R8: =X8*50% -> 2751.565 | S8: =K8*50% -> 9071.5 | T8: =R8+S8 -> 11823.065 | U8: =R8 -> 2751.565 | V8: =K8*50% -> 9071.5 | W8: =U8+V8 -> 11823.065 | X8: 5503.13 | Y8: =T8+W8 -> 23646.13
A9: 3 | B9: Claude VonStroke - Night 2 | C9: 5 | D9: 43505 | E9: =D9 -> 43505 | F9: 810 | G9: 800 | H9: =IFERROR(F9/G9,"") -> 1.0125 | I9: 26875 | J9: =IFERROR(I9/F9,"") -> 33.179012 | K9: 21111.5 | L9: =IFERROR(K9/F9,"") -> 26.06358 | M9: =15000+125+100+150+75 -> 15450 | N9: =IFERROR(M9/I9,"") -> 0.57488372 | O9: =R9+U9 -> 6280.05 | P9: =S9+V9 -> 21111.5 | Q9: =O9+P9 -> 27391.55 | R9: =X9*50% -> 3140.025 | S9: =K9*50% -> 10555.75 | T9: =R9+S9 -> 13695.775 | U9: =R9 -> 3140.025 | V9: =K9*50% -> 10555.75 | W9: =U9+V9 -> 13695.775 | X9: 6280.05 | Y9: =T9+W9 -> 27391.55
A10: 4 | B10: Omega moos | C10: 5 | D10: 43518 | E10: =D10 -> 43518 | F10: 734 | G10: 700 | H10: =IFERROR(F10/G10,"") -> 1.0485714 | I10: 13853.5 | J10: =IFERROR(I10/F10,"") -> 18.873978 | K10: 9304 | L10: =IFERROR(K10/F10,"") -> 12.675749 | M10: 10150 | N10: =IFERROR(M10/I10,"") -> 0.73266684 | O10: =R10+U10 -> 1014.45 | P10: =S10+V10 -> 9304 | Q10: =O10+P10 -> 10318.45 | R10: =X10*50% -> 507.225 | S10: =K10*50% -> 4652 | T10: =R10+S10 -> 5159.225 | U10: =R10 -> 507.225 | V10: =K10*50% -> 4652 | W10: =U10+V10 -> 5159.225 | X10: 1014.45 | Y10: =T10+W10 -> 10318.45
A11: 5 | B11: Desert Hearts | C11: 5 | D11: 43519 | E11: =D11 -> 43519 | F11: 806 | G11: 700 | H11: =IFERROR(F11/G11,"") -> 1.1514286 | I11: 20546 | J11: =IFERROR(I11/F11,"") -> 25.491315 | K11: 17568 | L11: =IFERROR(K11/F11,"") -> 21.796526 | M11: 9525 | N11: =IFERROR(M11/I11,"") -> 0.46359389 | O11: =R11+U11 -> 4143.68 | P11: =S11+V11 -> 17568 | Q11: =O11+P11 -> 21711.68 | R11: =X11*50% -> 2071.84 | S11: =K11*50% -> 8784 | T11: =R11+S11 -> 10855.84 | U11: =R11 -> 2071.84 | V11: =K11*50% -> 8784 | W11: =U11+V11 -> 10855.84 | X11: 4143.68 | Y11: =T11+W11 -> 21711.68
A12: 6 | B12: Marco Carola | C12: 5 | D12: 43532 | E12: =D12 -> 43532 | F12: 510 | G12: 700 | H12: =IFERROR(F12/G12,"") -> 0.72857143 | I12: 16440 | J12: =IFERROR(I12/F12,"") -> 32.235294 | K12: 17184 | L12: =IFERROR(K12/F12,"") -> 33.694118 | M12: 18500 | N12: =IFERROR(M12/I12,"") -> 1.1253041 | O12: =R12+U12 -> -7036.43 | P12: =S12+V12 -> 17184 | Q12: =O12+P12 -> 10147.57 | R12: =X12*50% -> -3518.215 | S12: =K12*50% -> 8592 | T12: =R12+S12 -> 5073.785 | U12: =R12 -> -3518.215 | V12: =K12*50% -> 8592 | W12: =U12+V12 -> 5073.785 | X12: -7036.43 | Y12: =T12+W12 -> 10147.57
A13: 7 | B13: Charlesthefirst | C13: 5 | D13: 43533 | E13: =D13 -> 43533 | F13: 800 | G13: 800 | H13: =IFERROR(F13/G13,"") -> 1 | I13: 14620 | J13: =IFERROR(I13/F13,"") -> 18.275 | K13: 12599 | L13: =IFERROR(K13/F13,"") -> 15.74875 | M13: 8100 | N13: =IFERROR(M13/I13,"") -> 0.55403557 | O13: =R13+U13 -> 1590.67 | P13: =S13+V13 -> 12599 | Q13: =O13+P13 -> 14189.67 | R13: =X13*50% -> 795.335 | S13: =K13*50% -> 6299.5 | T13: =R13+S13 -> 7094.835 | U13: =R13 -> 795.335 | V13: =K13*50% -> 6299.5 | W13: =U13+V13 -> 7094.835 | X13: 1590.67 | Y13: =T13+W13 -> 14189.67
A14: 8 | B14: Desert Dwellers | C14: 8 | D14: 43547 | E14: =D14 -> 43547 | F14: 753 | G14: 700 | H14: =IFERROR(F14/G14,"") -> 1.0757143 | I14: 19105 | J14: =IFERROR(I14/F14,"") -> 25.371846 | K14: 10559 | L14: =IFERROR(K14/F14,"") -> 14.022576 | M14: 6050 | N14: =IFERROR(M14/I14,"") -> 0.31667103 | O14: =R14+U14 -> 10383.67 | P14: =S14+V14 -> 10559 | Q14: =O14+P14 -> 20942.67 | R14: =X14*50% -> 5191.835 | S14: =K14*50% -> 5279.5 | T14: =R14+S14 -> 10471.335 | U14: =R14 -> 5191.835 | V14: =K14*50% -> 5279.5 | W14: =U14+V14 -> 10471.335 | X14: 10383.67 | Y14: =T14+W14 -> 20942.67
A15: 9 | B15: Charlotte de Witte | C15: 5 | D15: 43553 | E15: =D15 -> 43553 | F15: 846 | G15: 800 | H15: =IFERROR(F15/G15,"") -> 1.0575 | I15: 21440 | J15: =IFERROR(I15/F15,"") -> 25.34279 | K15: 16341 | L15: =IFERROR(K15/F15,"") -> 19.315603 | M15: 10700 | N15: =IFERROR(M15/I15,"") -> 0.49906716 | O15: =R15+U15 -> 5607.96 | P15: =S15+V15 -> 16341 | Q15: =O15+P15 -> 21948.96 | R15: =X15*50% -> 2803.98 | S15: =K15*50% -> 8170.5 | T15: =R15+S15 -> 10974.48 | U15: =R15 -> 2803.98 | V15: =K15*50% -> 8170.5 | W15: =U15+V15 -> 10974.48 | X15: 5607.96 | Y15: =T15+W15 -> 21948.96
A16: 10 | B16: The True Blue [RENTAL] | C16: 6 | D16: 43554 | E16: =D16 -> 43554 | H16: =IFERROR(F16/G16,"") | J16: =IFERROR(I16/F16,"") | K16: 2361 | L16: =IFERROR(K16/F16,"") | N16: =IFERROR(M16/I16,"") | O16: =R16+U16 -> -120 | P16: =S16+V16 -> 2361 | Q16: =O16+P16 -> 2241 | R16: =X16*50% -> -60 | S16: =K16*50% -> 1180.5 | T16: =R16+S16 -> 1120.5 | U16: =R16 -> -60 | V16: =K16*50% -> 1180.5 | W16: =U16+V16 -> 1120.5 | X16: -120 | Y16: =T16+W16 -> 2241
A17: 11 | B17: Droeloe | C17: 2 | D17: 43560 | E17: =D17 -> 43560 | F17: 736 | G17: 700 | H17: =IFERROR(F17/G17,"") -> 1.0514286 | I17: =11870+AA17 -> 14230 | J17: =IFERROR(I17/F17,"") -> 19.334239 | K17: 9681 | L17: =IFERROR(K17/F17,"") -> 13.153533 | M17: 6152.7 | N17: =IFERROR(M17/I17,"") -> 0.43237526 | O17: =R17+U17 -> 1320.98 | P17: =S17+V17 -> 9681 | Q17: =O17+P17 -> 11001.98 | R17: =(X17+AA17-AB17)/2 -> 660.49 | S17: =K17*50% -> 4840.5 | T17: =R17+S17 -> 5500.99 | U17: =R17 -> 660.49 | V17: =K17*50% -> 4840.5 | W17: =U17+V17 -> 5500.99 | X17: 1168.98 | Y17: =T17+W17 -> 11001.98 | AA17: =560+1800 -> 2360 | AB17: 2208
A18: 12 | B18: Crankdat | C18: 2 | D18: 43568 | E18: =D18 -> 43568 | F18: 442 | G18: 700 | H18: =IFERROR(F18/G18,"") -> 0.63142857 | I18: =7755+AA18 -> 9066 | J18: =IFERROR(I18/F18,"") -> 20.511312 | K18: 7513.5 | L18: =IFERROR(K18/F18,"") -> 16.998869 | M18: =1250+2000+750+400+175 -> 4575 | N18: =IFERROR(M18/I18,"") -> 0.50463269 | O18: =R18+U18 -> -571.79 | P18: =S18+V18 -> 7513.5 | Q18: =O18+P18 -> 6941.71 | R18: =(X18+AA18-AB18)/2 -> -285.895 | S18: =K18*50% -> 3756.75 | T18: =R18+S18 -> 3470.855 | U18: =R18 -> -285.895 | V18: =K18*50% -> 3756.75 | W18: =U18+V18 -> 3470.855 | X18: -556.79 | Y18: =T18+W18 -> 6941.71 | AA18: =291+1020 -> 1311 | AB18: 1326
A19: 13 | B19: Esseks | C19: 8 | D19: 43574 | E19: =D19 -> 43574 | F19: 462 | G19: 700 | H19: =IFERROR(F19/G19,"") -> 0.66 | I19: 7541 | J19: =IFERROR(I19/F19,"") -> 16.322511 | K19: 7542.5 | L19: =IFERROR(K19/F19,"") -> 16.325758 | M19: 5000 | N19: =IFERROR(M19/I19,"") -> 0.66304204 | O19: =R19+U19 -> 3430.92 | P19: =S19+V19 -> 7542.5 | Q19: =O19+P19 -> 10973.42 | R19: =X19*50% -> 1715.46 | S19: =K19*50% -> 3771.25 | T19: =R19+S19 -> 5486.71 | U19: =R19 -> 1715.46 | V19: =K19*50% -> 3771.25 | W19: =U19+V19 -> 5486.71 | X19: =SUM(Z19:AA19)-6480.58-AB19 -> 3430.92 | Y19: =T19+W19 -> 10973.42 | Z19: =3050+5515 -> 8565 | AA19: =1055.5+291 -> 1346.5 | AB19: 0
A20: 14 | B20: CloZee | C20: 2 | D20: 43581 | E20: =D20 -> 43581 | F20: 800 | G20: 800 | H20: =IFERROR(F20/G20,"") -> 1 | I20: =23036+AA20 -> 27047 | J20: =IFERROR(I20/F20,"") -> 33.80875 | K20: 14724 | L20: =IFERROR(K20/F20,"") -> 18.405 | M20: =10440.5+1000+250+500 -> 12190.5 | N20: =IFERROR(M20/I20,"") -> 0.45071542 | O20: =R20+U20 -> 4239.72 | P20: =S20+V20 -> 14724 | Q20: =O20+P20 -> 18963.72 | R20: =X20*50% -> 2119.86 | S20: =K20*50% -> 7362 | T20: =R20+S20 -> 9481.86 | U20: =R20 -> 2119.86 | V20: =K20*50% -> 7362 | W20: =U20+V20 -> 9481.86 | X20: =SUM(Z20:AA20)-16396.28-AB20 -> 4239.72 | Y20: =T20+W20 -> 18963.72 | Z20: =75+18950 -> 19025 | AA20: =2889+642+480 -> 4011 | AB20: 2400 | AC20: =1276.86*2 -> 2553.72 | AD20: =AC20+AA20 -> 6564.72 | AE20: =AD20/2 -> 3282.36
A21: 15 | B21: Freddy Todd | C21: 2 | D21: 43589 | E21: =D21 -> 43589 | F21: 436 | G21: 700 | H21: =IFERROR(F21/G21,"") -> 0.62285714 | I21: =7595+AA21 -> 8460 | J21: =IFERROR(I21/F21,"") -> 19.40367 | K21: 5650 | L21: =IFERROR(K21/F21,"") -> 12.958716 | M21: 4550 | N21: =IFERROR(M21/I21,"") -> 0.53782506 | O21: =R21+U21 -> -2461.48 | P21: =S21+V21 -> 5650 | Q21: =O21+P21 -> 3188.52 | R21: =(X21+AA21-AB21)/2 -> -1230.74 | S21: =K21*50% -> 2825 | T21: =R21+S21 -> 1594.26 | U21: =R21 -> -1230.74 | V21: =K21*50% -> 2825 | W21: =U21+V21 -> 1594.26 | X21: -2336.48 | Y21: =T21+W21 -> 3188.52 | AA21: =687+178 -> 865 | AB21: 990
A22: 16 | B22: Cursive/Mewithoutyou | C22: 1 | D22: 43594 | E22: =D22 -> 43594 | F22: 401 | G22: 700 | H22: =IFERROR(F22/G22,"") -> 0.57285714 | I22: 11236 | J22: =IFERROR(I22/F22,"") -> 28.01995 | K22: 4843 | L22: =IFERROR(K22/F22,"") -> 12.077307 | M22: =4000+4000+500 -> 8500 | N22: =IFERROR(M22/I22,"") -> 0.75649697 | O22: =R22+U22 -> -50.71 | P22: =S22+V22 -> 4843 | Q22: =O22+P22 -> 4792.29 | R22: =X22*50% -> -25.355 | S22: =K22*50% -> 2421.5 | T22: =R22+S22 -> 2396.145 | U22: =R22 -> -25.355 | V22: =K22*50% -> 2421.5 | W22: =U22+V22 -> 2396.145 | X22: -50.71 | Y22: =T22+W22 -> 4792.29 | AB22: 23036
A23: 17 | B23: Riverside | C23: 1 | D23: 43603 | E23: =D23 -> 43603 | F23: 267 | G23: 700 | H23: =IFERROR(F23/G23,"") -> 0.38142857 | I23: 7096.75 | J23: =IFERROR(I23/F23,"") -> 26.579588 | K23: 2405 | L23: =IFERROR(K23/F23,"") -> 9.0074906 | M23: 5000 | N23: =IFERROR(M23/I23,"") -> 0.70454786 | O23: =R23+U23 -> -409.25 | P23: =S23+V23 -> 2405 | Q23: =O23+P23 -> 1995.75 | R23: =X23*50% -> -204.625 | S23: =K23*50% -> 1202.5 | T23: =R23+S23 -> 997.875 | U23: =R23 -> -204.625 | V23: =K23*50% -> 1202.5 | W23: =U23+V23 -> 997.875 | X23: =-1129.25+720 -> -409.25 | Y23: =T23+W23 -> 1995.75 | AB23: -16396.28
A24: 18 | B24: Snow Tha Product | C24: 4 | D24: 43607 | E24: =D24 -> 43607 | F24: 637 | G24: 700 | H24: =IFERROR(F24/G24,"") -> 0.91 | I24: 16427 | J24: =IFERROR(I24/F24,"") -> 25.788069 | K24: 9143 | L24: =IFERROR(K24/F24,"") -> 14.353218 | M24: =3729.16+3000+100 -> 6829.16 | N24: =IFERROR(M24/I24,"") -> 0.41572777 | O24: =R24+U24 -> 6103.47 | P24: =S24+V24 -> 9143 | Q24: =O24+P24 -> 15246.47 | R24: =X24*50% -> 3051.735 | S24: =K24*50% -> 4571.5 | T24: =R24+S24 -> 7623.235 | U24: =R24 -> 3051.735 | V24: =K24*50% -> 4571.5 | W24: =U24+V24 -> 7623.235 | X24: =6103.47 -> 6103.47 | Y24: =T24+W24 -> 15246.47
A25: 19 | B25: Walker And Royce | C25: 5 | D25: 43609 | E25: =D25 -> 43609 | F25: 829 | G25: 800 | H25: =IFERROR(F25/G25,"") -> 1.03625 | I25: 24387.5 | J25: =IFERROR(I25/F25,"") -> 29.417973 | K25: 22313.5 | L25: =IFERROR(K25/F25,"") -> 26.916164 | M25: 11725 | N25: =IFERROR(M25/I25,"") -> 0.48077909 | O25: =R25+U25 -> 5411.33 | P25: =S25+V25 -> 22313.5 | Q25: =O25+P25 -> 27724.83 | R25: =X25*50% -> 2705.665 | S25: =K25*50% -> 11156.75 | T25: =R25+S25 -> 13862.415 | U25: =R25 -> 2705.665 | V25: =K25*50% -> 11156.75 | W25: =U25+V25 -> 13862.415 | X25: 5411.33 | Y25: =T25+W25 -> 27724.83 | AB25: -2400
A26: 20 | B26: Detroit Love | C26: 5 | D26: 43610 | E26: =D26 -> 43610 | F26: 844 | G26: 800 | H26: =IFERROR(F26/G26,"") -> 1.055 | I26: 31245.5 | J26: =IFERROR(I26/F26,"") -> 37.020735 | K26: 15188.5 | L26: =IFERROR(K26/F26,"") -> 17.995853 | M26: 15000 | N26: =IFERROR(M26/I26,"") -> 0.48006913 | O26: =R26+U26 -> 9483.94 | P26: =S26+V26 -> 15188.5 | Q26: =O26+P26 -> 24672.44 | R26: =X26*50% -> 4741.97 | S26: =K26*50% -> 7594.25 | T26: =R26+S26 -> 12336.22 | U26: =R26 -> 4741.97 | V26: =K26*50% -> 7594.25 | W26: =U26+V26 -> 12336.22 | X26: 9483.94 | Y26: =T26+W26 -> 24672.44 | AB26: =AB22+AB23+AB25 -> 4239.72
A27: 21 | B27: Origins | C27: 5 | D27: 43611 | E27: =D27 -> 43611 | F27: 823 | G27: 800 | H27: =IFERROR(F27/G27,"") -> 1.02875 | I27: 29160.5 | J27: =IFERROR(I27/F27,"") -> 35.431956 | K27: 13424.5 | L27: =IFERROR(K27/F27,"") -> 16.311665 | M27: 12000 | N27: =IFERROR(M27/I27,"") -> 0.41151558 | O27: =R27+U27 -> 10680.97 | P27: =S27+V27 -> 13424.5 | Q27: =O27+P27 -> 24105.47 | R27: =X27*50% -> 5340.485 | S27: =K27*50% -> 6712.25 | T27: =R27+S27 -> 12052.735 | U27: =R27 -> 5340.485 | V27: =K27*50% -> 6712.25 | W27: =U27+V27 -> 12052.735 | X27: 10680.97 | Y27: =T27+W27 -> 24105.47 | AB27: =AB26/2 -> 2119.86
A28: 22 | B28: Repopulate Mars | C28: 5 | D28: 43612 | E28: =D28 -> 43612 | F28: 919 | G28: 800 | H28: =IFERROR(F28/G28,"") -> 1.14875 | I28: 33122 | J28: =IFERROR(I28/F28,"") -> 36.041349 | K28: 14128.5 | L28: =IFERROR(K28/F28,"") -> 15.373776 | M28: 12500 | N28: =IFERROR(M28/I28,"") -> 0.37739267 | O28: =R28+U28 -> 13403.32 | P28: =S28+V28 -> 14128.5 | Q28: =O28+P28 -> 27531.82 | R28: =X28*50% -> 6701.66 | S28: =K28*50% -> 7064.25 | T28: =R28+S28 -> 13765.91 | U28: =R28 -> 6701.66 | V28: =K28*50% -> 7064.25 | W28: =U28+V28 -> 13765.91 | X28: 13403.32 | Y28: =T28+W28 -> 27531.82
A29: 23 | B29: Goopsteppa [partial free tixs] | C29: 8 | D29: 43617 | E29: =D29 -> 43617 | F29: 252 | G29: 800 | H29: =IFERROR(F29/G29,"") -> 0.315 | I29: 2162.5 | J29: =IFERROR(I29/F29,"") -> 8.5813492 | K29: 3595 | L29: =IFERROR(K29/F29,"") -> 14.265873 | M29: =1250+425 -> 1675 | N29: =IFERROR(M29/I29,"") -> 0.77456647 | O29: =R29+U29 -> -1164.66 | P29: =S29+V29 -> 3595 | Q29: =O29+P29 -> 2430.34 | R29: =X29*50% -> -582.33 | S29: =K29*50% -> 1797.5 | T29: =R29+S29 -> 1215.17 | U29: =R29 -> -582.33 | V29: =K29*50% -> 1797.5 | W29: =U29+V29 -> 1215.17 | X29: -1164.66 | Y29: =T29+W29 -> 2430.34
A30: 24 | B30: If Walls Could Talk [band rental] | C30: 5 | D30: 43631 | E30: =D30 -> 43631 | F30: 286 | G30: 600 | H30: =IFERROR(F30/G30,"") -> 0.47666667 | I30: =780 -> 780 | J30: =IFERROR(I30/F30,"") -> 2.7272727 | K30: 2748 | L30: =IFERROR(K30/F30,"") -> 9.6083916 | M30: 0 | N30: =IFERROR(M30/I30,"") -> 0 | O30: =R30+U30 -> -383 | P30: =S30+V30 -> 2748 | Q30: =O30+P30 -> 2365 | R30: =X30*50% -> -191.5 | S30: =K30*50% -> 1374 | T30: =R30+S30 -> 1182.5 | U30: =R30 -> -191.5 | V30: =K30*50% -> 1374 | W30: =U30+V30 -> 1182.5 | X30: -383 | Y30: =T30+W30 -> 2365
A31: 25 | B31: Dub Down | C31: 1 | D31: 43659 | E31: =D31 -> 43659 | F31: 329 | G31: 700 | H31: =IFERROR(F31/G31,"") -> 0.47 | I31: 6575 | J31: =IFERROR(I31/F31,"") -> 19.984802 | K31: 5856 | L31: =IFERROR(K31/F31,"") -> 17.799392 | M31: =1250+1000+1000+1000+400 -> 4650 | N31: =IFERROR(M31/I31,"") -> 0.70722433 | O31: =R31+U31 -> -1431.28 | P31: =S31+V31 -> 5856 | Q31: =O31+P31 -> 4424.72 | R31: =X31*50% -> -715.64 | S31: =K31*50% -> 2928 | T31: =R31+S31 -> 2212.36 | U31: =R31 -> -715.64 | V31: =K31*50% -> 2928 | W31: =U31+V31 -> 2212.36 | X31: -1431.28 | Y31: =T31+W31 -> 4424.72
A32: 26 | B32: Louis Prima Jr. | C32: 3 | D32: 43671 | E32: =D32 -> 43671 | F32: 46 | G32: 700 | H32: =IFERROR(F32/G32,"") -> 0.065714286 | I32: =1020+98.5 -> 1118.5 | J32: =IFERROR(I32/F32,"") -> 24.315217 | K32: 317.9 | L32: =IFERROR(K32/F32,"") -> 6.9108696 | M32: 1500 | N32: =IFERROR(M32/I32,"") -> 1.3410818 | O32: =R32+U32 -> -2073.41 | P32: =S32+V32 -> 317.9 | Q32: =O32+P32 -> -1755.51 | R32: =(X32+AA32-AB32)*50% -> -1036.705 | S32: =K32*50% -> 158.95 | T32: =R32+S32 -> -877.755 | U32: =R32 -> -1036.705 | V32: =K32*50% -> 158.95 | W32: =U32+V32 -> -877.755 | X32: -2171.91 | Y32: =T32+W32 -> -1755.51 | AA32: 98.5 | AD32: =I32 -> 1118.5
A33: 27 | B33: Stick to your Guns | C33: 3 | D33: 43672 | E33: =D33 -> 43672 | F33: 439 | G33: 700 | H33: =IFERROR(F33/G33,"") -> 0.62714286 | I33: =8226+AA33 -> 9392 | J33: =IFERROR(I33/F33,"") -> 21.394077 | K33: 4401 | L33: =IFERROR(K33/F33,"") -> 10.025057 | M33: 7000 | N33: =IFERROR(M33/I33,"") -> 0.74531516 | O33: =R33+U33 -> -873.63 | P33: =S33+V33 -> 4401 | Q33: =O33+P33 -> 3527.37 | R33: =(X33+AA33-AB33)*50% -> -436.815 | S33: =K33*50% -> 2200.5 | T33: =R33+S33 -> 1763.685 | U33: =R33 -> -436.815 | V33: =K33*50% -> 2200.5 | W33: =U33+V33 -> 1763.685 | X33: =-2039.63 -> -2039.63 | Y33: =T33+W33 -> 3527.37 | AA33: =881+285 -> 1166 | AD33: =R33+U33 -> -873.63
A34: 28 | B34: Zebbler Encanti Experience | C34: 8 | D34: 43673 | E34: =D34 -> 43673 | F34: 249 | G34: 700 | H34: =IFERROR(F34/G34,"") -> 0.35571429 | I34: 5006.25 | J34: =IFERROR(I34/F34,"") -> 20.105422 | K34: 2976 | L34: =IFERROR(K34/F34,"") -> 11.951807 | M34: 2900 | N34: =IFERROR(M34/I34,"") -> 0.57927591 | O34: =R34+U34 -> -359.2 | P34: =S34+V34 -> 2976 | Q34: =O34+P34 -> 2616.8 | R34: =(X34+AA34-AB34)*50% -> -179.6 | S34: =K34*50% -> 1488 | T34: =R34+S34 -> 1308.4 | U34: =R34 -> -179.6 | V34: =K34*50% -> 1488 | W34: =U34+V34 -> 1308.4 | X34: -359.2
A35: 29 | B35: Mr. Bill | C35: 8 | D35: 43680 | E35: =D35 -> 43680 | F35: 306 | G35: 700 | H35: =IFERROR(F35/G35,"") -> 0.43714286 | I35: 5794.25 | J35: =IFERROR(I35/F35,"") -> 18.935458 | K35: 4634 | L35: =IFERROR(K35/F35,"") -> 15.143791 | M35: 4400 | N35: =IFERROR(M35/I35,"") -> 0.75937352 | O35: =R35+U35 -> -1326.82 | P35: =S35+V35 -> 4634 | Q35: =O35+P35 -> 3307.18 | R35: =(X35+AA35-AB35)*50% -> -663.41 | S35: =K35*50% -> 2317 | T35: =R35+S35 -> 1653.59 | U35: =R35 -> -663.41 | V35: =K35*50% -> 2317 | W35: =U35+V35 -> 1653.59 | X35: -1326.82
A36: 30 | B36: Solardo | C36: 5 | D36: 43686 | E36: =D36 -> 43686 | F36: 373 | G36: 700 | H36: =IFERROR(F36/G36,"") -> 0.53285714 | I36: 7918.5 | J36: =IFERROR(I36/F36,"") -> 21.229223 | K36: 8868 | L36: =IFERROR(K36/F36,"") -> 23.774799 | M36: 5450 | N36: =IFERROR(M36/I36,"") -> 0.68826167 | O36: =R36+U36 -> -1515.91 | P36: =S36+V36 -> 8868 | Q36: =O36+P36 -> 7352.09 | R36: =(X36+AA36-AB36)*50% -> -757.955 | S36: =K36*50% -> 4434 | T36: =R36+S36 -> 3676.045 | U36: =R36 -> -757.955 | V36: =K36*50% -> 4434 | W36: =U36+V36 -> 3676.045 | X36: -1515.91
A37: 31 | B37: Why? | C37: 1 | D37: 43693 | E37: =D37 -> 43693 | F37: 156 | G37: 700 | H37: =IFERROR(F37/G37,"") -> 0.22285714 | I37: 3329.5 | J37: =IFERROR(I37/F37,"") -> 21.342949 | K37: 1971 | L37: =IFERROR(K37/F37,"") -> 12.634615 | M37: 4850 | N37: =IFERROR(M37/I37,"") -> 1.4566752 | O37: =R37+U37 -> -3924.69 | P37: =S37+V37 -> 1971 | Q37: =O37+P37 -> -1953.69 | R37: =(X37+AA37-AB37)*50% -> -1962.345 | S37: =K37*50% -> 985.5 | T37: =R37+S37 -> -976.845 | U37: =R37 -> -1962.345 | V37: =K37*50% -> 985.5 | W37: =U37+V37 -> -976.845 | X37: -3924.69
A38: 32 | B38: Polo G | C38: 2 | D38: 43705 | E38: =D38 -> 43705 | F38: 593 | G38: 800 | H38: =IFERROR(F38/G38,"") -> 0.74125 | I38: =19845+2537.75 -> 22382.75 | J38: =IFERROR(I38/F38,"") -> 37.744941 | K38: 1593 | L38: =IFERROR(K38/F38,"") -> 2.6863406 | M38: 11500 | N38: =IFERROR(M38/I38,"") -> 0.51378852 | O38: =R38+U38 -> 567.2 | P38: =S38+V38 -> 1593 | Q38: =O38+P38 -> 2160.2 | R38: =(X38+AA38-AB38)*50% -> 283.6 | S38: =K38*50% -> 796.5 | T38: =R38+S38 -> 1080.1 | U38: =R38 -> 283.6 | V38: =K38*50% -> 796.5 | W38: =U38+V38 -> 1080.1 | X38: -191.55 | Y38: =T38+W38 -> 2160.2 | AA38: =1562.75+510+465 -> 2537.75 | AB38: 1779
A39: 33 | B39: Jessica Hernandez & The Deltas | C39: 3 | D39: 43707 | E39: =D39 -> 43707 | F39: 261 | G39: 600 | H39: =IFERROR(F39/G39,"") -> 0.435 | I39: 4671 | J39: =IFERROR(I39/F39,"") -> 17.896552 | K39: 4031 | L39: =IFERROR(K39/F39,"") -> 15.444444 | M39: 5050 | N39: =IFERROR(M39/I39,"") -> 1.0811389 | O39: =R39+U39 -> -2665.01 | P39: =S39+V39 -> 4031 | Q39: =O39+P39 -> 1365.99 | R39: =(X39+AA39-AB39)*50% -> -1332.505 | S39: =K39*50% -> 2015.5 | T39: =R39+S39 -> 682.995 | U39: =R39 -> -1332.505 | V39: =K39*50% -> 2015.5 | W39: =U39+V39 -> 682.995 | X39: -2890.76 | AA39: =326.75+160 -> 486.75 | AB39: 261
A40: 34 | B40: Golden Features | C40: 2 | D40: 43713 | E40: =D40 -> 43713 | F40: 44 | G40: 700 | H40: =IFERROR(F40/G40,"") -> 0.062857143 | I40: =489+AA40 -> 587.5 | J40: =IFERROR(I40/F40,"") -> 13.352273 | K40: 580 | L40: =IFERROR(K40/F40,"") -> 13.181818 | M40: 1200 | N40: =IFERROR(M40/I40,"") -> 2.0425532 | O40: =R40+U40 -> -1911.52 | P40: =S40+V40 -> 580 | Q40: =O40+P40 -> -1331.52 | R40: =(X40+AA40-AB40)*50% -> -955.76 | S40: =K40*50% -> 290 | T40: =R40+S40 -> -665.76 | U40: =R40 -> -955.76 | V40: =K40*50% -> 290 | W40: =U40+V40 -> -665.76 | X40: -1878.02 | AA40: 98.5 | AB40: 132
A41: 35 | B41: BoomBox | C41: 2 | D41: 43715 | E41: =D41 -> 43715 | F41: 591 | G41: 850 | H41: =IFERROR(F41/G41,"") -> 0.69529412 | I41: =13280+AA41 -> 14479.5 | J41: =IFERROR(I41/F41,"") -> 24.5 | K41: 13713 | L41: =IFERROR(K41/F41,"") -> 23.203046 | M41: 10750 | N41: =IFERROR(M41/I41,"") -> 0.74242895 | O41: =R41+U41 -> -994.47 | P41: =S41+V41 -> 13713 | Q41: =O41+P41 -> 12718.53 | R41: =(X41+AA41-AB41)*50% -> -497.235 | S41: =K41*50% -> 6856.5 | T41: =R41+S41 -> 6359.265 | U41: =R41 -> -497.235 | V41: =K41*50% -> 6856.5 | W41: =U41+V41 -> 6359.265 | X41: -420.97 | AA41: 1199.5 | AB41: 1773
A42: 36 | B42: Sacha Robotti | C42: 5 | D42: 43721 | E42: =D42 -> 43721 | F42: 284 | G42: 700 | H42: =IFERROR(F42/G42,"") -> 0.40571429 | I42: 5387 | J42: =IFERROR(I42/F42,"") -> 18.96831 | K42: 6149 | L42: =IFERROR(K42/F42,"") -> 21.651408 | M42: 3400 | N42: =IFERROR(M42/I42,"") -> 0.63114906 | O42: =R42+U42 -> -1535.36 | P42: =S42+V42 -> 6149 | Q42: =O42+P42 -> 4613.64 | R42: =(X42+AA42-AB42)*50% -> -767.68 | S42: =K42*50% -> 3074.5 | T42: =R42+S42 -> 2306.82 | U42: =R42 -> -767.68 | V42: =K42*50% -> 3074.5 | W42: =U42+V42 -> 2306.82 | X42: -1535.36
A43: 37 | B43: Kursa B2B Seppa | C43: 8 | D43: 43722 | E43: =D43 -> 43722 | F43: 350 | G43: 750 | H43: =IFERROR(F43/G43,"") -> 0.46666667 | I43: 7013.75 | J43: =IFERROR(I43/F43,"") -> 20.039286 | K43: 5611 | L43: =IFERROR(K43/F43,"") -> 16.031429 | M43: 3650 | N43: =IFERROR(M43/I43,"") -> 0.52040634 | O43: =R43+U43 -> 680.98 | P43: =S43+V43 -> 5611 | Q43: =O43+P43 -> 6291.98 | R43: =(X43+AA43-AB43)*50% -> 340.49 | S43: =K43*50% -> 2805.5 | T43: =R43+S43 -> 3145.99 | U43: =R43 -> 340.49 | V43: =K43*50% -> 2805.5 | W43: =U43+V43 -> 3145.99 | X43: 680.98
A44: 38 | B44: Bury Your Dead | C44: 3 | D44: 43728 | E44: =D44 -> 43728 | F44: 132 | G44: 750 | H44: =IFERROR(F44/G44,"") -> 0.176 | I44: =2512+AA44 -> 2718.25 | J44: =IFERROR(I44/F44,"") -> 20.592803 | K44: 2181 | L44: =IFERROR(K44/F44,"") -> 16.522727 | M44: 3000 | N44: =IFERROR(M44/I44,"") -> 1.1036512 | O44: =R44+U44 -> -2935.25 | P44: =S44+V44 -> 2181 | Q44: =O44+P44 -> -754.25 | R44: =(X44+AA44-AB44)*50% -> -1467.625 | S44: =K44*50% -> 1090.5 | T44: =R44+S44 -> -377.125 | U44: =R44 -> -1467.625 | V44: =K44*50% -> 1090.5 | W44: =U44+V44 -> -377.125 | X44: -3009.5 | AA44: 206.25 | AB44: 132
A45: 39 | B45: Man Man | C45: 1 | D45: 43729 | E45: =D45 -> 43729 | F45: 254 | G45: 700 | H45: =IFERROR(F45/G45,"") -> 0.36285714 | I45: 5227.75 | J45: =IFERROR(I45/F45,"") -> 20.581693 | K45: 3294 | L45: =IFERROR(K45/F45,"") -> 12.968504 | M45: 3500 | N45: =IFERROR(M45/I45,"") -> 0.66950409 | O45: =R45+U45 -> -586.35 | P45: =S45+V45 -> 3294 | Q45: =O45+P45 -> 2707.65 | R45: =(X45+AA45-AB45)*50% -> -293.175 | S45: =K45*50% -> 1647 | T45: =R45+S45 -> 1353.825 | U45: =R45 -> -293.175 | V45: =K45*50% -> 1647 | W45: =U45+V45 -> 1353.825 | X45: -586.35
A46: 40 | B46: Defunk | C46: 2 | D46: 43730 | E46: =D46 -> 43730 | F46: 99 | G46: 700 | H46: =IFERROR(F46/G46,"") -> 0.14142857 | I46: =1359+AA46 -> 1536.25 | J46: =IFERROR(I46/F46,"") -> 15.517677 | K46: 1660 | L46: =IFERROR(K46/F46,"") -> 16.767677 | M46: 2600 | N46: =IFERROR(M46/I46,"") -> 1.6924329 | O46: =R46+U46 -> -2327.13 | P46: =S46+V46 -> 1660 | Q46: =O46+P46 -> -667.13 | R46: =(X46+AA46-AB46)*50% -> -1163.565 | S46: =K46*50% -> 830 | T46: =R46+S46 -> -333.565 | U46: =R46 -> -1163.565 | V46: =K46*50% -> 830 | W46: =U46+V46 -> -333.565 | X46: -2207.38 | AA46: 177.25 | AB46: 297
A47: 41 | B47: Kaskade | C47: 2 | D47: 43734 | E47: =D47 -> 43734 | F47: 850 | G47: 850 | H47: =IFERROR(F47/G47,"") -> 1 | I47: =29750+AA47 -> 33362.5 | J47: =IFERROR(I47/F47,"") -> 39.25 | K47: 24643 | L47: =IFERROR(K47/F47,"") -> 28.991765 | M47: 20531.5 | N47: =IFERROR(M47/I47,"") -> 0.61540652 | O47: =R47+U47 -> 2574.64 | P47: =S47+V47 -> 24643 | Q47: =O47+P47 -> 27217.64 | R47: =(X47+AA47-AB47)*50% -> 1287.32 | S47: =K47*50% -> 12321.5 | T47: =R47+S47 -> 13608.82 | U47: =R47 -> 1287.32 | V47: =K47*50% -> 12321.5 | W47: =U47+V47 -> 13608.82 | X47: 1512.14 | AA47: =3612.5 -> 3612.5 | AB47: 2550
A48: 42 | B48: SoDown | C48: 8 | D48: 43735 | E48: =D48 -> 43735 | F48: 352 | G48: 700 | H48: =IFERROR(F48/G48,"") -> 0.50285714 | I48: 7106 | J48: =IFERROR(I48/F48,"") -> 20.1875 | K48: 6681 | L48: =IFERROR(K48/F48,"") -> 18.980114 | M48: 5375 | N48: =IFERROR(M48/I48,"") -> 0.75640304 | O48: =R48+U48 -> -1783.72 | P48: =S48+V48 -> 6681 | Q48: =O48+P48 -> 4897.28 | R48: =(X48+AA48-AB48)*50% -> -891.86 | S48: =K48*50% -> 3340.5 | T48: =R48+S48 -> 2448.64 | U48: =R48 -> -891.86 | V48: =K48*50% -> 3340.5 | W48: =U48+V48 -> 2448.64 | X48: -1783.72
A49: 43 | B49: Hayden James | C49: 2 | D49: 43736 | E49: =D49 -> 43736 | F49: 656 | G49: 700 | H49: =IFERROR(F49/G49,"") -> 0.93714286 | I49: =11880+AA49 -> 13482.5 | J49: =IFERROR(I49/F49,"") -> 20.552591 | K49: 12570.97 | L49: =IFERROR(K49/F49,"") -> 19.163064 | M49: 5779.09 | N49: =IFERROR(M49/I49,"") -> 0.42863638 | O49: =R49+U49 -> 502.4 | P49: =S49+V49 -> 12570.97 | Q49: =O49+P49 -> 13073.37 | R49: =(X49+AA49-AB49)*50% -> 251.2 | S49: =K49*50% -> 6285.485 | T49: =R49+S49 -> 6536.685 | U49: =R49 -> 251.2 | V49: =K49*50% -> 6285.485 | W49: =U49+V49 -> 6536.685 | X49: 867.9 | AA49: 1602.5 | AB49: 1968
A50: 44 | B50: Emotional Oranges | C50: 4 | D50: 43742 | E50: =D50 -> 43742 | F50: 264 | G50: 700 | H50: =IFERROR(F50/G50,"") -> 0.37714286 | I50: 6839.75 | J50: =IFERROR(I50/F50,"") -> 25.908144 | K50: 2123 | L50: =IFERROR(K50/F50,"") -> 8.0416667 | M50: 7000 | N50: =IFERROR(M50/I50,"") -> 1.0234292 | O50: =R50+U50 -> -2996.91 | P50: =S50+V50 -> 2123 | Q50: =O50+P50 -> -873.91 | R50: =(X50+AA50-AB50)*50% -> -1498.455 | S50: =K50*50% -> 1061.5 | T50: =R50+S50 -> -436.955 | U50: =R50 -> -1498.455 | V50: =K50*50% -> 1061.5 | W50: =U50+V50 -> -436.955 | X50: -2996.91
A51: 45 | B51: Detox Unit | C51: 2 | D51: 43743 | E51: =D51 -> 43743 | F51: 304 | G51: 700 | H51: =IFERROR(F51/G51,"") -> 0.43428571 | I51: =5615+AA51 -> 6285.5 | J51: =IFERROR(I51/F51,"") -> 20.675987 | K51: 4802 | L51: =IFERROR(K51/F51,"") -> 15.796053 | M51: 4500 | N51: =IFERROR(M51/I51,"") -> 0.7159335 | O51: =R51+U51 -> -1863.09 | P51: =S51+V51 -> 4802 | Q51: =O51+P51 -> 2938.91 | R51: =(X51+AA51-AB51)*50% -> -931.545 | S51: =K51*50% -> 2401 | T51: =R51+S51 -> 1469.455 | U51: =R51 -> -931.545 | V51: =K51*50% -> 2401 | W51: =U51+V51 -> 1469.455 | X51: -1621.59 | AA51: 670.5 | AB51: 912
A52: 46 | B52: Moon Boots | C52: 2 | D52: 43748 | E52: =D52 -> 43748 | F52: 256 | G52: 700 | H52: =IFERROR(F52/G52,"") -> 0.36571429 | I52: =4770+AA52 -> 5406 | J52: =IFERROR(I52/F52,"") -> 21.117188 | K52: 4827 | L52: =IFERROR(K52/F52,"") -> 18.855469 | M52: 4850 | N52: =IFERROR(M52/I52,"") -> 0.89715131 | O52: =R52+U52 -> -1967.91 | P52: =S52+V52 -> 4827 | Q52: =O52+P52 -> 2859.09 | R52: =(X52+AA52-AB52)*50% -> -983.955 | S52: =K52*50% -> 2413.5 | T52: =R52+S52 -> 1429.545 | U52: =R52 -> -983.955 | V52: =K52*50% -> 2413.5 | W52: =U52+V52 -> 1429.545 | X52: -1835.91 | AA52: 636 | AB52: 768
A53: 47 | B53: Jamie Jones | C53: 5 | D53: 43749 | E53: =D53 -> 43749 | F53: 610 | G53: 700 | H53: =IFERROR(F53/G53,"") -> 0.87142857 | I53: 18453.75 | J53: =IFERROR(I53/F53,"") -> 30.252049 | K53: 16806.5 | L53: =IFERROR(K53/F53,"") -> 27.551639 | M53: 16100 | N53: =IFERROR(M53/I53,"") -> 0.8724514 | O53: =R53+U53 -> -3459 | P53: =S53+V53 -> 16806.5 | Q53: =O53+P53 -> 13347.5 | R53: =(X53+AA53-AB53)*50% -> -1729.5 | S53: =K53*50% -> 8403.25 | T53: =R53+S53 -> 6673.75 | U53: =R53 -> -1729.5 | V53: =K53*50% -> 8403.25 | W53: =U53+V53 -> 6673.75 | X53: -3459
A54: 48 | B54: Cofresi | C54: 8 | D54: 43750 | E54: =D54 -> 43750 | F54: 176 | G54: 700 | H54: =IFERROR(F54/G54,"") -> 0.25142857 | I54: 3251.5 | J54: =IFERROR(I54/F54,"") -> 18.474432 | K54: 3978 | L54: =IFERROR(K54/F54,"") -> 22.602273 | M54: 1925 | N54: =IFERROR(M54/I54,"") -> 0.59203445 | O54: =R54+U54 -> -2038.26 | P54: =S54+V54 -> 3978 | Q54: =O54+P54 -> 1939.74 | R54: =(X54+AA54-AB54)*50% -> -1019.13 | S54: =K54*50% -> 1989 | T54: =R54+S54 -> 969.87 | U54: =R54 -> -1019.13 | V54: =K54*50% -> 1989 | W54: =U54+V54 -> 969.87 | X54: -2038.26
A55: 49 | B55: Kero Kero Bonito | C55: 7 | D55: 43754 | E55: =D55 -> 43754 | F55: 427 | G55: 700 | H55: =IFERROR(F55/G55,"") -> 0.61 | I55: 8988.5 | J55: =IFERROR(I55/F55,"") -> 21.050351 | K55: 2115.5 | L55: =IFERROR(K55/F55,"") -> 4.9543326 | M55: 5500 | N55: =IFERROR(M55/I55,"") -> 0.61189297 | O55: =R55+U55 -> 450.29 | P55: =S55+V55 -> 2115.5 | Q55: =O55+P55 -> 2565.79 | R55: =(X55+AA55-AB55)*50% -> 225.145 | S55: =K55*50% -> 1057.75 | T55: =R55+S55 -> 1282.895 | U55: =R55 -> 225.145 | V55: =K55*50% -> 1057.75 | W55: =U55+V55 -> 1282.895 | X55: 450.29
A56: 50 | B56: The Trifinity | C56: 2 | D56: 43756 | E56: =D56 -> 43756 | F56: 318 | G56: 700 | H56: =IFERROR(F56/G56,"") -> 0.45428571 | I56: =5945+AA56 -> 6725.25 | J56: =IFERROR(I56/F56,"") -> 21.148585 | K56: 4165 | L56: =IFERROR(K56/F56,"") -> 13.097484 | M56: 4000 | N56: =IFERROR(M56/I56,"") -> 0.59477343 | O56: =R56+U56 -> -1194.42 | P56: =S56+V56 -> 4165 | Q56: =O56+P56 -> 2970.58 | R56: =(X56+AA56-AB56)*50% -> -597.21 | S56: =K56*50% -> 2082.5 | T56: =R56+S56 -> 1485.29 | U56: =R56 -> -597.21 | V56: =K56*50% -> 2082.5 | W56: =U56+V56 -> 1485.29 | X56: -1020.67 | AA56: 780.25 | AB56: 954
A57: 51 | B57: Shiba San X Walker & Royce | C57: 2 | D57: 43757 | E57: =D57 -> 43757 | F57: 806 | G57: 800 | H57: =IFERROR(F57/G57,"") -> 1.0075 | I57: =23215+AA57 -> 26088.75 | J57: =IFERROR(I57/F57,"") -> 32.368176 | K57: 24354 | L57: =IFERROR(K57/F57,"") -> 30.215881 | M57: 15100 | N57: =IFERROR(M57/I57,"") -> 0.57879354 | O57: =R57+U57 -> 1876.33 | P57: =S57+V57 -> 24354 | Q57: =O57+P57 -> 26230.33 | R57: =(X57+AA57-AB57)*50% -> 938.165 | S57: =K57*50% -> 12177 | T57: =R57+S57 -> 13115.165 | U57: =R57 -> 938.165 | V57: =K57*50% -> 12177 | W57: =U57+V57 -> 13115.165 | X57: 1420.58 | AA57: 2873.75 | AB57: 2418
A58: 52 | B58: Tiny Moving Parts | C58: 1 | D58: 43760 | E58: =D58 -> 43760 | F58: 191 | G58: 700 | H58: =IFERROR(F58/G58,"") -> 0.27285714 | I58: 3977.75 | J58: =IFERROR(I58/F58,"") -> 20.825916 | K58: 1914 | L58: =IFERROR(K58/F58,"") -> 10.020942 | M58: 6050 | N58: =IFERROR(M58/I58,"") -> 1.5209603 | O58: =R58+U58 -> -5059.27 | P58: =S58+V58 -> 1914 | Q58: =O58+P58 -> -3145.27 | R58: =(X58+AA58-AB58)*50% -> -2529.635 | S58: =K58*50% -> 957 | T58: =R58+S58 -> -1572.635 | U58: =R58 -> -2529.635 | V58: =K58*50% -> 957 | W58: =U58+V58 -> -1572.635 | X58: -5059.27
A59: 53 | B59: Of Montreal | C59: 4 | D59: 43761 | E59: =D59 -> 43761 | F59: 502 | G59: 700 | H59: =IFERROR(F59/G59,"") -> 0.71714286 | I59: 13140 | J59: =IFERROR(I59/F59,"") -> 26.175299 | K59: 4910.7 | L59: =IFERROR(K59/F59,"") -> 9.7822709 | M59: 6870.55 | N59: =IFERROR(M59/I59,"") -> 0.52287291 | O59: =R59+U59 -> 1255.08 | P59: =S59+V59 -> 4910.7 | Q59: =O59+P59 -> 6165.78 | R59: =(X59+AA59-AB59)*50% -> 627.54 | S59: =K59*50% -> 2455.35 | T59: =R59+S59 -> 3082.89 | U59: =R59 -> 627.54 | V59: =K59*50% -> 2455.35 | W59: =U59+V59 -> 3082.89 | X59: 1255.08
A60: 54 | B60: Truth | C60: 5 | D60: 43763 | E60: =D60 -> 43763 | F60: 358 | G60: 700 | H60: =IFERROR(F60/G60,"") -> 0.51142857 | I60: 7554.75 | J60: =IFERROR(I60/F60,"") -> 21.102654 | K60: 6296 | L60: =IFERROR(K60/F60,"") -> 17.586592 | M60: 5875 | N60: =IFERROR(M60/I60,"") -> 0.77765644 | O60: =R60+U60 -> -2171.36 | P60: =S60+V60 -> 6296 | Q60: =O60+P60 -> 4124.64 | R60: =(X60+AA60-AB60)*50% -> -1085.68 | S60: =K60*50% -> 3148 | T60: =R60+S60 -> 2062.32 | U60: =R60 -> -1085.68 | V60: =K60*50% -> 3148 | W60: =U60+V60 -> 2062.32 | X60: -2171.36
A61: 55 | B61: Leftover Crack | C61: 3 | D61: 43764 | E61: =D61 -> 43764 | F61: 522 | G61: 750 | H61: =IFERROR(F61/G61,"") -> 0.696 | I61: 11936.25 | J61: =IFERROR(I61/F61,"") -> 22.866379 | K61: 8734 | L61: =IFERROR(K61/F61,"") -> 16.731801 | M61: 5134.06 | N61: =IFERROR(M61/I61,"") -> 0.43012336 | O61: =R61+U61 -> 741.94 | P61: =S61+V61 -> 8734 | Q61: =O61+P61 -> 9475.94 | R61: =(X61+AA61-AB61)*50% -> 370.97 | S61: =K61*50% -> 4367 | T61: =R61+S61 -> 4737.97 | U61: =R61 -> 370.97 | V61: =K61*50% -> 4367 | W61: =U61+V61 -> 4737.97 | X61: 1657.92 | AA61: 580.27 | AB61: 1496.25
A62: 56 | B62: Chris Lorenzo | C62: 2 | D62: 43764 | E62: =D62 -> 43764 | F62: 428 | G62: 700 | H62: =IFERROR(F62/G62,"") -> 0.61142857 | I62: =8380+AA62 -> 9522.75 | J62: =IFERROR(I62/F62,"") -> 22.249416 | K62: 5025 | L62: =IFERROR(K62/F62,"") -> 11.740654 | M62: 5000 | N62: =IFERROR(M62/I62,"") -> 0.52505841 | O62: =R62+U62 -> 223.54 | P62: =S62+V62 -> 5025 | Q62: =O62+P62 -> 5248.54 | R62: =(X62+AA62-AB62)*50% -> 111.77 | S62: =K62*50% -> 2512.5 | T62: =R62+S62 -> 2624.27 | U62: =R62 -> 111.77 | V62: =K62*50% -> 2512.5 | W62: =U62+V62 -> 2624.27 | X62: 364.79 | AA62: 1142.75 | AB62: 1284
A63: 57 | B63: The Menzingers | C63: 4 | D63: 43765 | E63: =D63 -> 43765 | F63: 740 | G63: 700 | H63: =IFERROR(F63/G63,"") -> 1.0571429 | I63: 19746 | J63: =IFERROR(I63/F63,"") -> 26.683784 | K63: 9358 | L63: =IFERROR(K63/F63,"") -> 12.645946 | M63: =8000+3000+1000 -> 12000 | N63: =IFERROR(M63/I63,"") -> 0.60771802 | O63: =R63+U63 -> 1567.07 | P63: =S63+V63 -> 9358 | Q63: =O63+P63 -> 10925.07 | R63: =(X63+AA63-AB63)*50% -> 783.535 | S63: =K63*50% -> 4679 | T63: =R63+S63 -> 5462.535 | U63: =R63 -> 783.535 | V63: =K63*50% -> 4679 | W63: =U63+V63 -> 5462.535 | X63: 1567.07
A64: 58 | B64: Yotto | C64: 2 | D64: 43768 | E64: =D64 -> 43768 | F64: 169 | G64: 700 | H64: =IFERROR(F64/G64,"") -> 0.24142857 | I64: =2955+AA64 -> 3435.25 | J64: =IFERROR(I64/F64,"") -> 20.326923 | K64: 2404.25 | L64: =IFERROR(K64/F64,"") -> 14.226331 | M64: 3700 | N64: =IFERROR(M64/I64,"") -> 1.0770686 | O64: =R64+U64 -> -2236.84 | P64: =S64+V64 -> 2404.25 | Q64: =O64+P64 -> 167.41 | R64: =(X64+AA64-AB64)*50% -> -1118.42 | S64: =K64*50% -> 1202.125 | T64: =R64+S64 -> 83.705 | U64: =R64 -> -1118.42 | V64: =K64*50% -> 1202.125 | W64: =U64+V64 -> 83.705 | X64: -2210.09 | AA64: =338.25+142 -> 480.25 | AB64: 507
A65: 59 | B65: Sonny Federa | C65: 2 | D65: 43776 | E65: =D65 -> 43776 | F65: 464 | G65: 700 | H65: =IFERROR(F65/G65,"") -> 0.66285714 | I65: =10255+AA65 -> 11486 | J65: =IFERROR(I65/F65,"") -> 24.75431 | K65: 13037.72 | L65: =IFERROR(K65/F65,"") -> 28.098534 | M65: 7700 | N65: =IFERROR(M65/I65,"") -> 0.67038133 | O65: =R65+U65 -> -794.82 | P65: =S65+V65 -> 13037.72 | Q65: =O65+P65 -> 12242.9 | R65: =(X65+AA65-AB65)*50% -> -397.41 | S65: =K65*50% -> 6518.86 | T65: =R65+S65 -> 6121.45 | U65: =R65 -> -397.41 | V65: =K65*50% -> 6518.86 | W65: =U65+V65 -> 6121.45 | X65: -633.82 | AA65: 1231 | AB65: 1392
A66: 60 | B66: Solomun | C66: 5 | D66: 43777 | E66: =D66 -> 43777 | F66: 850 | G66: 850 | H66: =IFERROR(F66/G66,"") -> 1 | I66: 28845.75 | J66: =IFERROR(I66/F66,"") -> 33.936176 | K66: 25428 | L66: =IFERROR(K66/F66,"") -> 29.915294 | M66: =15000+450+4500 -> 19950 | N66: =IFERROR(M66/I66,"") -> 0.69160968 | O66: =R66+U66 -> -690.88 | P66: =S66+V66 -> 25428 | Q66: =O66+P66 -> 24737.12 | R66: =(X66+AA66-AB66)*50% -> -345.44 | S66: =K66*50% -> 12714 | T66: =R66+S66 -> 12368.56 | U66: =R66 -> -345.44 | V66: =K66*50% -> 12714 | W66: =U66+V66 -> 12368.56 | X66: -690.88
A67: 61 | B67: Chromeo | C67: 2 | D67: 43778 | E67: =D67 -> 43778 | F67: 740 | G67: 800 | H67: =IFERROR(F67/G67,"") -> 0.925 | I67: =19746+AA66 -> 19746 | J67: =IFERROR(I67/F67,"") -> 26.683784 | K67: 7640.5 | L67: =IFERROR(K67/F67,"") -> 10.325 | M67: 15100 | N67: =IFERROR(M67/I67,"") -> 0.76471184 | O67: =R67+U67 -> -4343.47 | P67: =S67+V67 -> 7640.5 | Q67: =O67+P67 -> 3297.03 | R67: =(X67+AA67-AB67)*50% -> -2171.735 | S67: =K67*50% -> 3820.25 | T67: =R67+S67 -> 1648.515 | U67: =R67 -> -2171.735 | V67: =K67*50% -> 3820.25 | W67: =U67+V67 -> 1648.515 | X67: -4257.22 | AA67: 960.75 | AB67: 1047
B76: (1) in-house
B77: (2) React co-pro
B78: (3) Black Iris
B79: (4) Good Show
B80: (5) Paxahau
B81: (6) Rental event
B82: (7) Party Store co-pro
B83: (8) Further Frequencies

Sheet Magic Stick-by Promoter
B2: ***MAGIC STICK RESULTS*** | O2: MAGIC STICK TOTALS | S2: PROMOTER AVERAGES
B3: Name | D3: Shows | E3: Shows & Rentals | F3: Tickets Sold | G3: Venue Capacity | H3: Capacity Rate | I3: Gross Ticket Revenue | J3: Avg. Ticket Price (including TW rebate) | K3: Bar Revenue | L3: Avg sale of alcohol per guest | M3: Band(s) guarantee | N3: % of Gross Ticket Revenue | O3: Gate Settlement Gain/(Loss) | P3: Bar Sales - 100% | Q3: Show Gross Proceeds (before COGS, Labor, & Facility Costs) | R3: % of Total Gross Proceeds | S3: Gate Settlement Gain/(Loss) | T3: Bar Sales - 50% | U3: Show Gross Proceeds (before COGS, Labor, & Facility Costs)
B4: TOTALS | D4: =SUM(D7:D16) -> 60 | E4: =SUM(E7:E16) -> 61 | F4: =SUM(F7:F81) -> 28952 | G4: =SUM(G7:G81) -> 43700 | I4: =SUM(I7:I81) -> 754923 | K4: =SUM(K7:K81) -> 523492.54 | M4: =SUM(M7:M81) -> 456312.56 | N4: =SUM(N7:N81) -> 4.5034474 | O4: =SUM(O7:O81) -> 31502.43 | P4: =SUM(P7:P81) -> 523492.54 | Q4: =SUM(Q7:Q81) -> 554994.97 | R4: =SUM(R7:R81) -> 1
B5: AVERAGES | F5: =F4/D4 -> 482.53333 | G5: =G4/D4 -> 728.33333 | H5: =F4/G4 -> 0.66251716 | I5: =I4/D4 -> 12582.05 | J5: =I4/F4 -> 26.074986 | K5: =K4/E4 -> 8581.8449 | L5: =K4/F4 -> 18.081395 | M5: =M4/D4 -> 7605.2093 | N5: =M4/I4 -> 0.60444914 | O5: =O4/E4 -> 516.43328 | P5: =P4/E4 -> 8581.8449 | Q5: =Q4/E4 -> 9098.2782
A7: 5 | B7: Paxahau | D7: =COUNTIF('Magic Stick'!C:C,A:A) -> 17 | E7: =COUNTIF('Magic Stick'!C:C,A:A) -> 17 | F7: =SUMIF('Magic Stick'!$C:$C,A:A,'Magic Stick'!$F:$F) -> 11482 | G7: =SUMIF('Magic Stick'!$C:$C,A:A,'Magic Stick'!$G:$G) -> 12750 | H7: =F7/G7 -> 0.90054902 | I7: =SUMIF('Magic Stick'!$C:$C,A:A,'Magic Stick'!$I:$I) -> 328000.25 | J7: =I7/F7 -> 28.566474 | K7: =SUMIF('Magic Stick'!$C:$C,A:A,'Magic Stick'!$K:$K) -> 243601 | L7: =K7/F7 -> 21.215903 | M7: =SUMIF('Magic Stick'!$C:$C,A:A,'Magic Stick'!$M:$M) -> 189825 | N7: =M7/I7 -> 0.57873431 | O7: =SUMIF('Magic Stick'!$C:$C,A:A,'Magic Stick'!$O:$O) -> 46327.56 | P7: =K7 -> 243601 | Q7: =O7+P7 -> 289928.56 | R7: =Q7/$Q$4 -> 0.52239854 | S7: =O7/E7 -> 2725.1506 | T7: =P7/E7 -> 14329.471 | U7: =S7+T7 -> 17054.621
A8: 2 | B8: React co-pro | D8: =COUNTIF('Magic Stick'!C:C,A:A) -> 18 | E8: =COUNTIF('Magic Stick'!C:C,A:A) -> 18 | F8: =SUMIF('Magic Stick'!$C:$C,A:A,'Magic Stick'!$F:$F) -> 8732 | G8: =SUMIF('Magic Stick'!$C:$C,A:A,'Magic Stick'!$G:$G) -> 13300 | H8: =F8/G8 -> 0.65654135 | I8: =SUMIF('Magic Stick'!$C:$C,A:A,'Magic Stick'!$I:$I) -> 233329.5 | J8: =I8/F8 -> 26.721198 | K8: =SUMIF('Magic Stick'!$C:$C,A:A,'Magic Stick'!$K:$K) -> 158583.94 | L8: =K8/F8 -> 18.161239 | M8: =SUMIF('Magic Stick'!$C:$C,A:A,'Magic Stick'!$M:$M) -> 139778.79 | N8: =M8/I8 -> 0.5990618 | O8: =SUMIF('Magic Stick'!$C:$C,A:A,'Magic Stick'!$O:$O) -> -9362.13 | P8: =K8 -> 158583.94 | Q8: =O8+P8 -> 149221.81 | R8: =Q8/$Q$4 -> 0.26887056 | S8: =O8/E8 -> -520.11833 | T8: =P8/E8 -> 8810.2189 | U8: =S8+T8 -> 8290.1006
A9: 4 | B9: Good Show | D9: =COUNTIF('Magic Stick'!C:C,A:A) -> 4 | E9: =COUNTIF('Magic Stick'!C:C,A:A) -> 4 | F9: =SUMIF('Magic Stick'!$C:$C,A:A,'Magic Stick'!$F:$F) -> 2143 | G9: =SUMIF('Magic Stick'!$C:$C,A:A,'Magic Stick'!$G:$G) -> 2800 | H9: =F9/G9 -> 0.76535714 | I9: =SUMIF('Magic Stick'!$C:$C,A:A,'Magic Stick'!$I:$I) -> 56152.75 | J9: =I9/F9 -> 26.20287 | K9: =SUMIF('Magic Stick'!$C:$C,A:A,'Magic Stick'!$K:$K) -> 25534.7 | L9: =K9/F9 -> 11.915399 | M9: =SUMIF('Magic Stick'!$C:$C,A:A,'Magic Stick'!$M:$M) -> 32699.71 | N9: =M9/I9 -> 0.58233497 | O9: =SUMIF('Magic Stick'!$C:$C,A:A,'Magic Stick'!$O:$O) -> 5928.71 | P9: =K9 -> 25534.7 | Q9: =O9+P9 -> 31463.41 | R9: =Q9/$Q$4 -> 0.056691343 | S9: =O9/E9 -> 1482.1775 | T9: =P9/E9 -> 6383.675 | U9: =S9+T9 -> 7865.8525
A10: 8 | B10: Further Frequencies | D10: =COUNTIF('Magic Stick'!C:C,A:A) -> 8 | E10: =COUNTIF('Magic Stick'!C:C,A:A) -> 8 | F10: =SUMIF('Magic Stick'!$C:$C,A:A,'Magic Stick'!$F:$F) -> 2900 | G10: =SUMIF('Magic Stick'!$C:$C,A:A,'Magic Stick'!$G:$G) -> 5750 | H10: =F10/G10 -> 0.50434783 | I10: =SUMIF('Magic Stick'!$C:$C,A:A,'Magic Stick'!$I:$I) -> 56980.25 | J10: =I10/F10 -> 19.648362 | K10: =SUMIF('Magic Stick'!$C:$C,A:A,'Magic Stick'!$K:$K) -> 45576.5 | L10: =K10/F10 -> 15.716034 | M10: =SUMIF('Magic Stick'!$C:$C,A:A,'Magic Stick'!$M:$M) -> 30975 | N10: =M10/I10 -> 0.54360941 | O10: =SUMIF('Magic Stick'!$C:$C,A:A,'Magic Stick'!$O:$O) -> 7822.91 | P10: =K10 -> 45576.5 | Q10: =O10+P10 -> 53399.41 | R10: =Q10/$Q$4 -> 0.096216025 | S10: =O10/E10 -> 977.86375 | T10: =P10/E10 -> 5697.0625 | U10: =S10+T10 -> 6674.9263
A11: 7 | B11: Party Store co-pro | D11: =COUNTIF('Magic Stick'!C:C,A:A) -> 1 | E11: =COUNTIF('Magic Stick'!C:C,A:A) -> 1 | F11: =SUMIF('Magic Stick'!$C:$C,A:A,'Magic Stick'!$F:$F) -> 427 | G11: =SUMIF('Magic Stick'!$C:$C,A:A,'Magic Stick'!$G:$G) -> 700 | H11: =F11/G11 -> 0.61 | I11: =SUMIF('Magic Stick'!$C:$C,A:A,'Magic Stick'!$I:$I) -> 8988.5 | J11: =I11/F11 -> 21.050351 | K11: =SUMIF('Magic Stick'!$C:$C,A:A,'Magic Stick'!$K:$K) -> 2115.5 | L11: =K11/F11 -> 4.9543326 | M11: =SUMIF('Magic Stick'!$C:$C,A:A,'Magic Stick'!$M:$M) -> 5500 | N11: =M11/I11 -> 0.61189297 | O11: =SUMIF('Magic Stick'!$C:$C,A:A,'Magic Stick'!$O:$O) -> 450.29 | P11: =K11 -> 2115.5 | Q11: =O11+P11 -> 2565.79 | R11: =Q11/$Q$4 -> 0.0046230869 | S11: =O11/E11 -> 450.29 | T11: =P11/E11 -> 2115.5 | U11: =S11+T11 -> 2565.79
A12: 3 | B12: Black Iris | D12: =COUNTIF('Magic Stick'!C:C,A:A) -> 5 | E12: =COUNTIF('Magic Stick'!C:C,A:A) -> 5 | F12: =SUMIF('Magic Stick'!$C:$C,A:A,'Magic Stick'!$F:$F) -> 1400 | G12: =SUMIF('Magic Stick'!$C:$C,A:A,'Magic Stick'!$G:$G) -> 3500 | H12: =F12/G12 -> 0.4 | I12: =SUMIF('Magic Stick'!$C:$C,A:A,'Magic Stick'!$I:$I) -> 29836 | J12: =I12/F12 -> 21.311429 | K12: =SUMIF('Magic Stick'!$C:$C,A:A,'Magic Stick'!$K:$K) -> 19664.9 | L12: =K12/F12 -> 14.046357 | M12: =SUMIF('Magic Stick'!$C:$C,A:A,'Magic Stick'!$M:$M) -> 21684.06 | N12: =M12/I12 -> 0.72677504 | O12: =SUMIF('Magic Stick'!$C:$C,A:A,'Magic Stick'!$O:$O) -> -7805.36 | P12: =K12 -> 19664.9 | Q12: =O12+P12 -> 11859.54 | R12: =Q12/$Q$4 -> 0.021368734 | S12: =O12/E12 -> -1561.072 | T12: =P12/E12 -> 3932.98 | U12: =S12+T12 -> 2371.908
A13: 6 | B13: Rental event | E13: =COUNTIF('Magic Stick'!C:C,A:A) -> 1 | K13: =SUMIF('Magic Stick'!$C:$C,A:A,'Magic Stick'!$K:$K) -> 2361 | O13: =SUMIF('Magic Stick'!$C:$C,A:A,'Magic Stick'!$O:$O) -> -120 | P13: =K13 -> 2361 | Q13: =O13+P13 -> 2241 | R13: =Q13/$Q$4 -> 0.0040378744 | S13: =O13/E13 -> -120 | T13: =P13/E13 -> 2361 | U13: =S13+T13 -> 2241
A14: 1 | B14: Magic Stick in-house | D14: =COUNTIF('Magic Stick'!C:C,A:A) -> 7 | E14: =COUNTIF('Magic Stick'!C:C,A:A) -> 7 | F14: =SUMIF('Magic Stick'!$C:$C,A:A,'Magic Stick'!$F:$F) -> 1868 | G14: =SUMIF('Magic Stick'!$C:$C,A:A,'Magic Stick'!$G:$G) -> 4900 | H14: =F14/G14 -> 0.38122449 | I14: =SUMIF('Magic Stick'!$C:$C,A:A,'Magic Stick'!$I:$I) -> 41635.75 | J14: =I14/F14 -> 22.288945 | K14: =SUMIF('Magic Stick'!$C:$C,A:A,'Magic Stick'!$K:$K) -> 26055 | L14: =K14/F14 -> 13.948073 | M14: =SUMIF('Magic Stick'!$C:$C,A:A,'Magic Stick'!$M:$M) -> 35850 | N14: =M14/I14 -> 0.86103889 | O14: =SUMIF('Magic Stick'!$C:$C,A:A,'Magic Stick'!$O:$O) -> -11739.55 | P14: =K14 -> 26055 | Q14: =O14+P14 -> 14315.45 | R14: =Q14/$Q$4 -> 0.025793837 | S14: =O14/E14 -> -1677.0786 | T14: =P14/E14 -> 3722.1429 | U14: =S14+T14 -> 2045.0643
