Workbook

Sheet Magic Stick
O1: VENUE TOTAL
B2: ***MAGIC STICK RESULTS*** | O2: MAGIC STICK
B3: Name | C3: Promoter Code | D3: Date | E3: Day of the week | F3: Tickets Sold | G3: Venue Capacity | H3: Capacity Rate | I3: Gross Ticket Revenue | J3: Avg. Ticket Price (including TW rebate) | K3: Bar Revenue | L3: Avg sale of alcohol per guest | M3: Band(s) guarantee | N3: % of Gross Ticket Revenue | O3: Gate Settlement Gain/(Loss) | P3: Bar Sales - 100% | Q3: Show Gross Proceeds (before COGS, Labor, & Facility Costs)
B4: TOTALS | F4: =SUM(F7:F114) -> 33013 | G4: =SUM(G7:G114) -> 76457 | I4: =SUM(I7:I114) -> 1139644.4 | K4: =SUM(K7:K114) -> 699964.5 | M4: =SUM(M7:M114) -> 624775.14 | N4: =SUM(N7:N114) -> 64.223711 | O4: =SUM(O7:O114) -> 112015.24 | P4: =SUM(P7:P114) -> 699964.5 | Q4: =SUM(Q7:Q114) -> 811979.74
B5: AVERAGES | F5: =F4/COUNTA(F7:F114) -> 383.87209 | G5: =G4/COUNTA(G7:G114) -> 764.57 | H5: =F4/G4 -> 0.43178519 | I5: =I4/COUNTA(I7:I114) -> 13251.679 | J5: =I4/F4 -> 34.521079 | K5: =K4/COUNTA(K7:K114) -> 8139.1221 | L5: =K4/F4 -> 21.202693 | M5: =M4/COUNTA(M7:M114) -> 7264.8272 | N5: =M4/I4 -> 0.54821938 | O5: =O4/COUNTA(O7:O114) -> 1333.5148 | P5: =P4/COUNTA(P7:P114) -> 8139.1221 | Q5: =Q4/COUNTA(Q7:Q114) -> 8119.7974
A7: 1 | B7: Omnom | C7: 5 | D7: 45682 | E7: =D7 -> 45682 | F7: 819 | G7: 800 | H7: =IFERROR(F7/G7,"") -> 1.02375 | I7: 24929 | J7: =IFERROR(I7/F7,"") -> 30.438339 | K7: 20096 | L7: =IFERROR(K7/F7,"") -> 24.537241 | M7: =(5000+200+200+200) -> 5600 | N7: =IFERROR(M7/I7,"") -> 0.22463797 | O7: 8948.87 | P7: =K7 -> 20096 | Q7: =SUM(O7:P7) -> 29044.87
A8: 2 | B8: Fulton Lee | C8: 1 | D8: 45686 | E8: =D8 -> 45686 | F8: 307 | G8: 800 | H8: =IFERROR(F8/G8,"") -> 0.38375 | I8: 10997 | J8: =IFERROR(I8/F8,"") -> 35.820847 | K8: 2601 | L8: =IFERROR(K8/F8,"") -> 8.4723127 | M8: =5750 -> 5750 | N8: =IFERROR(M8/I8,"") -> 0.52286987 | O8: 1712.63 | P8: =K8 -> 2601 | Q8: =O8+P8 -> 4313.63
A9: 3 | B9: DJ Pauly D | C9: 5 | D9: 45688 | E9: =D9 -> 45688 | F9: 905 | G9: 781 | H9: =IFERROR(F9/G9,"") -> 1.1587708 | I9: 49813.5 | J9: =IFERROR(I9/F9,"") -> 55.042541 | K9: 31248 | L9: =IFERROR(K9/F9,"") -> 34.528177 | M9: =(30000+1026+200+250+250) -> 31726 | N9: =IFERROR(M9/I9,"") -> 0.63689562 | O9: 10101.91 | P9: =K9 -> 31248 | Q9: =O9+P9 -> 41349.91
A10: 4 | B10: Ayybo | C10: 5 | D10: 45689 | E10: =D10 -> 45689 | F10: 932 | G10: 750 | H10: =IFERROR(F10/G10,"") -> 1.2426667 | I10: 26036 | J10: =IFERROR(I10/F10,"") -> 27.935622 | K10: 26954 | L10: =IFERROR(K10/F10,"") -> 28.920601 | M10: =(3000+200+200) -> 3400 | N10: =IFERROR(M10/I10,"") -> 0.13058842 | O10: 10339.67 | P10: =K10 -> 26954 | Q10: =O10+P10 -> 37293.67
A11: 5 | B11: J Worra | C11: 5 | D11: 45695 | E11: =D11 -> 45695 | F11: 425 | G11: 800 | H11: =IFERROR(F11/G11,"") -> 0.53125 | I11: 11313.5 | J11: =IFERROR(I11/F11,"") -> 26.62 | K11: 11968 | L11: =IFERROR(K11/F11,"") -> 28.16 | M11: =(7500+200+200) -> 7900 | N11: =IFERROR(M11/I11,"") -> 0.69828082 | O11: -1581.03 | P11: =K11 -> 11968 | Q11: =O11+P11 -> 10386.97
A12: 6 | B12: Girl Math | C12: 5 | D12: 45702 | E12: =D12 -> 45702 | F12: 413 | G12: 800 | H12: =IFERROR(F12/G12,"") -> 0.51625 | I12: 9819.5 | J12: =IFERROR(I12/F12,"") -> 23.776029 | K12: 9578 | L12: =IFERROR(K12/F12,"") -> 23.191283 | M12: =(3000+3000+300) -> 6300 | N12: =IFERROR(M12/I12,"") -> 0.64158053 | O12: -1958.41 | P12: =K12 -> 9578 | Q12: =O12+P12 -> 7619.59
A13: 7 | B13: Boombox | C13: 1 | D13: 45703 | E13: =D13 -> 45703 | F13: 400 | G13: 800 | H13: =IFERROR(F13/G13,"") -> 0.5 | I13: 9951.75 | J13: =IFERROR(I13/F13,"") -> 24.879375 | K13: 7801 | L13: =IFERROR(K13/F13,"") -> 19.5025 | M13: =(6500+300) -> 6800 | N13: =IFERROR(M13/I13,"") -> 0.68329691 | O13: -375.11 | P13: =K13 -> 7801 | Q13: =O13+P13 -> 7425.89
A14: 8 | B14: Nemahsis | C14: 1 | D14: 45704 | E14: =D14 -> 45704 | F14: 402 | G14: 814 | H14: =IFERROR(F14/G14,"") -> 0.49385749 | I14: 14492 | J14: =IFERROR(I14/F14,"") -> 36.049751 | K14: 1556 | L14: =IFERROR(K14/F14,"") -> 3.8706468 | M14: =7500+500 -> 8000 | N14: =IFERROR(M14/I14,"") -> 0.55202871 | O14: 2796.84 | P14: =K14 -> 1556 | Q14: =O14+P14 -> 4352.84
A15: 9 | B15: Foster the People | C15: 5 | D15: 45705 | E15: =D15 -> 45705 | F15: 192 | G15: 800 | H15: =IFERROR(F15/G15,"") -> 0.24 | I15: 5536.5 | J15: =IFERROR(I15/F15,"") -> 28.835938 | K15: 3244 | L15: =IFERROR(K15/F15,"") -> 16.895833 | M15: =(2766+200) -> 2966 | N15: =IFERROR(M15/I15,"") -> 0.53571751 | O15: -457.02 | P15: =K15 -> 3244 | Q15: =O15+P15 -> 2786.98
A16: 10 | B16: Third Prty | C16: 2 | D16: 45709 | E16: =D16 -> 45709 | F16: 197 | G16: 800 | H16: =IFERROR(F16/G16,"") -> 0.24625 | I16: 5165.25 | J16: =IFERROR(I16/F16,"") -> 26.219543 | K16: 7279 | L16: =IFERROR(K16/F16,"") -> 36.949239 | M16: =(4000+350+200+150) -> 4700 | N16: =IFERROR(M16/I16,"") -> 0.90992692 | O16: -2227.39 | P16: =K16 -> 7279 | Q16: =O16+P16 -> 5051.61
A17: 11 | B17: JSTJR | C17: 2 | D17: 45710 | E17: =D17 -> 45710 | F17: 339 | G17: 800 | H17: =IFERROR(F17/G17,"") -> 0.42375 | I17: 10013.25 | J17: =IFERROR(I17/F17,"") -> 29.537611 | K17: 7400 | L17: =IFERROR(K17/F17,"") -> 21.828909 | M17: =(5000+300+250+150) -> 5700 | N17: =IFERROR(M17/I17,"") -> 0.56924575 | O17: 1129.18 | P17: =K17 -> 7400 | Q17: =O17+P17 -> 8529.18
A18: 12 | B18: LF System | C18: 2 | D18: 45717 | E18: =D18 -> 45717 | G18: 750 | H18: =IFERROR(F18/G18,"") -> 0 | J18: =IFERROR(I18/F18,"") | L18: =IFERROR(K18/F18,"") | N18: =IFERROR(M18/I18,"") | P18: =K18 | Q18: =O18+P18 -> 0
A19: 13 | B19: Paul van Dyk | C19: 5 | D19: 45730 | E19: =D19 -> 45730 | F19: 591 | G19: 800 | H19: =IFERROR(F19/G19,"") -> 0.73875 | I19: 17304 | J19: =IFERROR(I19/F19,"") -> 29.279188 | K19: 12779 | L19: =IFERROR(K19/F19,"") -> 21.622673 | M19: =10000 -> 10000 | N19: =IFERROR(M19/I19,"") -> 0.57790106 | O19: 1830.67 | P19: =K19 -> 12779 | Q19: =O19+P19 -> 14609.67
A20: 14 | B20: Dino Munaco | D20: 45731 | E20: =D20 -> 45731 | F20: 153 | G20: 750 | H20: =IFERROR(F20/G20,"") -> 0.204 | I20: 3470.5 | J20: =IFERROR(I20/F20,"") -> 22.683007 | K20: 4636 | L20: =IFERROR(K20/F20,"") -> 30.300654 | M20: =(500+700) -> 1200 | N20: =IFERROR(M20/I20,"") -> 0.3457715 | O20: 798.47 | P20: =K20 -> 4636 | Q20: =O20+P20 -> 5434.47
A21: 15 | B21: Qrion | C21: 5 | D21: 45737 | E21: =D21 -> 45737 | F21: 140 | G21: 800 | H21: =IFERROR(F21/G21,"") -> 0.175 | I21: 2678 | J21: =IFERROR(I21/F21,"") -> 19.128571 | K21: 2262 | L21: =IFERROR(K21/F21,"") -> 16.157143 | M21: =(2000+200+200) -> 2400 | N21: =IFERROR(M21/I21,"") -> 0.89619119 | O21: -2346.71 | P21: =K21 -> 2262 | Q21: =O21+P21 -> -84.71
A22: 16 | B22: Nora en Pure | C22: 5 | D22: 45744 | E22: =D22 -> 45744 | F22: 741 | G22: 750 | H22: =IFERROR(F22/G22,"") -> 0.988 | I22: 33729 | J22: =IFERROR(I22/F22,"") -> 45.518219 | K22: 18889 | L22: =IFERROR(K22/F22,"") -> 25.491228 | M22: =(25000+200+200) -> 25400 | N22: =IFERROR(M22/I22,"") -> 0.75306116 | O22: -513.1 | P22: =K22 -> 18889 | Q22: =O22+P22 -> 18375.9
A23: 17 | B23: Kaaze | C23: 2 | D23: 45369 | E23: =D23 -> 45369 | F23: 242 | G23: 750 | H23: =IFERROR(F23/G23,"") -> 0.32266667 | I23: 6432.25 | J23: =IFERROR(I23/F23,"") -> 26.579545 | K23: 5790 | L23: =IFERROR(K23/F23,"") -> 23.92562 | M23: =(5000+400+350) -> 5750 | N23: =IFERROR(M23/I23,"") -> 0.89393292 | O23: -2088.85 | P23: =K23 -> 5790 | Q23: =O23+P23 -> 3701.15
A24: 18 | B24: Marie Vaunt | C24: 2 | D24: 45751 | E24: =D24 -> 45751 | F24: 169 | G24: 1503 | H24: =IFERROR(F24/G24,"") -> 0.11244178 | I24: 4131.75 | J24: =IFERROR(I24/F24,"") -> 24.448225 | K24: 3327 | L24: =IFERROR(K24/F24,"") -> 19.686391 | M24: =(3500+300+200) -> 4000 | N24: =IFERROR(M24/I24,"") -> 0.96811279 | O24: -2789.39 | P24: =K24 -> 3327 | Q24: =O24+P24 -> 537.61
A25: 19 | B25: KC Lights | C25: 2 | D25: 45752 | E25: =D25 -> 45752 | F25: 271 | G25: 750 | H25: =IFERROR(F25/G25,"") -> 0.36133333 | I25: 6463 | J25: =IFERROR(I25/F25,"") -> 23.848708 | K25: 7878 | L25: =IFERROR(K25/F25,"") -> 29.070111 | M25: =(3500+1750+250+150) -> 5650 | N25: =IFERROR(M25/I25,"") -> 0.87420702 | O25: -2896.22 | P25: =K25 -> 7878 | Q25: =O25+P25 -> 4981.78
A26: 20 | B26: No Thanks | C26: 2 | D26: 45758 | E26: =D26 -> 45758 | F26: 170 | G26: 800 | H26: =IFERROR(F26/G26,"") -> 0.2125 | I26: 2327 | J26: =IFERROR(I26/F26,"") -> 13.688235 | K26: 3199 | L26: =IFERROR(K26/F26,"") -> 18.817647 | M26: =(3000+300+200) -> 3500 | N26: =IFERROR(M26/I26,"") -> 1.5040825 | O26: -3340.79 | P26: =K26 -> 3199 | Q26: =O26+P26 -> -141.79
A27: 21 | B27: Afrobeats to the World | C27: 1 | D27: 45759 | E27: =D27 -> 45759 | F27: 738 | G27: 800 | H27: =IFERROR(F27/G27,"") -> 0.9225 | I27: 21580 | J27: =IFERROR(I27/F27,"") -> 29.241192 | K27: 14283 | L27: =IFERROR(K27/F27,"") -> 19.353659 | M27: =16422 -> 16422 | N27: =IFERROR(M27/I27,"") -> 0.76098239 | O27: 2769.9 | P27: =K27 -> 14283 | Q27: =O27+P27 -> 17052.9
A28: 22 | B28: Ranger Trucco | C28: 5 | D28: 45766 | E28: =D28 -> 45766 | F28: 386 | G28: 750 | H28: =IFERROR(F28/G28,"") -> 0.51466667 | I28: 9980 | J28: =IFERROR(I28/F28,"") -> 25.854922 | K28: 9990 | L28: =IFERROR(K28/F28,"") -> 25.880829 | M28: 5000 | N28: =IFERROR(M28/I28,"") -> 0.501002 | O28: -49.74 | P28: =K28 -> 9990 | Q28: =O28+P28 -> 9940.26
A29: 23 | B29: Cristoph | C29: 5 | D29: 45772 | E29: =D29 -> 45772 | F29: 294 | G29: 750 | H29: =IFERROR(F29/G29,"") -> 0.392 | I29: 8409 | J29: =IFERROR(I29/F29,"") -> 28.602041 | K29: 7098 | L29: =IFERROR(K29/F29,"") -> 24.142857 | M29: 5000 | N29: =IFERROR(M29/I29,"") -> 0.59460102 | O29: -1382.41 | P29: =K29 -> 7098 | Q29: =O29+P29 -> 5715.59
A30: 24 | B30: Desert Hearts | C30: 5 | D30: 45773 | E30: =D30 -> 45773 | F30: 466 | G30: 750 | H30: =IFERROR(F30/G30,"") -> 0.62133333 | I30: 13895.75 | J30: =IFERROR(I30/F30,"") -> 29.819206 | K30: 12756 | L30: =IFERROR(K30/F30,"") -> 27.373391 | M30: =(2500+2500+2500) -> 7500 | N30: =IFERROR(M30/I30,"") -> 0.53973337 | O30: -2479.68 | P30: =K30 -> 12756 | Q30: =O30+P30 -> 10276.32
A31: 25 | B31: G-Space | C31: 5 | D31: 45780 | E31: =D31 -> 45780 | F31: 101 | G31: 754 | H31: =IFERROR(F31/G31,"") -> 0.13395225 | I31: 2492.5 | J31: =IFERROR(I31/F31,"") -> 24.678218 | K31: 2614 | L31: =IFERROR(K31/F31,"") -> 25.881188 | M31: =(3000+1000+500+150) -> 4650 | N31: =IFERROR(M31/I31,"") -> 1.8655968 | O31: 4030.77 | P31: =K31 -> 2614 | Q31: =O31+P31 -> 6644.77
A32: 26 | B32: Iann Dior | C32: 1 | D32: 45781 | E32: =D32 -> 45781 | F32: 228 | G32: 750 | H32: =IFERROR(F32/G32,"") -> 0.304 | I32: 11855.25 | J32: =IFERROR(I32/F32,"") -> 51.996711 | K32: 1736 | L32: =IFERROR(K32/F32,"") -> 7.6140351 | M32: =(6000+500) -> 6500 | N32: =IFERROR(M32/I32,"") -> 0.5482803 | O32: -2158.27 | P32: =K32 -> 1736 | Q32: =O32+P32 -> -422.27
A33: 27 | B33: Mereba | C33: 1 | D33: 45784 | E33: =D33 -> 45784 | F33: 314 | G33: 800 | H33: =IFERROR(F33/G33,"") -> 0.3925 | I33: 9547.5 | J33: =IFERROR(I33/F33,"") -> 30.406051 | K33: 2803 | L33: =IFERROR(K33/F33,"") -> 8.9267516 | M33: =3500+500 -> 4000 | N33: =IFERROR(M33/I33,"") -> 0.41895784 | O33: 2093.17 | P33: =K33 -> 2803 | Q33: =O33+P33 -> 4896.17
A34: 28 | B34: Klangkarussell | C34: 2 | D34: 45785 | E34: =D34 -> 45785 | F34: 196 | G34: 800 | H34: =IFERROR(F34/G34,"") -> 0.245 | I34: 5657 | J34: =IFERROR(I34/F34,"") -> 28.862245 | K34: 4391 | L34: =IFERROR(K34/F34,"") -> 22.403061 | M34: =(4000+150+300) -> 4450 | N34: =IFERROR(M34/I34,"") -> 0.78663603 | O34: -1741.99 | P34: =K34 -> 4391 | Q34: =O34+P34 -> 2649.01
A35: 29 | B35: Joe Kay | C35: 5 | D35: 45786 | E35: =D35 -> 45786 | F35: 741 | G35: 700 | H35: =IFERROR(F35/G35,"") -> 1.0585714 | I35: 31671 | J35: =IFERROR(I35/F35,"") -> 42.740891 | K35: 17147 | L35: =IFERROR(K35/F35,"") -> 23.140351 | M35: =(10000+500) -> 10500 | N35: =IFERROR(M35/I35,"") -> 0.33153358 | O35: 10300.4 | P35: =K35 -> 17147 | Q35: =O35+P35 -> 27447.4
A36: 30 | B36: Acraze | C36: 5 | D36: 45787 | E36: =D36 -> 45787 | F36: 500 | G36: 800 | H36: =IFERROR(F36/G36,"") -> 0.625 | I36: 16227 | J36: =IFERROR(I36/F36,"") -> 32.454 | K36: 12848 | L36: =IFERROR(K36/F36,"") -> 25.696 | M36: =(10000+200+200+200) -> 10600 | N36: =IFERROR(M36/I36,"") -> 0.65323227 | O36: 262.87 | P36: =K36 -> 12848 | Q36: =O36+P36 -> 13110.87
A37: 31 | B37: Raveena | C37: 1 | D37: 45788 | E37: =D37 -> 45788 | F37: 326 | G37: 750 | H37: =IFERROR(F37/G37,"") -> 0.43466667 | I37: 13887.75 | J37: =IFERROR(I37/F37,"") -> 42.60046 | K37: 1868.5 | L37: =IFERROR(K37/F37,"") -> 5.7315951 | M37: =(9000+500) -> 9500 | N37: =IFERROR(M37/I37,"") -> 0.68405609 | O37: -3025.89 | P37: =K37 -> 1868.5 | Q37: =O37+P37 -> -1157.39
A38: 32 | B38: A-Trak | C38: 5 | D38: 45419 | E38: =D38 -> 45419 | G38: 750 | H38: =IFERROR(F38/G38,"") -> 0 | J38: =IFERROR(I38/F38,"") | L38: =IFERROR(K38/F38,"") | N38: =IFERROR(M38/I38,"") | P38: =K38 | Q38: =O38+P38 -> 0
A39: 33 | B39: Baroness | C39: 1 | D39: 45794 | E39: =D39 -> 45794 | F39: 518 | G39: 750 | H39: =IFERROR(F39/G39,"") -> 0.69066667 | I39: 18635 | J39: =IFERROR(I39/F39,"") -> 35.974903 | K39: 7087 | L39: =IFERROR(K39/F39,"") -> 13.681467 | M39: =(8254.66+250) -> 8504.66 | N39: =IFERROR(M39/I39,"") -> 0.456381 | O39: 5443.21 | P39: =K39 -> 7087 | Q39: =O39+P39 -> 12530.21
A40: 34 | B40: Max Styler | C40: 5 | D40: 45800 | E40: =D40 -> 45800 | F40: 932 | G40: 800 | H40: =IFERROR(F40/G40,"") -> 1.165 | I40: 42057.5 | J40: =IFERROR(I40/F40,"") -> 45.126073 | K40: 31398 | L40: =IFERROR(K40/F40,"") -> 33.688841 | M40: =(12500+2200+400) -> 15100 | N40: =IFERROR(M40/I40,"") -> 0.35903228 | O40: 13560.94 | P40: =K40 -> 31398 | Q40: =O40+P40 -> 44958.94
A41: 35 | B41: Defected | C41: 5 | D41: 45801 | E41: =D41 -> 45801 | F41: 1005 | G41: 800 | H41: =IFERROR(F41/G41,"") -> 1.25625 | I41: 56166 | J41: =IFERROR(I41/F41,"") -> 55.886567 | K41: 21795 | L41: =IFERROR(K41/F41,"") -> 21.686567 | M41: =3500+10000 -> 13500 | N41: =IFERROR(M41/I41,"") -> 0.24035894 | O41: 25317.24 | P41: =K41 -> 21795 | Q41: =O41+P41 -> 47112.24
A42: 36 | B42: Odd Mob | C42: 5 | D42: 45802 | E42: =D42 -> 45802 | F42: 987 | G42: 750 | H42: =IFERROR(F42/G42,"") -> 1.316 | I42: 53726 | J42: =IFERROR(I42/F42,"") -> 54.433637 | K42: 23002 | L42: =IFERROR(K42/F42,"") -> 23.304965 | M42: =(17500+2500+300+400) -> 20700 | N42: =IFERROR(M42/I42,"") -> 0.38528831 | O42: 21150.76 | P42: =K42 -> 23002 | Q42: =O42+P42 -> 44152.76
A43: 37 | B43: Repopulate Mars | C43: 5 | D43: 45803 | E43: =D43 -> 45803 | F43: 624 | G43: 750 | H43: =IFERROR(F43/G43,"") -> 0.832 | I43: 27651 | J43: =IFERROR(I43/F43,"") -> 44.3125 | K43: 12348 | L43: =IFERROR(K43/F43,"") -> 19.788462 | M43: =(5000+5000+5000+1000+600) -> 16600 | N43: =IFERROR(M43/I43,"") -> 0.60033995 | O43: 2504.97 | P43: =K43 -> 12348 | Q43: =O43+P43 -> 14852.97
A44: 38 | B44: Curtis Dalston | C44: 6 | D44: 45807 | E44: =D44 -> 45807 | F44: 700 | G44: 830 | H44: =IFERROR(F44/G44,"") -> 0.84337349 | I44: 4902 | J44: =IFERROR(I44/F44,"") -> 7.0028571 | K44: 11816 | L44: =IFERROR(K44/F44,"") -> 16.88 | M44: 0 | N44: =IFERROR(M44/I44,"") -> 0 | O44: 2609 | P44: =K44 -> 11816 | Q44: =O44+P44 -> 14425
A45: 39 | B45: Sander Kleinberg | C45: 5 | D45: 45814 | E45: =D45 -> 45814 | G45: 850 | H45: =IFERROR(F45/G45,"") -> 0 | J45: =IFERROR(I45/F45,"") | L45: =IFERROR(K45/F45,"") | N45: =IFERROR(M45/I45,"") | P45: =K45 | Q45: =O45+P45 -> 0
A46: 40 | B46: Glitterbox | C46: 5 | D46: 45815 | E46: =D46 -> 45815 | F46: 371 | G46: 850 | H46: =IFERROR(F46/G46,"") -> 0.43647059 | I46: 13133.25 | J46: =IFERROR(I46/F46,"") -> 35.399596 | K46: 11367 | L46: =IFERROR(K46/F46,"") -> 30.638814 | M46: =(8000+1500+1000+500+1500+1500) -> 14000 | N46: =IFERROR(M46/I46,"") -> 1.0659966 | O46: -9856.88 | P46: =K46 -> 11367 | Q46: =O46+P46 -> 1510.12
A47: 41 | B47: Geordie Kieffer | C47: 1 | D47: 45816 | E47: =D47 -> 45816 | F47: 158 | G47: 800 | H47: =IFERROR(F47/G47,"") -> 0.1975 | I47: 6922 | J47: =IFERROR(I47/F47,"") -> 43.810127 | K47: 2147 | L47: =IFERROR(K47/F47,"") -> 13.588608 | M47: =(4000+500) -> 4500 | N47: =IFERROR(M47/I47,"") -> 0.65010113 | O47: -1991.56 | P47: =K47 -> 2147 | Q47: =O47+P47 -> 155.44
A48: 42 | B48: Lords of Acid | C48: 1 | D48: 45817 | E48: =D48 -> 45817 | F48: 534 | G48: 800 | H48: =IFERROR(F48/G48,"") -> 0.6675 | I48: 21962 | J48: =IFERROR(I48/F48,"") -> 41.127341 | K48: 6973 | L48: =IFERROR(K48/F48,"") -> 13.058052 | M48: =(8000+3000) -> 11000 | N48: =IFERROR(M48/I48,"") -> 0.50086513 | O48: 5561.9 | P48: =K48 -> 6973 | Q48: =O48+P48 -> 12534.9
A49: 43 | B49: Crusy | C49: 2 | D49: 45821 | E49: =D49 -> 45821 | F49: 60 | G49: 250 | H49: =IFERROR(F49/G49,"") -> 0.24 | I49: 1210 | J49: =IFERROR(I49/F49,"") -> 20.166667 | K49: 1238 | L49: =IFERROR(K49/F49,"") -> 20.633333 | M49: =(2000+150+100+100) -> 2350 | N49: =IFERROR(M49/I49,"") -> 1.9421488 | O49: -2286.68 | P49: =K49 -> 1238 | Q49: =O49+P49 -> -1048.68
A50: 44 | B50: Caroline Baniewicz | C50: 1 | D50: 45830 | E50: =D50 -> 45830 | F50: 18 | G50: 750 | H50: =IFERROR(F50/G50,"") -> 0.024 | I50: 565.5 | J50: =IFERROR(I50/F50,"") -> 31.416667 | K50: 174 | L50: =IFERROR(K50/F50,"") -> 9.6666667 | M50: =1000 -> 1000 | N50: =IFERROR(M50/I50,"") -> 1.7683466 | O50: -2738 | P50: =K50 -> 174 | Q50: =O50+P50 -> -2564
A51: 45 | B51: Austin Millz | C51: 5 | D51: 45850 | E51: =D51 -> 45850 | F51: 242 | G51: 750 | H51: =IFERROR(F51/G51,"") -> 0.32266667 | I51: 7330.5 | J51: =IFERROR(I51/F51,"") -> 30.291322 | K51: 7314 | L51: =IFERROR(K51/F51,"") -> 30.22314 | M51: =(4500+350+350) -> 5200 | N51: =IFERROR(M51/I51,"") -> 0.70936498 | O51: -803.06 | P51: =K51 -> 7314 | Q51: =O51+P51 -> 6510.94
A52: 46 | B52: Hyaden James | C52: 5 | D52: 45856 | E52: =D52 -> 45856 | F52: 659 | G52: 750 | H52: =IFERROR(F52/G52,"") -> 0.87866667 | I52: 20798 | J52: =IFERROR(I52/F52,"") -> 31.559939 | K52: 18263 | L52: =IFERROR(K52/F52,"") -> 27.713202 | M52: =(10000+200+200) -> 10400 | N52: =IFERROR(M52/I52,"") -> 0.50004808 | P52: =K52 -> 18263 | Q52: =O52+P52 -> 18263
A53: 47 | B53: Afrobeats to the World | C53: 1 | D53: 45857 | E53: =D53 -> 45857 | F53: 465 | G53: 750 | H53: =IFERROR(F53/G53,"") -> 0.62 | I53: 12493.5 | J53: =IFERROR(I53/F53,"") -> 26.867742 | K53: 8045 | L53: =IFERROR(K53/F53,"") -> 17.301075 | M53: =8924 -> 8924 | N53: =IFERROR(M53/I53,"") -> 0.71429143 | O53: 512.76 | P53: =K53 -> 8045 | Q53: =O53+P53 -> 8557.76
A54: 48 | B54: KenTheMan | C54: 1 | D54: 45858 | E54: =D54 -> 45858 | F54: 750 | G54: 700 | H54: =IFERROR(F54/G54,"") -> 1.0714286 | I54: 27556.25 | J54: =IFERROR(I54/F54,"") -> 36.741667 | K54: 8431 | L54: =IFERROR(K54/F54,"") -> 11.241333 | M54: =11380.93 -> 11380.93 | N54: =IFERROR(M54/I54,"") -> 0.41300721 | P54: =K54 -> 8431 | Q54: =O54+P54 -> 8431
A55: 49 | B55: New Bomb Turks | C55: 1 | D55: 45863 | E55: =D55 -> 45863 | F55: 188 | G55: 800 | H55: =IFERROR(F55/G55,"") -> 0.235 | I55: 6061 | J55: =IFERROR(I55/F55,"") -> 32.239362 | K55: 4192 | L55: =IFERROR(K55/F55,"") -> 22.297872 | M55: =(5000+1500+250+200) -> 6950 | N55: =IFERROR(M55/I55,"") -> 1.1466755 | O55: -4651.74 | P55: =K55 -> 4192 | Q55: =O55+P55 -> -459.74
A56: 50 | B56: Kickstand Productions | C56: 6 | D56: 45865 | E56: =D56 -> 45865 | F56: 554 | G56: 800 | H56: =IFERROR(F56/G56,"") -> 0.6925 | I56: 19384.75 | J56: =IFERROR(I56/F56,"") -> 34.990523 | K56: 3017 | L56: =IFERROR(K56/F56,"") -> 5.4458484 | M56: 12343 | N56: =IFERROR(M56/I56,"") -> 0.63673764 | O56: 3570.6 | P56: =K56 -> 3017 | Q56: =O56+P56 -> 6587.6
A57: 51 | B57: Spafford | C57: 1 | D57: 45872 | E57: =D57 -> 45872 | F57: 226 | G57: 850 | H57: =IFERROR(F57/G57,"") -> 0.26588235 | I57: 6800.51 | J57: =IFERROR(I57/F57,"") -> 30.090752 | K57: 5417 | L57: =IFERROR(K57/F57,"") -> 23.969027 | M57: =(4000+500) -> 4500 | N57: =IFERROR(M57/I57,"") -> 0.66171508 | O57: 2049.3 | P57: =K57 -> 5417 | Q57: =O57+P57 -> 7466.3
A58: 52 | B58: Wesghost | C58: 1 | D58: 45878 | E58: =D58 -> 45878 | F58: 280 | G58: 800 | H58: =IFERROR(F58/G58,"") -> 0.35 | I58: 14711 | J58: =IFERROR(I58/F58,"") -> 52.539286 | K58: 2684 | L58: =IFERROR(K58/F58,"") -> 9.5857143 | M58: =3000+500 -> 3500 | N58: =IFERROR(M58/I58,"") -> 0.2379172 | O58: 1967.01 | P58: =K58 -> 2684 | Q58: =O58+P58 -> 4651.01
A59: 53 | B59: R&B Bangers | C59: 6 | D59: 45885 | E59: =D59 -> 45885 | F59: 45 | G59: 750 | H59: =IFERROR(F59/G59,"") -> 0.06 | I59: 6228.5 | J59: =IFERROR(I59/F59,"") -> 138.41111 | K59: 10215 | L59: =IFERROR(K59/F59,"") -> 227 | M59: 1185 | N59: =IFERROR(M59/I59,"") -> 0.19025448 | O59: 3065.94 | P59: =K59 -> 10215 | Q59: =O59+P59 -> 13280.94
A60: 54 | B60: Obi's House | C60: 6 | D60: 45886 | E60: =D60 -> 45886 | F60: 192 | G60: 750 | H60: =IFERROR(F60/G60,"") -> 0.256 | I60: 13331.5 | J60: =IFERROR(I60/F60,"") -> 69.434896 | K60: 11824 | L60: =IFERROR(K60/F60,"") -> 61.583333 | M60: =7553+288 -> 7841 | N60: =IFERROR(M60/I60,"") -> 0.58815587 | O60: 3079.51 | P60: =K60 -> 11824 | Q60: =O60+P60 -> 14903.51
A61: 55 | B61: Simon Doty | C61: 5 | D61: 45892 | E61: =D61 -> 45892 | F61: 150 | G61: 750 | H61: =IFERROR(F61/G61,"") -> 0.2 | I61: 3619.75 | J61: =IFERROR(I61/F61,"") -> 24.131667 | K61: 3404 | L61: =IFERROR(K61/F61,"") -> 22.693333 | M61: -336.48 | N61: =IFERROR(M61/I61,"") -> -0.092956696 | O61: =2000+200+150 -> 2350 | P61: =K61 -> 3404 | Q61: =O61+P61 -> 5754
A62: 56 | B62: DJ Funk Benefit | D62: 45899 | E62: =D62 -> 45899 | F62: 85 | G62: 750 | H62: =IFERROR(F62/G62,"") -> 0.11333333 | I62: 1792.62 | J62: =IFERROR(I62/F62,"") -> 21.089647 | K62: 1720 | L62: =IFERROR(K62/F62,"") -> 20.235294 | M62: 680 | N62: =IFERROR(M62/I62,"") -> 0.37933304 | O62: -286.92 | P62: =K62 -> 1720 | Q62: =O62+P62 -> 1433.08
A63: 57 | B63: Spencer Brown | C63: 5 | D63: 45905 | E63: =D63 -> 45905 | F63: 82 | G63: 250 | H63: =IFERROR(F63/G63,"") -> 0.328 | I63: 1477.75 | J63: =IFERROR(I63/F63,"") -> 18.021341 | K63: 1759 | L63: =IFERROR(K63/F63,"") -> 21.45122 | M63: =(2500+200) -> 2700 | N63: =IFERROR(M63/I63,"") -> 1.827102 | O63: -2976.92 | P63: =K63 -> 1759 | Q63: =O63+P63 -> -1217.92
A64: 58 | B64: Russian Circles | C64: 1 | D64: 45911 | E64: =D64 -> 45911 | F64: 287 | G64: 250 | H64: =IFERROR(F64/G64,"") -> 1.148 | I64: 9586.93 | J64: =IFERROR(I64/F64,"") -> 33.403937 | K64: 3829 | L64: =IFERROR(K64/F64,"") -> 13.341463 | M64: =(5000+1500) -> 6500 | N64: =IFERROR(M64/I64,"") -> 0.67800641 | O64: -793.97 | P64: =K64 -> 3829 | Q64: =O64+P64 -> 3035.03
A65: 59 | B65: Restricted | C65: 2 | D65: 45913 | E65: =D65 -> 45913 | F65: 593 | G65: 750 | H65: =IFERROR(F65/G65,"") -> 0.79066667 | I65: 18591.31 | J65: =IFERROR(I65/F65,"") -> 31.351282 | K65: 10332 | L65: =IFERROR(K65/F65,"") -> 17.423271 | M65: =(4000+1500+150) -> 5650 | N65: =IFERROR(M65/I65,"") -> 0.30390543 | O65: 7158.91 | P65: =K65 -> 10332 | Q65: =O65+P65 -> 17490.91
A66: 60 | B66: Marsh | C66: 5 | D66: 45926 | E66: =D66 -> 45926 | F66: 288 | G66: 700 | H66: =IFERROR(F66/G66,"") -> 0.41142857 | I66: 6937 | J66: =IFERROR(I66/F66,"") -> 24.086806 | K66: 7413 | L66: =IFERROR(K66/F66,"") -> 25.739583 | M66: =(4000+200+200) -> 4400 | N66: =IFERROR(M66/I66,"") -> 0.63427995 | O66: -321.97 | P66: =K66 -> 7413 | Q66: =O66+P66 -> 7091.03
A67: 61 | B67: Club 1 BD | C67: 1 | D67: 45927 | E67: =D67 -> 45927 | F67: 802 | G67: 750 | H67: =IFERROR(F67/G67,"") -> 1.0693333 | I67: 28781.75 | J67: =IFERROR(I67/F67,"") -> 35.887469 | K67: 11593 | L67: =IFERROR(K67/F67,"") -> 14.455112 | M67: =18736 -> 18736 | N67: =IFERROR(M67/I67,"") -> 0.65096806 | O67: 7310.37 | P67: =K67 -> 11593 | Q67: =O67+P67 -> 18903.37
A68: 62 | B68: Anamanaguchi | C68: 6 | D68: 45933 | E68: =D68 -> 45933 | F68: 328 | G68: 800 | H68: =IFERROR(F68/G68,"") -> 0.41 | I68: 11391.56 | J68: =IFERROR(I68/F68,"") -> 34.730366 | K68: 4375 | L68: =IFERROR(K68/F68,"") -> 13.338415 | M68: =(7249.75) -> 7249.75 | N68: =IFERROR(M68/I68,"") -> 0.63641415 | O68: 1558.58 | P68: =K68 -> 4375 | Q68: =O68+P68 -> 5933.58
A69: 63 | B69: Torren Foot/Airwolf Paradise | C69: 5 | D69: 45934 | E69: =D69 -> 45934 | F69: 186 | G69: 800 | H69: =IFERROR(F69/G69,"") -> 0.2325 | I69: 4936.75 | J69: =IFERROR(I69/F69,"") -> 26.541667 | K69: 4430 | L69: =IFERROR(K69/F69,"") -> 23.817204 | M69: =(3000+150+150) -> 3300 | N69: =IFERROR(M69/I69,"") -> 0.66845597 | O69: -1108.11 | P69: =K69 -> 4430 | Q69: =O69+P69 -> 3321.89
A70: 64 | B70: Pixel Grip | C70: 1 | D70: 45939 | E70: =D70 -> 45939 | F70: 340 | G70: 750 | H70: =IFERROR(F70/G70,"") -> 0.45333333 | I70: 8483.5 | J70: =IFERROR(I70/F70,"") -> 24.951471 | K70: 4084 | L70: =IFERROR(K70/F70,"") -> 12.011765 | M70: =3500+500 -> 4000 | N70: =IFERROR(M70/I70,"") -> 0.47150351 | O70: -475.58 | P70: =K70 -> 4084 | Q70: =O70+P70 -> 3608.42
A71: 65 | B71: Dombresky | C71: 5 | D71: 45940 | E71: =D71 -> 45940 | F71: 770 | G71: 750 | H71: =IFERROR(F71/G71,"") -> 1.0266667 | I71: 28177.25 | J71: =IFERROR(I71/F71,"") -> 36.593831 | K71: 20068 | L71: =IFERROR(K71/F71,"") -> 26.062338 | M71: =(10000+250+250+2000+200) -> 12700 | N71: =IFERROR(M71/I71,"") -> 0.45071822 | O71: 5096.45 | P71: =K71 -> 20068 | Q71: =O71+P71 -> 25164.45
A72: 66 | B72: Sultan + Shepard | C72: 5 | D72: 45941 | E72: =D72 -> 45941 | F72: 494 | G72: 700 | H72: =IFERROR(F72/G72,"") -> 0.70571429 | I72: 14594 | J72: =IFERROR(I72/F72,"") -> 29.54251 | K72: 8867 | L72: =IFERROR(K72/F72,"") -> 17.949393 | M72: =(7500+200+200) -> 7900 | N72: =IFERROR(M72/I72,"") -> 0.54131835 | O72: 3378.5 | P72: =K72 -> 8867 | Q72: =O72+P72 -> 12245.5
A73: 67 | B73: Cuco | C73: 1 | D73: 45946 | E73: =D73 -> 45946 | F73: 750 | G73: 800 | H73: =IFERROR(F73/G73,"") -> 0.9375 | I73: 30229 | J73: =IFERROR(I73/F73,"") -> 40.305333 | K73: 3557 | L73: =IFERROR(K73/F73,"") -> 4.7426667 | M73: =10000 -> 10000 | N73: =IFERROR(M73/I73,"") -> 0.33080816 | O73: 5799.12 | P73: =K73 -> 3557 | Q73: =O73+P73 -> 9356.12
A74: 68 | B74: Pretty Pink | C74: 2 | D74: 45948 | E74: =D74 -> 45948 | F74: 82 | G74: 800 | H74: =IFERROR(F74/G74,"") -> 0.1025 | I74: 2010.9 | J74: =IFERROR(I74/F74,"") -> 24.523171 | K74: 1551 | L74: =IFERROR(K74/F74,"") -> 18.914634 | M74: =(3500+300+200-1000) -> 3000 | N74: =IFERROR(M74/I74,"") -> 1.4918693 | O74: -2788.24 | P74: =K74 -> 1551 | Q74: =O74+P74 -> -1237.24
A75: 69 | B75: Bonnie x Clyde | C75: 5 | D75: 45954 | E75: =D75 -> 45954 | F75: 293 | G75: 650 | H75: =IFERROR(F75/G75,"") -> 0.45076923 | I75: 8150 | J75: =IFERROR(I75/F75,"") -> 27.8157 | K75: 8746 | L75: =IFERROR(K75/F75,"") -> 29.849829 | M75: =(4000+200) -> 4200 | N75: =IFERROR(M75/I75,"") -> 0.51533742 | O75: -1298.89 | P75: =K75 -> 8746 | Q75: =O75+P75 -> 7447.11
A76: 70 | B76: Skrilla | C76: 1 | D76: 45957 | E76: =D76 -> 45957 | F76: 121 | G76: 800 | H76: =IFERROR(F76/G76,"") -> 0.15125 | I76: 3384 | J76: =IFERROR(I76/F76,"") -> 27.966942 | K76: 1090 | L76: =IFERROR(K76/F76,"") -> 9.0082645 | M76: =3500+250 -> 3750 | N76: =IFERROR(M76/I76,"") -> 1.108156 | O76: 2951.1 | P76: =K76 -> 1090 | Q76: =O76+P76 -> 4041.1
A77: 71 | B77: Chezile | C77: 1 | D77: 45961 | E77: =D77 -> 45961 | F77: 217 | G77: 800 | H77: =IFERROR(F77/G77,"") -> 0.27125 | I77: 6677.25 | J77: =IFERROR(I77/F77,"") -> 30.770737 | K77: 315 | L77: =IFERROR(K77/F77,"") -> 1.4516129 | M77: =4500+500 -> 5000 | N77: =IFERROR(M77/I77,"") -> 0.74881126 | O77: -1412.71 | P77: =K77 -> 315 | Q77: =O77+P77 -> -1097.71
A78: 72 | B78: Essel | C78: 2 | D78: 45962 | E78: =D78 -> 45962 | F78: 75 | G78: 750 | H78: =IFERROR(F78/G78,"") -> 0.1 | I78: 2041.25 | J78: =IFERROR(I78/F78,"") -> 27.216667 | K78: 1689 | L78: =IFERROR(K78/F78,"") -> 22.52 | M78: =(3500+300+200) -> 4000 | N78: =IFERROR(M78/I78,"") -> 1.9595836 | O78: -3766.74 | P78: =K78 -> 1689 | Q78: =O78+P78 -> -2077.74
A79: 73 | B79: the Olllam | C79: 1 | D79: 45968 | E79: =D79 -> 45968 | F79: 271 | G79: 750 | H79: =IFERROR(F79/G79,"") -> 0.36133333 | I79: 9070.37 | J79: =IFERROR(I79/F79,"") -> 33.47 | K79: 3137 | L79: =IFERROR(K79/F79,"") -> 11.575646 | M79: =5500+800 -> 6300 | N79: =IFERROR(M79/I79,"") -> 0.69456924 | O79: -1028.97 | P79: =K79 -> 3137 | Q79: =O79+P79 -> 2108.03
A80: 74 | B80: Dogs in a Pile | C80: 1 | D80: 45969 | E80: =D80 -> 45969 | F80: 320 | G80: 750 | H80: =IFERROR(F80/G80,"") -> 0.42666667 | I80: 9939.26 | J80: =IFERROR(I80/F80,"") -> 31.060188 | K80: 5801 | L80: =IFERROR(K80/F80,"") -> 18.128125 | M80: =5000+750 -> 5750 | N80: =IFERROR(M80/I80,"") -> 0.57851389 | O80: 216.57 | P80: =K80 -> 5801 | Q80: =O80+P80 -> 6017.57
A81: 75 | B81: Lotus | C81: 1 | D81: 45975 | E81: =D81 -> 45975 | F81: 531 | G81: 800 | H81: =IFERROR(F81/G81,"") -> 0.66375 | I81: 19040 | J81: =IFERROR(I81/F81,"") -> 35.856874 | K81: 12703 | L81: =IFERROR(K81/F81,"") -> 23.922787 | M81: =10000 -> 10000 | N81: =IFERROR(M81/I81,"") -> 0.52521008 | O81: 4353.15 | P81: =K81 -> 12703 | Q81: =O81+P81 -> 17056.15
A82: 76 | B82: Only Fire | C82: 1 | D82: 45976 | E82: =D82 -> 45976 | F82: 89 | G82: 800 | H82: =IFERROR(F82/G82,"") -> 0.11125 | I82: 1875 | J82: =IFERROR(I82/F82,"") -> 21.067416 | K82: 1907 | L82: =IFERROR(K82/F82,"") -> 21.426966 | M82: =3000+300+300 -> 3600 | N82: =IFERROR(M82/I82,"") -> 1.92 | O82: 3447.83 | P82: =K82 -> 1907 | Q82: =O82+P82 -> 5354.83
A83: 77 | B83: Curbi | C83: 2 | D83: 45981 | E83: =D83 -> 45981 | F83: 114 | G83: 750 | H83: =IFERROR(F83/G83,"") -> 0.152 | I83: 2524.75 | J83: =IFERROR(I83/F83,"") -> 22.14693 | K83: 4316 | L83: =IFERROR(K83/F83,"") -> 37.859649 | M83: =2500+200+300+150 -> 3150 | N83: =IFERROR(M83/I83,"") -> 1.2476483 | O83: -3282.13 | P83: =K83 -> 4316 | Q83: =O83+P83 -> 1033.87
A84: 78 | B84: Joel Corry | C84: 5 | D84: 45982 | E84: =D84 -> 45982 | F84: 234 | G84: 800 | H84: =IFERROR(F84/G84,"") -> 0.2925 | I84: 6457.5 | J84: =IFERROR(I84/F84,"") -> 27.596154 | K84: 6506 | L84: =IFERROR(K84/F84,"") -> 27.803419 | M84: =5000+200+200 -> 5400 | N84: =IFERROR(M84/I84,"") -> 0.83623693 | O84: -3152 | P84: =K84 -> 6506 | Q84: =O84+P84 -> 3354
A85: 79 | B85: Nils Hoffman | C85: 5 | D85: 45983 | E85: =D85 -> 45983 | F85: 191 | G85: 750 | H85: =IFERROR(F85/G85,"") -> 0.25466667 | I85: 4854 | J85: =IFERROR(I85/F85,"") -> 25.413613 | K85: 4136 | L85: =IFERROR(K85/F85,"") -> 21.65445 | M85: =2500+200+200 -> 2900 | N85: =IFERROR(M85/I85,"") -> 0.59744541 | O85: -1044.96 | P85: =K85 -> 4136 | Q85: =O85+P85 -> 3091.04
A86: 80 | B86: Tony Romera | C86: 2 | D86: 45989 | E86: =D86 -> 45989 | F86: 82 | G86: 800 | H86: =IFERROR(F86/G86,"") -> 0.1025 | I86: 2572.87 | J86: =IFERROR(I86/F86,"") -> 31.376463 | K86: 2363 | L86: =IFERROR(K86/F86,"") -> 28.817073 | M86: =(2500+2500+2500) -> 7500 | N86: =IFERROR(M86/I86,"") -> 2.9150326 | O86: -8190.62 | P86: =K86 -> 2363 | Q86: =O86+P86 -> -5827.62
A87: 81 | B87: Black V Neck | C87: 5 | D87: 45990 | E87: =D87 -> 45990 | F87: 125 | G87: 800 | H87: =IFERROR(F87/G87,"") -> 0.15625 | I87: 2629 | J87: =IFERROR(I87/F87,"") -> 21.032 | K87: 2843 | L87: =IFERROR(K87/F87,"") -> 22.744 | M87: =3000+100+100+100+100 -> 3400 | N87: =IFERROR(M87/I87,"") -> 1.2932674 | O87: -2885.86 | P87: =K87 -> 2843 | Q87: =O87+P87 -> -42.86
A88: 82 | B88: Masceal | C88: 1 | D88: 45991 | E88: =D88 -> 45991 | F88: 191 | G88: 800 | H88: =IFERROR(F88/G88,"") -> 0.23875 | I88: 6030.5 | J88: =IFERROR(I88/F88,"") -> 31.573298 | K88: 2167 | L88: =IFERROR(K88/F88,"") -> 11.34555 | M88: =3218.8 -> 3218.8 | N88: =IFERROR(M88/I88,"") -> 0.53375342 | O88: -969.86 | P88: =K88 -> 2167 | Q88: =O88+P88 -> 1197.14
A89: 83 | B89: Darude | C89: 5 | D89: 45997 | E89: =D89 -> 45997 | F89: 677 | G89: 750 | H89: =IFERROR(F89/G89,"") -> 0.90266667 | I89: 20064.5 | J89: =IFERROR(I89/F89,"") -> 29.637371 | K89: 17342 | L89: =IFERROR(K89/F89,"") -> 25.615953 | M89: =5000+200+200 -> 5400 | N89: =IFERROR(M89/I89,"") -> 0.26913205 | O89: 7481.13 | P89: =K89 -> 17342 | Q89: =O89+P89 -> 24823.13
A90: 84 | B90: Ghost Note | C90: 1 | D90: 45999 | E90: =D90 -> 45999 | F90: 215 | G90: 750 | H90: =IFERROR(F90/G90,"") -> 0.28666667 | I90: 6341.25 | J90: =IFERROR(I90/F90,"") -> 29.494186 | K90: 2388 | L90: =IFERROR(K90/F90,"") -> 11.106977 | M90: =(4000+500) -> 4500 | N90: =IFERROR(M90/I90,"") -> 0.70963927 | O90: -1266.05 | P90: =K90 -> 2388 | Q90: =O90+P90 -> 1121.95
A91: 85 | B91: Fovos | C91: 2 | D91: 46004 | E91: =D91 -> 46004 | F91: 191 | G91: 800 | H91: =IFERROR(F91/G91,"") -> 0.23875 | I91: 4232.5 | J91: =IFERROR(I91/F91,"") -> 22.159686 | K91: 3068 | L91: =IFERROR(K91/F91,"") -> 16.062827 | M91: =(3500+400+150) -> 4050 | N91: =IFERROR(M91/I91,"") -> 0.95688128 | O91: -2726.17 | P91: =K91 -> 3068 | Q91: =O91+P91 -> 341.83
A92: 86 | B92: Protomatyr | C92: 5 | D92: 46007 | E92: =D92 -> 46007 | F92: 551 | G92: 800 | H92: =IFERROR(F92/G92,"") -> 0.68875 | I92: 18592.49 | J92: =IFERROR(I92/F92,"") -> 33.743176 | K92: 6549 | L92: =IFERROR(K92/F92,"") -> 11.885662 | M92: =(10000+500) -> 10500 | N92: =IFERROR(M92/I92,"") -> 0.56474415 | O92: 3941.72 | P92: =K92 -> 6549 | Q92: =O92+P92 -> 10490.72
A93: 87 | B93: Sam Feldt | C93: 5 | D93: 46011 | E93: =D93 -> 46011 | F93: 203 | G93: 750 | H93: =IFERROR(F93/G93,"") -> 0.27066667 | I93: 6719.5 | J93: =IFERROR(I93/F93,"") -> 33.100985 | K93: 8181 | L93: =IFERROR(K93/F93,"") -> 40.300493 | M93: =12500+200+200 -> 12900 | N93: =IFERROR(M93/I93,"") -> 1.9197857 | O93: -9654.7 | P93: =K93 -> 8181 | Q93: =O93+P93 -> -1473.7
A94: 88 | B94: Mustard Plug | C94: 1 | D94: 46017 | E94: =D94 -> 46017 | F94: 725 | G94: 725 | H94: =IFERROR(F94/G94,"") -> 1 | I94: 18387.56 | J94: =IFERROR(I94/F94,"") -> 25.362152 | K94: 11799 | L94: =IFERROR(K94/F94,"") -> 16.274483 | M94: =8184.48+850+500+250+250 -> 10034.48 | N94: =IFERROR(M94/I94,"") -> 0.54572113 | O94: 4490.66 | P94: =K94 -> 11799 | Q94: =O94+P94 -> 16289.66
A95: 89 | B95: Habstrakt | C95: 5 | D95: 46022 | E95: =D95 -> 46022 | F95: 754 | G95: 800 | H95: =IFERROR(F95/G95,"") -> 0.9425 | I95: 28019.5 | J95: =IFERROR(I95/F95,"") -> 37.161141 | K95: 21170 | L95: =IFERROR(K95/F95,"") -> 28.076923 | M95: =(10000+1000+1000+400) -> 12400 | N95: =IFERROR(M95/I95,"") -> 0.44254894 | O95: 8143.95 | P95: =K95 -> 21170 | Q95: =O95+P95 -> 29313.95
A96: 90 | D96: 45615 | E96: =D96 -> 45615 | G96: 750 | H96: =IFERROR(F96/G96,"") -> 0 | J96: =IFERROR(I96/F96,"") | L96: =IFERROR(K96/F96,"") | N96: =IFERROR(M96/I96,"") | P96: =K96 | Q96: =O96+P96 -> 0
A97: 91 | D97: 45618 | E97: =D97 -> 45618 | G97: 800 | H97: =IFERROR(F97/G97,"") -> 0 | J97: =IFERROR(I97/F97,"") | L97: =IFERROR(K97/F97,"") | N97: =IFERROR(M97/I97,"") | P97: =K97 | Q97: =O97+P97 -> 0
A98: 92 | D98: 45619 | E98: =D98 -> 45619 | G98: 800 | H98: =IFERROR(F98/G98,"") -> 0 | J98: =IFERROR(I98/F98,"") | L98: =IFERROR(K98/F98,"") | N98: =IFERROR(M98/I98,"") | P98: =K98 | Q98: =O98+P98 -> 0
A99: 93 | D99: 45625 | E99: =D99 -> 45625 | G99: 800 | H99: =IFERROR(F99/G99,"") -> 0 | J99: =IFERROR(I99/F99,"") | L99: =IFERROR(K99/F99,"") | N99: =IFERROR(M99/I99,"") | P99: =K99 | Q99: =O99+P99 -> 0
A100: 94 | D100: 45626 | E100: =D100 -> 45626 | G100: 800 | H100: =IFERROR(F100/G100,"") -> 0 | J100: =IFERROR(I100/F100,"") | L100: =IFERROR(K100/F100,"") | N100: =IFERROR(M100/I100,"") | P100: =K100 | Q100: =O100+P100 -> 0
A101: 95 | D101: 45627 | E101: =D101 -> 45627 | G101: 750 | H101: =IFERROR(F101/G101,"") -> 0 | J101: =IFERROR(I101/F101,"") | L101: =IFERROR(K101/F101,"") | N101: =IFERROR(M101/I101,"") | P101: =K101 | Q101: =O101+P101 -> 0
...

Sheet Magic Stick-by Promoter
B2: ***MAGIC STICK RESULTS*** | O2: MAGIC STICK TOTALS | S2: PROMOTER PER-SHOW AVERAGES
B3: Name | D3: Shows | E3: Shows & Rentals | F3: Tickets Sold | G3: Venue Capacity | H3: Capacity Rate | I3: Gross Ticket Revenue | J3: Avg. Ticket Price (including TW rebate) | K3: Bar Revenue | L3: Avg sale of alcohol per guest | M3: Band(s) guarantee | N3: % of Gross Ticket Revenue | O3: Gate Settlement Gain/(Loss) | P3: Bar Sales - 100% | Q3: Show Gross Proceeds (before COGS, Labor, & Facility Costs) | R3: % of Total Gross Proceeds | S3: Gate Settlement Gain/(Loss) | T3: Bar Sales - 50% | U3: Show Gross Proceeds (before COGS, Labor, & Facility Costs)
B4: TOTALS | D4: =SUM(D7:D16) -> 0 | E4: =SUM(E7:E16) -> 0 | F4: =SUM(F7:F81) -> 30956 | G4: =SUM(G7:G81) -> 62577 | I4: =SUM(I7:I81) -> 1079142.9 | K4: =SUM(K7:K81) -> 693608.5 | M4: =SUM(M7:M81) -> 594276.39 | N4: =SUM(N7:N81) -> #DIV/0! | O4: =SUM(O7:O81) -> 111503.69 | P4: =SUM(P7:P81) -> 693608.5 | Q4: =SUM(Q7:Q81) -> 805112.19 | R4: =SUM(R7:R81) -> 1
B5: AVERAGES | F5: =F4/D4 -> #DIV/0! | G5: =G4/D4 -> #DIV/0! | H5: =F4/G4 -> 0.49468655 | I5: =I4/D4 -> #DIV/0! | J5: =I4/F4 -> 34.860542 | K5: =K4/E4 -> #DIV/0! | L5: =K4/F4 -> 22.40627 | M5: =M4/D4 -> #DIV/0! | N5: =M4/I4 -> 0.55069293 | O5: =O4/E4 -> #DIV/0! | P5: =P4/E4 -> #DIV/0! | Q5: =Q4/E4 -> #DIV/0!
A7: 5 | B7: Paxahau - Tom Pattyn | D7: {=COUNTIF('Magic Stick'!C:C,A:A)} -> 0 | E7: {=COUNTIF('Magic Stick'!C:C,A:A)} -> 0 | F7: =SUMIF('Magic Stick'!$C:$C,A:A,'Magic Stick'!$F:$F) -> 17464 | G7: =SUMIF('Magic Stick'!$C:$C,A:A,'Magic Stick'!$G:$G) -> 28685 | H7: =F7/G7 -> 0.60881994 | I7: =SUMIF('Magic Stick'!$C:$C,A:A,'Magic Stick'!$I:$I) -> 639925.49 | J7: =I7/F7 -> 36.64255 | K7: =SUMIF('Magic Stick'!$C:$C,A:A,'Magic Stick'!$K:$K) -> 446372 | L7: =K7/F7 -> 25.559551 | M7: =SUMIF('Magic Stick'!$C:$C,A:A,'Magic Stick'!$M:$M) -> 322205.52 | N7: =M7/I7 -> 0.50350474 | O7: =SUMIF('Magic Stick'!$C:$C,A:A,'Magic Stick'!$O:$O) -> 94869.37 | P7: =K7 -> 446372 | Q7: =O7+P7 -> 541241.37 | R7: =Q7/$Q$4 -> 0.67225584 | S7: =O7/E7 -> #DIV/0! | T7: =P7/E7 -> #DIV/0! | U7: =S7+T7 -> #DIV/0!
A8: 1 | B8: In-House - Zach | D8: {=COUNTIF('Magic Stick'!C:C,A:A)} -> 0 | E8: {=COUNTIF('Magic Stick'!C:C,A:A)} -> 0 | F8: =SUMIF('Magic Stick'!$C:$C,A:A,'Magic Stick'!$F:$F) -> 10711 | G8: =SUMIF('Magic Stick'!$C:$C,A:A,'Magic Stick'!$G:$G) -> 22039 | H8: =F8/G8 -> 0.48600209 | I8: =SUMIF('Magic Stick'!$C:$C,A:A,'Magic Stick'!$I:$I) -> 365844.38 | J8: =I8/F8 -> 34.15595 | K8: =SUMIF('Magic Stick'!$C:$C,A:A,'Magic Stick'!$K:$K) -> 142168.5 | L8: =K8/F8 -> 13.27313 | M8: =SUMIF('Magic Stick'!$C:$C,A:A,'Magic Stick'!$M:$M) -> 208620.87 | N8: =M8/I8 -> 0.57024484 | O8: =SUMIF('Magic Stick'!$C:$C,A:A,'Magic Stick'!$O:$O) -> 32587.81 | P8: =K8 -> 142168.5 | Q8: =O8+P8 -> 174756.31 | R8: =Q8/$Q$4 -> 0.21705833 | S8: =O8/E8 -> #DIV/0! | T8: =P8/E8 -> #DIV/0! | U8: =S8+T8 -> #DIV/0!
A9: 2 | B9: In-House - Brie | D9: {=COUNTIF('Magic Stick'!C:C,A:A)} -> 0 | E9: {=COUNTIF('Magic Stick'!C:C,A:A)} -> 0 | F9: =SUMIF('Magic Stick'!$C:$C,A:A,'Magic Stick'!$F:$F) -> 2781 | G9: =SUMIF('Magic Stick'!$C:$C,A:A,'Magic Stick'!$G:$G) -> 11853 | H9: =F9/G9 -> 0.23462415 | I9: =SUMIF('Magic Stick'!$C:$C,A:A,'Magic Stick'!$I:$I) -> 73373.08 | J9: =I9/F9 -> 26.383704 | K9: =SUMIF('Magic Stick'!$C:$C,A:A,'Magic Stick'!$K:$K) -> 63821 | L9: =K9/F9 -> 22.948939 | M9: =SUMIF('Magic Stick'!$C:$C,A:A,'Magic Stick'!$M:$M) -> 63450 | N9: =M9/I9 -> 0.86475857 | O9: =SUMIF('Magic Stick'!$C:$C,A:A,'Magic Stick'!$O:$O) -> -29837.12 | P9: =K9 -> 63821 | Q9: =O9+P9 -> 33983.88 | R9: =Q9/$Q$4 -> 0.042210117 | S9: =O9/E9 -> #DIV/0! | T9: =P9/E9 -> #DIV/0! | U9: =S9+T9 -> #DIV/0!
A10: 8 | B10: Further Frequencies | D10: {=COUNTIF('Magic Stick'!C:C,A:A)} -> 0 | E10: {=COUNTIF('Magic Stick'!C:C,A:A)} -> 0 | F10: =SUMIF('Magic Stick'!$C:$C,A:A,'Magic Stick'!$F:$F) -> 0 | G10: =SUMIF('Magic Stick'!$C:$C,A:A,'Magic Stick'!$G:$G) -> 0 | H10: =F10/G10 -> #DIV/0! | I10: =SUMIF('Magic Stick'!$C:$C,A:A,'Magic Stick'!$I:$I) -> 0 | J10: =I10/F10 -> #DIV/0! | K10: =SUMIF('Magic Stick'!$C:$C,A:A,'Magic Stick'!$K:$K) -> 0 | L10: =K10/F10 -> #DIV/0! | M10: =SUMIF('Magic Stick'!$C:$C,A:A,'Magic Stick'!$M:$M) -> 0 | N10: =M10/I10 -> #DIV/0! | O10: =SUMIF('Magic Stick'!$C:$C,A:A,'Magic Stick'!$O:$O) -> 0 | P10: =K10 -> 0 | Q10: =O10+P10 -> 0 | R10: =Q10/$Q$4 -> 0 | S10: =O10/E10 -> #DIV/0! | T10: =P10/E10 -> #DIV/0! | U10: =S10+T10 -> #DIV/0!
A11: 4 | B11: Good Show - Jason Berry | D11: {=COUNTIF('Magic Stick'!C:C,A:A)} -> 0 | E11: {=COUNTIF('Magic Stick'!C:C,A:A)} -> 0 | F11: =SUMIF('Magic Stick'!$C:$C,A:A,'Magic Stick'!$F:$F) -> 0 | G11: =SUMIF('Magic Stick'!$C:$C,A:A,'Magic Stick'!$G:$G) -> 0 | H11: =F11/G11 -> #DIV/0! | I11: =SUMIF('Magic Stick'!$C:$C,A:A,'Magic Stick'!$I:$I) -> 0 | J11: =I11/F11 -> #DIV/0! | K11: =SUMIF('Magic Stick'!$C:$C,A:A,'Magic Stick'!$K:$K) -> 0 | L11: =K11/F11 -> #DIV/0! | M11: =SUMIF('Magic Stick'!$C:$C,A:A,'Magic Stick'!$M:$M) -> 0 | N11: =M11/I11 -> #DIV/0! | O11: =SUMIF('Magic Stick'!$C:$C,A:A,'Magic Stick'!$O:$O) -> 0 | P11: =K11 -> 0 | Q11: =O11+P11 -> 0 | R11: =Q11/$Q$4 -> 0 | S11: =O11/E11 -> #DIV/0! | T11: =P11/E11 -> #DIV/0! | U11: =S11+T11 -> #DIV/0!
A12: 3 | B12: Black Iris | D12: {=COUNTIF('Magic Stick'!C:C,A:A)} -> 0 | E12: {=COUNTIF('Magic Stick'!C:C,A:A)} -> 0 | F12: =SUMIF('Magic Stick'!$C:$C,A:A,'Magic Stick'!$F:$F) -> 0 | G12: =SUMIF('Magic Stick'!$C:$C,A:A,'Magic Stick'!$G:$G) -> 0 | H12: =F12/G12 -> #DIV/0! | I12: =SUMIF('Magic Stick'!$C:$C,A:A,'Magic Stick'!$I:$I) -> 0 | J12: =I12/F12 -> #DIV/0! | K12: =SUMIF('Magic Stick'!$C:$C,A:A,'Magic Stick'!$K:$K) -> 0 | L12: =K12/F12 -> #DIV/0! | M12: =SUMIF('Magic Stick'!$C:$C,A:A,'Magic Stick'!$M:$M) -> 0 | N12: =M12/I12 -> #DIV/0! | O12: =SUMIF('Magic Stick'!$C:$C,A:A,'Magic Stick'!$O:$O) -> 0 | P12: =K12 -> 0 | Q12: =O12+P12 -> 0 | R12: =Q12/$Q$4 -> 0 | S12: =O12/E12 -> #DIV/0! | T12: =P12/E12 -> #DIV/0! | U12: =S12+T12 -> #DIV/0!
A13: 6 | B13: Rental event | E13: {=COUNTIF('Magic Stick'!C:C,A:A)} -> 0 | K13: =SUMIF('Magic Stick'!$C:$C,A:A,'Magic Stick'!$K:$K) -> 41247 | O13: =SUMIF('Magic Stick'!$C:$C,A:A,'Magic Stick'!$O:$O) -> 13883.63 | P13: =K13 -> 41247 | Q13: =O13+P13 -> 55130.63 | R13: =Q13/$Q$4 -> 0.068475711 | S13: =O13/E13 -> #DIV/0! | T13: =P13/E13 -> #DIV/0! | U13: =S13+T13 -> #DIV/0!
A14: 7 | B14: Party Store co-pro | D14: {=COUNTIF('Magic Stick'!C:C,A:A)} -> 0 | E14: {=COUNTIF('Magic Stick'!C:C,A:A)} -> 0 | F14: =SUMIF('Magic Stick'!$C:$C,A:A,'Magic Stick'!$F:$F) -> 0 | G14: =SUMIF('Magic Stick'!$C:$C,A:A,'Magic Stick'!$G:$G) -> 0 | H14: =F14/G14 -> #DIV/0! | I14: =SUMIF('Magic Stick'!$C:$C,A:A,'Magic Stick'!$I:$I) -> 0 | J14: =I14/F14 -> #DIV/0! | K14: =SUMIF('Magic Stick'!$C:$C,A:A,'Magic Stick'!$K:$K) -> 0 | L14: =K14/F14 -> #DIV/0! | M14: =SUMIF('Magic Stick'!$C:$C,A:A,'Magic Stick'!$M:$M) -> 0 | N14: =M14/I14 -> #DIV/0! | O14: =SUMIF('Magic Stick'!$C:$C,A:A,'Magic Stick'!$O:$O) -> 0 | P14: =K14 -> 0 | Q14: =O14+P14 -> 0 | R14: =Q14/$Q$4 -> 0 | S14: =O14/E14 -> #DIV/0! | T14: =P14/E14 -> #DIV/0! | U14: =S14+T14 -> #DIV/0!
